Workbook
Name CurrentRow: [1]Time!$C$14
Name delete: #REF!
Name delete: #REF!
Name delete: #REF!
Name delete: #REF!
Name delete: #REF!
Name delete: #REF!
Name dlete: [1]Time!#REF!
Name dlete: [1]Time!#REF!
Name dlete: [1]Time!#REF!
Name dlete: [1]Time!#REF!
Name dlete: [1]Time!#REF!
Name dlete: [1]Time!#REF!
Name EndRow: [1]Time!#REF!
Name EndRow: [1]Time!#REF!
Name EndRow: [1]Time!#REF!
Name EndRow: [1]Time!#REF!
Name EndRow: [1]Time!#REF!
Name EndRow: [1]Time!#REF!
Name EndRow: [1]Time!#REF!
Name EndRow: [1]Time!#REF!
Name EndRow: [1]Time!#REF!
Name EndRow: [1]Time!#REF!
Name EndRow: [1]Time!#REF!
Name EndRow: [1]Time!#REF!
Name IsExample: TRUE
Name JobNumber: #REF!
Name JobNumber: #REF!
Name JobNumber: #REF!
Name JobNumber: #REF!
Name JobNumber: 'Job Details'!$A$2
Name JobNumber: #REF!
Name JobNumber: #REF!
Name JobNumber: #REF!
Name JobNumber: #REF!
Name JobNumber: #REF!
Name JobNumber: #REF!
Name JobNumber: #REF!
Name JobNumber: #REF!
Name LeClaire: #REF!
Name LeClaire: #REF!
Name LeClaire: #REF!
Name LeClaire: #REF!
Name LeClaire: #REF!
Name LeClaire: #REF!
Name MacroStatus: [1]Information!$E$8
Name PeriodBegin: [1]Time!$C$5
Name PeriodEnd: [1]Time!$C$6
Name qryJCCategory: 'Job Details'!$A$10:$E$229
Name qryJCExtra: 'Job Details'!$G$10:$I$12
Name qryJCExtra: 'Job List'!#REF!
Name qryJCJob1: 'Job List'!$A$2:$H$215
Name qryJCPhase: 'Job Details'!$K$10:$L$40
Name qryPRCertifiedclass: 'Certified Codes'!$A$2:$D$83
Name qryPREmployee: Employees!$A$2:$I$1725
Name SampleValues: '[1]Sample Values'!$C$6:$C$7,'[1]Sample Values'!$C$10:$C$16
Name Skaar: [1]Time!#REF!
Name Skaar: [1]Time!#REF!
Name Skaar: [1]Time!#REF!
Name Skaar: [1]Time!#REF!

Sheet Master Template (9) JOB
AB1: TIME ENTRY SHEET (Template 9) | AZ1: 42917 | BA1: WEEK ENDING: | BB1: 43673
A2: EE: # | C2: <--Enter Employee # to populate all other info
A3: UNION ID | B3: =IF(ISNA(VLOOKUP($B$2,Employees!$B:$H,4,FALSE)),"",VLOOKUP($B$2,Employees!$B:$H,4,FALSE)) | C3: IMPORT TIME? | D3: x | L3: =BB1-5 -> 43668 | R3: =BB1-4 -> 43669 | X3: =BB1-3 -> 43670 | AD3: =BB1-2 -> 43671 | AJ3: =BB1-1 -> 43672 | AP3: =BB1-0 -> 43673 | AV3: =BB1-6 -> 43667
A4: UNION LOCAL | B4: =IF(ISNA(VLOOKUP($B$2,Employees!$B:$H,5,FALSE)),"",VLOOKUP($B$2,Employees!$B:$H,5,FALSE)) | L4: MON | R4: TUE | X4: WED | AD4: THUR | AJ4: FRI | AP4: SAT | AV4: SUN | BB4: TOTALS
K5: Start
K6: Lunch Out
K7: Lunch In
K8: Stop
K9: Total Hours | L9: =IF(AND(L5>=0,L8>=0),(L6-L5+L8-L7)*24,0) -> 0 | R9: =IF(AND(R5>=0,R8>=0),(R6-R5+R8-R7)*24,0) -> 0 | X9: =IF(AND(X5>=0,X8>=0),(X6-X5+X8-X7)*24,0) -> 0 | AD9: =IF(AND(AD5>=0,AD8>=0),(AD6-AD5+AD8-AD7)*24,0) -> 0 | AJ9: =IF(AND(AJ5>=0,AJ8>=0),(AJ6-AJ5+AJ8-AJ7)*24,0) -> 0 | AP9: =IF(AND(AP5>=0,AP8>=0),(AP6-AP5+AP8-AP7)*24,0) -> 0 | AV9: =IF(AND(AV5>=0,AV8>=0),(AV6-AV5+AV8-AV7)*24,0) -> 0 | BB9: =SUM(L9:BA9) -> 0 | BI9: DO NOT TYPE IN OR DELETE FORMULAS
K10: Time Sheet Hours | L10: =L24+M24+N24 -> 0 | R10: =R24+S24+T24 -> 0 | X10: =X24+Y24+Z24 -> 0 | AD10: =AD24+AE24+AF24 -> 0 | AJ10: =AJ24+AK24+AL24 -> 0 | AP10: =AP24+AQ24+AR24 -> 0 | AV10: =AV24+AW24+AX24 -> 0 | BB10: =SUM(L10:BA10) -> 0 | BI10: OC CERTIFIED IMPORT
C11: FILL JOB# IN FIRST | K11: Difference | L11: =L9-L10 -> 0 | R11: =R9-R10 -> 0 | X11: =X9-X10 -> 0 | AD11: =AD9-AD10 -> 0 | AJ11: =AJ9-AJ10 -> 0 | AP11: =AP9-AP10 -> 0 | AV11: =AV9-AV10 -> 0 | BB11: =BB9-BB10 -> 0 | BI11: =L3 -> 43668 | BO11: =R3 -> 43669 | BU11: =X3 -> 43670 | CA11: =AD3 -> 43671 | CG11: =AJ3 -> 43672 | CM11: =AP3 -> 43673 | CS11: =AV3 -> 43667
A12: IMPORT TIME? | B12: WC CODE | C12: JOB | D12: EXTRA | E12: PHASE | F12: UNION LOCAL | G12: WC STATE | H12: ST | I12: UNION CLASS | J12: Cert Class Form | K12: CERT. CLASS | L12: RT1 | M12: OT1 | N12: DT1 | O12: PD1 | P12: 4D1 | Q12: 4A1 | R12: RT2 | S12: OT2 | T12: DT2 | U12: PD2 | V12: 4D2 | W12: 4A2 | X12: RT3 | Y12: OT3 | Z12: DT3 | AA12: PD3 | AB12: 4D3 | AC12: 4A3 | AD12: RT4 | AE12: OT4 | AF12: DT4 | AG12: PD4 | AH12: 4D4 | AI12: 4A4 | AJ12: RT5 | AK12: OT5 | AL12: DT5 | AM12: PD5 | AN12: 4D5 | AO12: 4A5 | AP12: RT6 | AQ12: OT6 | AR12: DT6 | AS12: PD6 | AT12: 4D6 | AU12: 4A6 | AV12: RT7 | AW12: OT7 | AX12: DT7 | AY12: PD7 | AZ12: 4D7 | BA12: 4A7 | BB12: 1 | BC12: 3 | BD12: 2 | BE12: 4 | BF12: 4D | BG12: 4A | BH12: Total | BI12: COC1.1 | BJ12: COC3.1 | BK12: COC2.1 | BL12: COC2.13 | BM12: COC2.12 | BN12: COC4A.1 | BO12: COC1.2 | BP12: COC3.2 | BQ12: COC2.2 | BR12: COC2.23 | BS12: COC2.22 | BT12: COC4A.2 | BU12: COC1.3 | BV12: COC3.3 | BW12: COC2.3 | BX12: COC2.33 | BY12: COC2.32 | BZ12: COC4A.3 | CA12: COC1.4 | CB12: COC3.4 | CC12: COC2.4 | CD12: COC2.43 | CE12: COC2.42 | CF12: COC4A.4 | CG12: COC1.5 | CH12: COC3.5 | CI12: COC2.5 | CJ12: COC2.53 | CK12: COC2.52 | CL12: COC4A.5 | CM12: COC1.6 | CN12: COC3.6 | CO12: COC2.6 | CP12: COC2.63 | CQ12: COC2.62 | CR12: COC4A.6 | CS12: COC1.7 | CT12: COC3.7 | CU12: COC2.7 | CV12: COC2.72 | CW12: COC2.8 | CX12: COC4A.7
A13: =IF(ISBLANK(C13),"",IF(ISBLANK($D$3),"",$D$3)) | F13: =IF(ISBLANK($B$4),"",$B$4) | J13: =IF($K13=0,"",IF($K13<10,"0"&$K13,$K13)) | BB13: =SUM(AV13,AP13,AJ13,AD13,X13,R13,L13) -> 0 | BC13: =SUM(AW13,AQ13,AK13,AE13,Y13,S13,M13) -> 0 | BD13: =SUM(AX13,AR13,AL13,AF13,Z13,T13,N13) -> 0 | BE13: =SUM(AY13,AS13,AM13,AG13,AA13,U13,O13) -> 0 | BF13: =SUM(AZ13,AT13,AN13,AH13,AB13,V13,P13) -> 0 | BG13: =SUM(BA13,AU13,AO13,AI13,AC13,W13,Q13) -> 0 | BH13: =SUM(TimeSheet34[[#This Row],[1]:[4A]]) -> 0 | BI13: =IF(AND(NOT(ISBLANK($C13)),NOT(ISBLANK($E13)),$A13="x"),IF(L13=0,0,[2]!TSImport("PRTime","","Time_NINE","","Date",$BI$11,"Employee",$B$2,"JCJob",$C13,"JCExtra",$D13,"JCCostCode",$E13,"WCCode",$B13,"WCState",$G13,"State",$H13,"PayID",$BB$12,"Units",L13,"UnionID",$B$3,"UnionLocal",$F13,"UnionClass",$I13,"CertifiedClass",$J13)),0) -> 0 | BJ13: =IF(AND(NOT(ISBLANK($C13)),NOT(ISBLANK($E13)),$A13="x"),IF(M13=0,0,[2]!TSImport("PRTime","","Time_NINE","","Date",$BI$11,"Employee",$B$2,"JCJob",$C13,"JCExtra",$D13,"JCCostCode",$E13,"WCCode",$B13,"WCState",$G13,"State",$H13,"PayID",$BC$12,"Units",M13,"UnionID",$B$3,"UnionLocal",$F13,"UnionClass",$I13,"CertifiedClass",$J13)),0) -> 0 | BK13: =IF(AND(NOT(ISBLANK($C13)),NOT(ISBLANK($E13)),$A13="x"),IF(N13=0,0,[2]!TSImport("PRTime","","Time_NINE","","Date",$BI$11,"Employee",$B$2,"JCJob",$C13,"JCExtra",$D13,"JCCostCode",$E13,"WCCode",$B13,"WCState",$G13,"State",$H13,"PayID",$BD$12,"Units",N13,"UnionID",$B$3,"UnionLocal",$F13,"UnionClass",$I13,"CertifiedClass",$J13)),0) -> 0 | BL13: =IF(AND(NOT(ISBLANK($C13)),NOT(ISBLANK($E13)),$A13="x"),IF(O13=0,0,[2]!TSImport("PRTime","","Time_NINE","","Date",$BI$11,"Employee",$B$2,"JCJob",$C13,"JCExtra",$D13,"JCCostCode",$E13,"WCCode",$B13,"WCState",$G13,"State",$H13,"PayID",$BE$12,"Units",O13,"UnionID",$B$3,"UnionLocal",$F13,"UnionClass",$I13,"CertifiedClass",$J13)),0) -> 0 | BM13: =IF(AND(NOT(ISBLANK($C13)),NOT(ISBLANK($E13)),$A13="x"),IF(P13=0,0,[2]!TSImport("PRTime","","Time_NINE","","Date",$BI$11,"Employee",$B$2,"JCJob",$C13,"JCExtra",$D13,"JCCostCode",$E13,"WCCode",$B13,"WCState",$G13,"State",$H13,"PayID",$BF$12,"Units",P13,"UnionID",$B$3,"UnionLocal",$F13,"UnionClass",$I13,"CertifiedClass",$J13)),0) -> 0 | BN13: =IF(AND(NOT(ISBLANK($C13)),NOT(ISBLANK($E13)),$A13="x"),IF(Q13=0,0,[2]!TSImport("PRTime","","Time_NINE","","Date",$BI$11,"Employee",$B$2,"JCJob",$C13,"JCExtra",$D13,"JCCostCode",$E13,"WCCode",$B13,"WCState",$G13,"State",$H13,"PayID",$BG$12,"Units",Q13,"UnionID",$B$3,"UnionLocal",$F13,"UnionClass",$I13,"CertifiedClass",$J13)),0) -> 0 | BO13: =IF(AND(NOT(ISBLANK($C13)),NOT(ISBLANK($E13)),$A13="x"),IF(R13=0,0,[2]!TSImport("PRTime","","Time_NINE","","Date",$BO$11,"Employee",$B$2,"JCJob",$C13,"JCExtra",$D13,"JCCostCode",$E13,"WCCode",$B13,"WCState",$G13,"State",$H13,"PayID",$BB$12,"Units",R13,"UnionID",$B$3,"UnionLocal",$F13,"UnionClass",$I13,"CertifiedClass",$J13)),0) -> 0 | BP13: =IF(AND(NOT(ISBLANK($C13)),NOT(ISBLANK($E13)),$A13="x"),IF(S13=0,0,[2]!TSImport("PRTime","","Time_NINE","","Date",$BO$11,"Employee",$B$2,"JCJob",$C13,"JCExtra",$D13,"JCCostCode",$E13,"WCCode",$B13,"WCState",$G13,"State",$H13,"PayID",$BC$12,"Units",S13,"UnionID",$B$3,"UnionLocal",$F13,"UnionClass",$I13,"CertifiedClass",$J13)),0) -> 0 | BQ13: =IF(AND(NOT(ISBLANK($C13)),NOT(ISBLANK($E13)),$A13="x"),IF(T13=0,0,[2]!TSImport("PRTime","","Time_NINE","","Date",$BO$11,"Employee",$B$2,"JCJob",$C13,"JCExtra",$D13,"JCCostCode",$E13,"WCCode",$B13,"WCState",$G13,"State",$H13,"PayID",$BD$12,"Units",T13,"UnionID",$B$3,"UnionLocal",$F13,"UnionClass",$I13,"CertifiedClass",$J13)),0) -> 0 | BR13: =IF(AND(NOT(ISBLANK($C13)),NOT(ISBLANK($E13)),$A13="x"),IF(U13=0,0,[2]!TSImport("PRTime","","Time_NINE","","Date",$BO$11,"Employee",$B$2,"JCJob",$C13,"JCExtra",$D13,"JCCostCode",$E13,"WCCode",$B13,"WCState",$G13,"State",$H13,"PayID",$BE$12,"Units",U13,"UnionID",$B$3,"UnionLocal",$F13,"UnionClass",$I13,"CertifiedClass",$J13)),0) -> 0 | BS13: =IF(AND(NOT(ISBLANK($C13)),NOT(ISBLANK($E13)),$A13="x"),IF(V13=0,0,[2]!TSImport("PRTime","","Time_NINE","","Date",$BO$11,"Employee",$B$2,"JCJob",$C13,"JCExtra",$D13,"JCCostCode",$E13,"WCCode",$B13,"WCState",$G13,"State",$H13,"PayID",$BF$12,"Units",V13,"UnionID",$B$3,"UnionLocal",$F13,"UnionClass",$I13,"CertifiedClass",$J13)),0) -> 0 | BT13: =IF(AND(NOT(ISBLANK($C13)),NOT(ISBLANK($E13)),$A13="x"),IF(W13=0,0,[2]!TSImport("PRTime","","Time_NINE","","Date",$BO$11,"Employee",$B$2,"JCJob",$C13,"JCExtra",$D13,"JCCostCode",$E13,"WCCode",$B13,"WCState",$G13,"State",$H13,"PayID",$BG$12,"Units",W13,"UnionID",$B$3,"UnionLocal",$F13,"UnionClass",$I13,"CertifiedClass",$J13)),0) -> 0 | BU13: =IF(AND(NOT(ISBLANK($C13)),NOT(ISBLANK($E13)),$A13="x"),IF(X13=0,0,[2]!TSImport("PRTime","","Time_NINE","","Date",$BU$11,"Employee",$B$2,"JCJob",$C13,"JCExtra",$D13,"JCCostCode",$E13,"WCCode",$B13,"WCState",$G13,"State",$H13,"PayID",$BB$12,"Units",X13,"UnionID",$B$3,"UnionLocal",$F13,"UnionClass",$I13,"CertifiedClass",$J13)),0) -> 0 | BV13: =IF(AND(NOT(ISBLANK($C13)),NOT(ISBLANK($E13)),$A13="x"),IF(Y13=0,0,[2]!TSImport("PRTime","","Time_NINE","","Date",$BU$11,"Employee",$B$2,"JCJob",$C13,"JCExtra",$D13,"JCCostCode",$E13,"WCCode",$B13,"WCState",$G13,"State",$H13,"PayID",$BC$12,"Units",Y13,"UnionID",$B$3,"UnionLocal",$F13,"UnionClass",$I13,"CertifiedClass",$J13)),0) -> 0 | BW13: =IF(AND(NOT(ISBLANK($C13)),NOT(ISBLANK($E13)),$A13="x"),IF(Z13=0,0,[2]!TSImport("PRTime","","Time_NINE","","Date",$BU$11,"Employee",$B$2,"JCJob",$C13,"JCExtra",$D13,"JCCostCode",$E13,"WCCode",$B13,"WCState",$G13,"State",$H13,"PayID",$BD$12,"Units",Z13,"UnionID",$B$3,"UnionLocal",$F13,"UnionClass",$I13,"CertifiedClass",$J13)),0) -> 0 | BX13: =IF(AND(NOT(ISBLANK($C13)),NOT(ISBLANK($E13)),$A13="x"),IF(AA13=0,0,[2]!TSImport("PRTime","","Time_NINE","","Date",$BU$11,"Employee",$B$2,"JCJob",$C13,"JCExtra",$D13,"JCCostCode",$E13,"WCCode",$B13,"WCState",$G13,"State",$H13,"PayID",$BE$12,"Units",AA13,"UnionID",$B$3,"UnionLocal",$F13,"UnionClass",$I13,"CertifiedClass",$J13)),0) -> 0 | BY13: =IF(AND(NOT(ISBLANK($C13)),NOT(ISBLANK($E13)),$A13="x"),IF(AB13=0,0,[2]!TSImport("PRTime","","Time_NINE","","Date",$BU$11,"Employee",$B$2,"JCJob",$C13,"JCExtra",$D13,"JCCostCode",$E13,"WCCode",$B13,"WCState",$G13,"State",$H13,"PayID",$BF$12,"Units",AB13,"UnionID",$B$3,"UnionLocal",$F13,"UnionClass",$I13,"CertifiedClass",$J13)),0) -> 0 | BZ13: =IF(AND(NOT(ISBLANK($C13)),NOT(ISBLANK($E13)),$A13="x"),IF(AC13=0,0,[2]!TSImport("PRTime","","Time_NINE","","Date",$BU$11,"Employee",$B$2,"JCJob",$C13,"JCExtra",$D13,"JCCostCode",$E13,"WCCode",$B13,"WCState",$G13,"State",$H13,"PayID",$BG$12,"Units",AC13,"UnionID",$B$3,"UnionLocal",$F13,"UnionClass",$I13,"CertifiedClass",$J13)),0) -> 0 | CA13: =IF(AND(NOT(ISBLANK($C13)),NOT(ISBLANK($E13)),$A13="x"),IF(AD13=0,0,[2]!TSImport("PRTime","","Time_NINE","","Date",$CA$11,"Employee",$B$2,"JCJob",$C13,"JCExtra",$D13,"JCCostCode",$E13,"WCCode",$B13,"WCState",$G13,"State",$H13,"PayID",$BB$12,"Units",AD13,"UnionID",$B$3,"UnionLocal",$F13,"UnionClass",$I13,"CertifiedClass",$J13)),0) -> 0 | CB13: =IF(AND(NOT(ISBLANK($C13)),NOT(ISBLANK($E13)),$A13="x"),IF(AE13=0,0,[2]!TSImport("PRTime","","Time_NINE","","Date",$CA$11,"Employee",$B$2,"JCJob",$C13,"JCExtra",$D13,"JCCostCode",$E13,"WCCode",$B13,"WCState",$G13,"State",$H13,"PayID",$BC$12,"Units",AE13,"UnionID",$B$3,"UnionLocal",$F13,"UnionClass",$I13,"CertifiedClass",$J13)),0) -> 0 | CC13: =IF(AND(NOT(ISBLANK($C13)),NOT(ISBLANK($E13)),$A13="x"),IF(AF13=0,0,[2]!TSImport("PRTime","","Time_NINE","","Date",$CA$11,"Employee",$B$2,"JCJob",$C13,"JCExtra",$D13,"JCCostCode",$E13,"WCCode",$B13,"WCState",$G13,"State",$H13,"PayID",$BD$12,"Units",AF13,"UnionID",$B$3,"UnionLocal",$F13,"UnionClass",$I13,"CertifiedClass",$J13)),0) -> 0 | CD13: =IF(AND(NOT(ISBLANK($C13)),NOT(ISBLANK($E13)),$A13="x"),IF(AG13=0,0,[2]!TSImport("PRTime","","Time_NINE","","Date",$CA$11,"Employee",$B$2,"JCJob",$C13,"JCExtra",$D13,"JCCostCode",$E13,"WCCode",$B13,"WCState",$G13,"State",$H13,"PayID",$BE$12,"Units",AG13,"UnionID",$B$3,"UnionLocal",$F13,"UnionClass",$I13,"CertifiedClass",$J13)),0) -> 0 | CE13: =IF(AND(NOT(ISBLANK($C13)),NOT(ISBLANK($E13)),$A13="x"),IF(AH13=0,0,[2]!TSImport("PRTime","","Time_NINE","","Date",$CA$11,"Employee",$B$2,"JCJob",$C13,"JCExtra",$D13,"JCCostCode",$E13,"WCCode",$B13,"WCState",$G13,"State",$H13,"PayID",$BF$12,"Units",AH13,"UnionID",$B$3,"UnionLocal",$F13,"UnionClass",$I13,"CertifiedClass",$J13)),0) -> 0 | CF13: =IF(AND(NOT(ISBLANK($C13)),NOT(ISBLANK($E13)),$A13="x"),IF(AI13=0,0,[2]!TSImport("PRTime","","Time_NINE","","Date",$CA$11,"Employee",$B$2,"JCJob",$C13,"JCExtra",$D13,"JCCostCode",$E13,"WCCode",$B13,"WCState",$G13,"State",$H13,"PayID",$BG$12,"Units",AI13,"UnionID",$B$3,"UnionLocal",$F13,"UnionClass",$I13,"CertifiedClass",$J13)),0) -> 0 | CG13: =IF(AND(NOT(ISBLANK($C13)),NOT(ISBLANK($E13)),$A13="x"),IF(AJ13=0,0,[2]!TSImport("PRTime","","Time_NINE","","Date",$CG$11,"Employee",$B$2,"JCJob",$C13,"JCExtra",$D13,"JCCostCode",$E13,"WCCode",$B13,"WCState",$G13,"State",$H13,"PayID",$BB$12,"Units",AJ13,"UnionID",$B$3,"UnionLocal",$F13,"UnionClass",$I13,"CertifiedClass",$J13)),0) -> 0 | CH13: =IF(AND(NOT(ISBLANK($C13)),NOT(ISBLANK($E13)),$A13="x"),IF(AK13=0,0,[2]!TSImport("PRTime","","Time_NINE","","Date",$CG$11,"Employee",$B$2,"JCJob",$C13,"JCExtra",$D13,"JCCostCode",$E13,"WCCode",$B13,"WCState",$G13,"State",$H13,"PayID",$BC$12,"Units",AK13,"UnionID",$B$3,"UnionLocal",$F13,"UnionClass",$I13,"CertifiedClass",$J13)),0) -> 0 | CI13: =IF(AND(NOT(ISBLANK($C13)),NOT(ISBLANK($E13)),$A13="x"),IF(AL13=0,0,[2]!TSImport("PRTime","","Time_NINE","","Date",$CG$11,"Employee",$B$2,"JCJob",$C13,"JCExtra",$D13,"JCCostCode",$E13,"WCCode",$B13,"WCState",$G13,"State",$H13,"PayID",$BD$12,"Units",AL13,"UnionID",$B$3,"UnionLocal",$F13,"UnionClass",$I13,"CertifiedClass",$J13)),0) -> 0 | CJ13: =IF(AND(NOT(ISBLANK($C13)),NOT(ISBLANK($E13)),$A13="x"),IF(AM13=0,0,[2]!TSImport("PRTime","","Time_NINE","","Date",$CG$11,"Employee",$B$2,"JCJob",$C13,"JCExtra",$D13,"JCCostCode",$E13,"WCCode",$B13,"WCState",$G13,"State",$H13,"PayID",$BE$12,"Units",AM13,"UnionID",$B$3,"UnionLocal",$F13,"UnionClass",$I13,"CertifiedClass",$J13)),0) -> 0 | CK13: =IF(AND(NOT(ISBLANK($C13)),NOT(ISBLANK($E13)),$A13="x"),IF(AN13=0,0,[2]!TSImport("PRTime","","Time_NINE","","Date",$CG$11,"Employee",$B$2,"JCJob",$C13,"JCExtra",$D13,"JCCostCode",$E13,"WCCode",$B13,"WCState",$G13,"State",$H13,"PayID",$BF$12,"Units",AN13,"UnionID",$B$3,"UnionLocal",$F13,"UnionClass",$I13,"CertifiedClass",$J13)),0) -> 0 | CL13: =IF(AND(NOT(ISBLANK($C13)),NOT(ISBLANK($E13)),$A13="x"),IF(AO13=0,0,[2]!TSImport("PRTime","","Time_NINE","","Date",$CG$11,"Employee",$B$2,"JCJob",$C13,"JCExtra",$D13,"JCCostCode",$E13,"WCCode",$B13,"WCState",$G13,"State",$H13,"PayID",$BG$12,"Units",AO13,"UnionID",$B$3,"UnionLocal",$F13,"UnionClass",$I13,"CertifiedClass",$J13)),0) -> 0 | CM13: =IF(AND(NOT(ISBLANK($C13)),NOT(ISBLANK($E13)),$A13="x"),IF(AP13=0,0,[2]!TSImport("PRTime","","Time_NINE","","Date",$CM$11,"Employee",$B$2,"JCJob",$C13,"JCExtra",$D13,"JCCostCode",$E13,"WCCode",$B13,"WCState",$G13,"State",$H13,"PayID",$BB$12,"Units",AP13,"UnionID",$B$3,"UnionLocal",$F13,"UnionClass",$I13,"CertifiedClass",$J13)),0) -> 0 | CN13: =IF(AND(NOT(ISBLANK($C13)),NOT(ISBLANK($E13)),$A13="x"),IF(AQ13=0,0,[2]!TSImport("PRTime","","Time_NINE","","Date",$CM$11,"Employee",$B$2,"JCJob",$C13,"JCExtra",$D13,"JCCostCode",$E13,"WCCode",$B13,"WCState",$G13,"State",$H13,"PayID",$BC$12,"Units",AQ13,"UnionID",$B$3,"UnionLocal",$F13,"UnionClass",$I13,"CertifiedClass",$J13)),0) -> 0 | CO13: =IF(AND(NOT(ISBLANK($C13)),NOT(ISBLANK($E13)),$A13="x"),IF(AR13=0,0,[2]!TSImport("PRTime","","Time_NINE","","Date",$CM$11,"Employee",$B$2,"JCJob",$C13,"JCExtra",$D13,"JCCostCode",$E13,"WCCode",$B13,"WCState",$G13,"State",$H13,"PayID",$BD$12,"Units",AR13,"UnionID",$B$3,"UnionLocal",$F13,"UnionClass",$I13,"CertifiedClass",$J13)),0) -> 0 | CP13: =IF(AND(NOT(ISBLANK($C13)),NOT(ISBLANK($E13)),$A13="x"),IF(AS13=0,0,[2]!TSImport("PRTime","","Time_NINE","","Date",$CM$11,"Employee",$B$2,"JCJob",$C13,"JCExtra",$D13,"JCCostCode",$E13,"WCCode",$B13,"WCState",$G13,"State",$H13,"PayID",$BE$12,"Units",AS13,"UnionID",$B$3,"UnionLocal",$F13,"UnionClass",$I13,"CertifiedClass",$J13)),0) -> 0 | CQ13: =IF(AND(NOT(ISBLANK($C13)),NOT(ISBLANK($E13)),$A13="x"),IF(AT13=0,0,[2]!TSImport("PRTime","","Time_NINE","","Date",$CM$11,"Employee",$B$2,"JCJob",$C13,"JCExtra",$D13,"JCCostCode",$E13,"WCCode",$B13,"WCState",$G13,"State",$H13,"PayID",$BF$12,"Units",AT13,"UnionID",$B$3,"UnionLocal",$F13,"UnionClass",$I13,"CertifiedClass",$J13)),0) -> 0 | CR13: =IF(AND(NOT(ISBLANK($C13)),NOT(ISBLANK($E13)),$A13="x"),IF(AU13=0,0,[2]!TSImport("PRTime","","Time_NINE","","Date",$CM$11,"Employee",$B$2,"JCJob",$C13,"JCExtra",$D13,"JCCostCode",$E13,"WCCode",$B13,"WCState",$G13,"State",$H13,"PayID",$BG$12,"Units",AU13,"UnionID",$B$3,"UnionLocal",$F13,"UnionClass",$I13,"CertifiedClass",$J13)),0) -> 0 | CS13: =IF(AND(NOT(ISBLANK($C13)),NOT(ISBLANK($E13)),$A13="x"),IF(AV13=0,0,[2]!TSImport("PRTime","","Time_NINE","","Date",$CS$11,"Employee",$B$2,"JCJob",$C13,"JCExtra",$D13,"JCCostCode",$E13,"WCCode",$B13,"WCState",$G13,"State",$H13,"PayID",$BB$12,"Units",AV13,"UnionID",$B$3,"UnionLocal",$F13,"UnionClass",$I13,"CertifiedClass",$J13)),0) -> 0 | CT13: =IF(AND(NOT(ISBLANK($C13)),NOT(ISBLANK($E13)),$A13="x"),IF(AW13=0,0,[2]!TSImport("PRTime","","Time_NINE","","Date",$CS$11,"Employee",$B$2,"JCJob",$C13,"JCExtra",$D13,"JCCostCode",$E13,"WCCode",$B13,"WCState",$G13,"State",$H13,"PayID",$BC$12,"Units",AW13,"UnionID",$B$3,"UnionLocal",$F13,"UnionClass",$I13,"CertifiedClass",$J13)),0) -> 0 | CU13: =IF(AND(NOT(ISBLANK($C13)),NOT(ISBLANK($E13)),$A13="x"),IF(AX13=0,0,[2]!TSImport("PRTime","","Time_NINE","","Date",$CS$11,"Employee",$B$2,"JCJob",$C13,"JCExtra",$D13,"JCCostCode",$E13,"WCCode",$B13,"WCState",$G13,"State",$H13,"PayID",$BD$12,"Units",AX13,"UnionID",$B$3,"UnionLocal",$F13,"UnionClass",$I13,"CertifiedClass",$J13)),0) -> 0 | CV13: =IF(AND(NOT(ISBLANK($C13)),NOT(ISBLANK($E13)),$A13="x"),IF(AY13=0,0,[2]!TSImport("PRTime","","Time_NINE","","Date",$CS$11,"Employee",$B$2,"JCJob",$C13,"JCExtra",$D13,"JCCostCode",$E13,"WCCode",$B13,"WCState",$G13,"State",$H13,"PayID",$BE$12,"Units",AY13,"UnionID",$B$3,"UnionLocal",$F13,"UnionClass",$I13,"CertifiedClass",$J13)),0) -> 0 | CW13: =IF(AND(NOT(ISBLANK($C13)),NOT(ISBLANK($E13)),$A13="x"),IF(AZ13=0,0,[2]!TSImport("PRTime","","Time_NINE","","Date",$CS$11,"Employee",$B$2,"JCJob",$C13,"JCExtra",$D13,"JCCostCode",$E13,"WCCode",$B13,"WCState",$G13,"State",$H13,"PayID",$BF$12,"Units",AZ13,"UnionID",$B$3,"UnionLocal",$F13,"UnionClass",$I13,"CertifiedClass",$J13)),0) -> 0 | CX13: =IF(AND(NOT(ISBLANK($C13)),NOT(ISBLANK($E13)),$A13="x"),IF(BA13=0,0,[2]!TSImport("PRTime","","Time_NINE","","Date",$CS$11,"Employee",$B$2,"JCJob",$C13,"JCExtra",$D13,"JCCostCode",$E13,"WCCode",$B13,"WCState",$G13,"State",$H13,"PayID",$BG$12,"Units",BA13,"UnionID",$B$3,"UnionLocal",$F13,"UnionClass",$I13,"CertifiedClass",$J13)),0) -> 0
A14: =IF(ISBLANK(C14),"",IF(ISBLANK($D$3),"",$D$3)) | F14: =IF(ISBLANK($B$4),"",$B$4) | J14: =IF($K14=0,"",IF($K14<10,"0"&$K14,$K14)) | BB14: =SUM(AV14,AP14,AJ14,AD14,X14,R14,L14) -> 0 | BC14: =SUM(AW14,AQ14,AK14,AE14,Y14,S14,M14) -> 0 | BD14: =SUM(AX14,AR14,AL14,AF14,Z14,T14,N14) -> 0 | BE14: =SUM(AY14,AS14,AM14,AG14,AA14,U14,O14) -> 0 | BF14: =SUM(AZ14,AT14,AN14,AH14,AB14,V14,P14) -> 0 | BG14: =SUM(BA14,AU14,AO14,AI14,AC14,W14,Q14) -> 0 | BH14: =SUM(TimeSheet34[[#This Row],[1]:[4A]]) -> 0 | BI14: =IF(AND(NOT(ISBLANK($C14)),NOT(ISBLANK($E14)),$A14="x"),IF(L14=0,0,[2]!TSImport("PRTime","","Time_NINE","","Date",$BI$11,"Employee",$B$2,"JCJob",$C14,"JCExtra",$D14,"JCCostCode",$E14,"WCCode",$B14,"WCState",$G14,"State",$H14,"PayID",$BB$12,"Units",L14,"UnionID",$B$3,"UnionLocal",$F14,"UnionClass",$I14,"CertifiedClass",$J14)),0) -> 0 | BJ14: =IF(AND(NOT(ISBLANK($C14)),NOT(ISBLANK($E14)),$A14="x"),IF(M14=0,0,[2]!TSImport("PRTime","","Time_NINE","","Date",$BI$11,"Employee",$B$2,"JCJob",$C14,"JCExtra",$D14,"JCCostCode",$E14,"WCCode",$B14,"WCState",$G14,"State",$H14,"PayID",$BC$12,"Units",M14,"UnionID",$B$3,"UnionLocal",$F14,"UnionClass",$I14,"CertifiedClass",$J14)),0) -> 0 | BK14: =IF(AND(NOT(ISBLANK($C14)),NOT(ISBLANK($E14)),$A14="x"),IF(N14=0,0,[2]!TSImport("PRTime","","Time_NINE","","Date",$BI$11,"Employee",$B$2,"JCJob",$C14,"JCExtra",$D14,"JCCostCode",$E14,"WCCode",$B14,"WCState",$G14,"State",$H14,"PayID",$BD$12,"Units",N14,"UnionID",$B$3,"UnionLocal",$F14,"UnionClass",$I14,"CertifiedClass",$J14)),0) -> 0 | BL14: =IF(AND(NOT(ISBLANK($C14)),NOT(ISBLANK($E14)),$A14="x"),IF(O14=0,0,[2]!TSImport("PRTime","","Time_NINE","","Date",$BI$11,"Employee",$B$2,"JCJob",$C14,"JCExtra",$D14,"JCCostCode",$E14,"WCCode",$B14,"WCState",$G14,"State",$H14,"PayID",$BE$12,"Units",O14,"UnionID",$B$3,"UnionLocal",$F14,"UnionClass",$I14,"CertifiedClass",$J14)),0) -> 0 | BM14: =IF(AND(NOT(ISBLANK($C14)),NOT(ISBLANK($E14)),$A14="x"),IF(P14=0,0,[2]!TSImport("PRTime","","Time_NINE","","Date",$BI$11,"Employee",$B$2,"JCJob",$C14,"JCExtra",$D14,"JCCostCode",$E14,"WCCode",$B14,"WCState",$G14,"State",$H14,"PayID",$BF$12,"Units",P14,"UnionID",$B$3,"UnionLocal",$F14,"UnionClass",$I14,"CertifiedClass",$J14)),0) -> 0 | BN14: =IF(AND(NOT(ISBLANK($C14)),NOT(ISBLANK($E14)),$A14="x"),IF(Q14=0,0,[2]!TSImport("PRTime","","Time_NINE","","Date",$BI$11,"Employee",$B$2,"JCJob",$C14,"JCExtra",$D14,"JCCostCode",$E14,"WCCode",$B14,"WCState",$G14,"State",$H14,"PayID",$BG$12,"Units",Q14,"UnionID",$B$3,"UnionLocal",$F14,"UnionClass",$I14,"CertifiedClass",$J14)),0) -> 0 | BO14: =IF(AND(NOT(ISBLANK($C14)),NOT(ISBLANK($E14)),$A14="x"),IF(R14=0,0,[2]!TSImport("PRTime","","Time_NINE","","Date",$BO$11,"Employee",$B$2,"JCJob",$C14,"JCExtra",$D14,"JCCostCode",$E14,"WCCode",$B14,"WCState",$G14,"State",$H14,"PayID",$BB$12,"Units",R14,"UnionID",$B$3,"UnionLocal",$F14,"UnionClass",$I14,"CertifiedClass",$J14)),0) -> 0 | BP14: =IF(AND(NOT(ISBLANK($C14)),NOT(ISBLANK($E14)),$A14="x"),IF(S14=0,0,[2]!TSImport("PRTime","","Time_NINE","","Date",$BO$11,"Employee",$B$2,"JCJob",$C14,"JCExtra",$D14,"JCCostCode",$E14,"WCCode",$B14,"WCState",$G14,"State",$H14,"PayID",$BC$12,"Units",S14,"UnionID",$B$3,"UnionLocal",$F14,"UnionClass",$I14,"CertifiedClass",$J14)),0) -> 0 | BQ14: =IF(AND(NOT(ISBLANK($C14)),NOT(ISBLANK($E14)),$A14="x"),IF(T14=0,0,[2]!TSImport("PRTime","","Time_NINE","","Date",$BO$11,"Employee",$B$2,"JCJob",$C14,"JCExtra",$D14,"JCCostCode",$E14,"WCCode",$B14,"WCState",$G14,"State",$H14,"PayID",$BD$12,"Units",T14,"UnionID",$B$3,"UnionLocal",$F14,"UnionClass",$I14,"CertifiedClass",$J14)),0) -> 0 | BR14: =IF(AND(NOT(ISBLANK($C14)),NOT(ISBLANK($E14)),$A14="x"),IF(U14=0,0,[2]!TSImport("PRTime","","Time_NINE","","Date",$BO$11,"Employee",$B$2,"JCJob",$C14,"JCExtra",$D14,"JCCostCode",$E14,"WCCode",$B14,"WCState",$G14,"State",$H14,"PayID",$BE$12,"Units",U14,"UnionID",$B$3,"UnionLocal",$F14,"UnionClass",$I14,"CertifiedClass",$J14)),0) -> 0 | BS14: =IF(AND(NOT(ISBLANK($C14)),NOT(ISBLANK($E14)),$A14="x"),IF(V14=0,0,[2]!TSImport("PRTime","","Time_NINE","","Date",$BO$11,"Employee",$B$2,"JCJob",$C14,"JCExtra",$D14,"JCCostCode",$E14,"WCCode",$B14,"WCState",$G14,"State",$H14,"PayID",$BF$12,"Units",V14,"UnionID",$B$3,"UnionLocal",$F14,"UnionClass",$I14,"CertifiedClass",$J14)),0) -> 0 | BT14: =IF(AND(NOT(ISBLANK($C14)),NOT(ISBLANK($E14)),$A14="x"),IF(W14=0,0,[2]!TSImport("PRTime","","Time_NINE","","Date",$BO$11,"Employee",$B$2,"JCJob",$C14,"JCExtra",$D14,"JCCostCode",$E14,"WCCode",$B14,"WCState",$G14,"State",$H14,"PayID",$BG$12,"Units",W14,"UnionID",$B$3,"UnionLocal",$F14,"UnionClass",$I14,"CertifiedClass",$J14)),0) -> 0 | BU14: =IF(AND(NOT(ISBLANK($C14)),NOT(ISBLANK($E14)),$A14="x"),IF(X14=0,0,[2]!TSImport("PRTime","","Time_NINE","","Date",$BU$11,"Employee",$B$2,"JCJob",$C14,"JCExtra",$D14,"JCCostCode",$E14,"WCCode",$B14,"WCState",$G14,"State",$H14,"PayID",$BB$12,"Units",X14,"UnionID",$B$3,"UnionLocal",$F14,"UnionClass",$I14,"CertifiedClass",$J14)),0) -> 0 | BV14: =IF(AND(NOT(ISBLANK($C14)),NOT(ISBLANK($E14)),$A14="x"),IF(Y14=0,0,[2]!TSImport("PRTime","","Time_NINE","","Date",$BU$11,"Employee",$B$2,"JCJob",$C14,"JCExtra",$D14,"JCCostCode",$E14,"WCCode",$B14,"WCState",$G14,"State",$H14,"PayID",$BC$12,"Units",Y14,"UnionID",$B$3,"UnionLocal",$F14,"UnionClass",$I14,"CertifiedClass",$J14)),0) -> 0 | BW14: =IF(AND(NOT(ISBLANK($C14)),NOT(ISBLANK($E14)),$A14="x"),IF(Z14=0,0,[2]!TSImport("PRTime","","Time_NINE","","Date",$BU$11,"Employee",$B$2,"JCJob",$C14,"JCExtra",$D14,"JCCostCode",$E14,"WCCode",$B14,"WCState",$G14,"State",$H14,"PayID",$BD$12,"Units",Z14,"UnionID",$B$3,"UnionLocal",$F14,"UnionClass",$I14,"CertifiedClass",$J14)),0) -> 0 | BX14: =IF(AND(NOT(ISBLANK($C14)),NOT(ISBLANK($E14)),$A14="x"),IF(AA14=0,0,[2]!TSImport("PRTime","","Time_NINE","","Date",$BU$11,"Employee",$B$2,"JCJob",$C14,"JCExtra",$D14,"JCCostCode",$E14,"WCCode",$B14,"WCState",$G14,"State",$H14,"PayID",$BE$12,"Units",AA14,"UnionID",$B$3,"UnionLocal",$F14,"UnionClass",$I14,"CertifiedClass",$J14)),0) -> 0 | BY14: =IF(AND(NOT(ISBLANK($C14)),NOT(ISBLANK($E14)),$A14="x"),IF(AB14=0,0,[2]!TSImport("PRTime","","Time_NINE","","Date",$BU$11,"Employee",$B$2,"JCJob",$C14,"JCExtra",$D14,"JCCostCode",$E14,"WCCode",$B14,"WCState",$G14,"State",$H14,"PayID",$BF$12,"Units",AB14,"UnionID",$B$3,"UnionLocal",$F14,"UnionClass",$I14,"CertifiedClass",$J14)),0) -> 0 | BZ14: =IF(AND(NOT(ISBLANK($C14)),NOT(ISBLANK($E14)),$A14="x"),IF(AC14=0,0,[2]!TSImport("PRTime","","Time_NINE","","Date",$BU$11,"Employee",$B$2,"JCJob",$C14,"JCExtra",$D14,"JCCostCode",$E14,"WCCode",$B14,"WCState",$G14,"State",$H14,"PayID",$BG$12,"Units",AC14,"UnionID",$B$3,"UnionLocal",$F14,"UnionClass",$I14,"CertifiedClass",$J14)),0) -> 0 | CA14: =IF(AND(NOT(ISBLANK($C14)),NOT(ISBLANK($E14)),$A14="x"),IF(AD14=0,0,[2]!TSImport("PRTime","","Time_NINE","","Date",$CA$11,"Employee",$B$2,"JCJob",$C14,"JCExtra",$D14,"JCCostCode",$E14,"WCCode",$B14,"WCState",$G14,"State",$H14,"PayID",$BB$12,"Units",AD14,"UnionID",$B$3,"UnionLocal",$F14,"UnionClass",$I14,"CertifiedClass",$J14)),0) -> 0 | CB14: =IF(AND(NOT(ISBLANK($C14)),NOT(ISBLANK($E14)),$A14="x"),IF(AE14=0,0,[2]!TSImport("PRTime","","Time_NINE","","Date",$CA$11,"Employee",$B$2,"JCJob",$C14,"JCExtra",$D14,"JCCostCode",$E14,"WCCode",$B14,"WCState",$G14,"State",$H14,"PayID",$BC$12,"Units",AE14,"UnionID",$B$3,"UnionLocal",$F14,"UnionClass",$I14,"CertifiedClass",$J14)),0) -> 0 | CC14: =IF(AND(NOT(ISBLANK($C14)),NOT(ISBLANK($E14)),$A14="x"),IF(AF14=0,0,[2]!TSImport("PRTime","","Time_NINE","","Date",$CA$11,"Employee",$B$2,"JCJob",$C14,"JCExtra",$D14,"JCCostCode",$E14,"WCCode",$B14,"WCState",$G14,"State",$H14,"PayID",$BD$12,"Units",AF14,"UnionID",$B$3,"UnionLocal",$F14,"UnionClass",$I14,"CertifiedClass",$J14)),0) -> 0 | CD14: =IF(AND(NOT(ISBLANK($C14)),NOT(ISBLANK($E14)),$A14="x"),IF(AG14=0,0,[2]!TSImport("PRTime","","Time_NINE","","Date",$CA$11,"Employee",$B$2,"JCJob",$C14,"JCExtra",$D14,"JCCostCode",$E14,"WCCode",$B14,"WCState",$G14,"State",$H14,"PayID",$BE$12,"Units",AG14,"UnionID",$B$3,"UnionLocal",$F14,"UnionClass",$I14,"CertifiedClass",$J14)),0) -> 0 | CE14: =IF(AND(NOT(ISBLANK($C14)),NOT(ISBLANK($E14)),$A14="x"),IF(AH14=0,0,[2]!TSImport("PRTime","","Time_NINE","","Date",$CA$11,"Employee",$B$2,"JCJob",$C14,"JCExtra",$D14,"JCCostCode",$E14,"WCCode",$B14,"WCState",$G14,"State",$H14,"PayID",$BF$12,"Units",AH14,"UnionID",$B$3,"UnionLocal",$F14,"UnionClass",$I14,"CertifiedClass",$J14)),0) -> 0 | CF14: =IF(AND(NOT(ISBLANK($C14)),NOT(ISBLANK($E14)),$A14="x"),IF(AI14=0,0,[2]!TSImport("PRTime","","Time_NINE","","Date",$CA$11,"Employee",$B$2,"JCJob",$C14,"JCExtra",$D14,"JCCostCode",$E14,"WCCode",$B14,"WCState",$G14,"State",$H14,"PayID",$BG$12,"Units",AI14,"UnionID",$B$3,"UnionLocal",$F14,"UnionClass",$I14,"CertifiedClass",$J14)),0) -> 0 | CG14: =IF(AND(NOT(ISBLANK($C14)),NOT(ISBLANK($E14)),$A14="x"),IF(AJ14=0,0,[2]!TSImport("PRTime","","Time_NINE","","Date",$CG$11,"Employee",$B$2,"JCJob",$C14,"JCExtra",$D14,"JCCostCode",$E14,"WCCode",$B14,"WCState",$G14,"State",$H14,"PayID",$BB$12,"Units",AJ14,"UnionID",$B$3,"UnionLocal",$F14,"UnionClass",$I14,"CertifiedClass",$J14)),0) -> 0 | CH14: =IF(AND(NOT(ISBLANK($C14)),NOT(ISBLANK($E14)),$A14="x"),IF(AK14=0,0,[2]!TSImport("PRTime","","Time_NINE","","Date",$CG$11,"Employee",$B$2,"JCJob",$C14,"JCExtra",$D14,"JCCostCode",$E14,"WCCode",$B14,"WCState",$G14,"State",$H14,"PayID",$BC$12,"Units",AK14,"UnionID",$B$3,"UnionLocal",$F14,"UnionClass",$I14,"CertifiedClass",$J14)),0) -> 0 | CI14: =IF(AND(NOT(ISBLANK($C14)),NOT(ISBLANK($E14)),$A14="x"),IF(AL14=0,0,[2]!TSImport("PRTime","","Time_NINE","","Date",$CG$11,"Employee",$B$2,"JCJob",$C14,"JCExtra",$D14,"JCCostCode",$E14,"WCCode",$B14,"WCState",$G14,"State",$H14,"PayID",$BD$12,"Units",AL14,"UnionID",$B$3,"UnionLocal",$F14,"UnionClass",$I14,"CertifiedClass",$J14)),0) -> 0 | CJ14: =IF(AND(NOT(ISBLANK($C14)),NOT(ISBLANK($E14)),$A14="x"),IF(AM14=0,0,[2]!TSImport("PRTime","","Time_NINE","","Date",$CG$11,"Employee",$B$2,"JCJob",$C14,"JCExtra",$D14,"JCCostCode",$E14,"WCCode",$B14,"WCState",$G14,"State",$H14,"PayID",$BE$12,"Units",AM14,"UnionID",$B$3,"UnionLocal",$F14,"UnionClass",$I14,"CertifiedClass",$J14)),0) -> 0 | CK14: =IF(AND(NOT(ISBLANK($C14)),NOT(ISBLANK($E14)),$A14="x"),IF(AN14=0,0,[2]!TSImport("PRTime","","Time_NINE","","Date",$CG$11,"Employee",$B$2,"JCJob",$C14,"JCExtra",$D14,"JCCostCode",$E14,"WCCode",$B14,"WCState",$G14,"State",$H14,"PayID",$BF$12,"Units",AN14,"UnionID",$B$3,"UnionLocal",$F14,"UnionClass",$I14,"CertifiedClass",$J14)),0) -> 0 | CL14: =IF(AND(NOT(ISBLANK($C14)),NOT(ISBLANK($E14)),$A14="x"),IF(AO14=0,0,[2]!TSImport("PRTime","","Time_NINE","","Date",$CG$11,"Employee",$B$2,"JCJob",$C14,"JCExtra",$D14,"JCCostCode",$E14,"WCCode",$B14,"WCState",$G14,"State",$H14,"PayID",$BG$12,"Units",AO14,"UnionID",$B$3,"UnionLocal",$F14,"UnionClass",$I14,"CertifiedClass",$J14)),0) -> 0 | CM14: =IF(AND(NOT(ISBLANK($C14)),NOT(ISBLANK($E14)),$A14="x"),IF(AP14=0,0,[2]!TSImport("PRTime","","Time_NINE","","Date",$CM$11,"Employee",$B$2,"JCJob",$C14,"JCExtra",$D14,"JCCostCode",$E14,"WCCode",$B14,"WCState",$G14,"State",$H14,"PayID",$BB$12,"Units",AP14,"UnionID",$B$3,"UnionLocal",$F14,"UnionClass",$I14,"CertifiedClass",$J14)),0) -> 0 | CN14: =IF(AND(NOT(ISBLANK($C14)),NOT(ISBLANK($E14)),$A14="x"),IF(AQ14=0,0,[2]!TSImport("PRTime","","Time_NINE","","Date",$CM$11,"Employee",$B$2,"JCJob",$C14,"JCExtra",$D14,"JCCostCode",$E14,"WCCode",$B14,"WCState",$G14,"State",$H14,"PayID",$BC$12,"Units",AQ14,"UnionID",$B$3,"UnionLocal",$F14,"UnionClass",$I14,"CertifiedClass",$J14)),0) -> 0 | CO14: =IF(AND(NOT(ISBLANK($C14)),NOT(ISBLANK($E14)),$A14="x"),IF(AR14=0,0,[2]!TSImport("PRTime","","Time_NINE","","Date",$CM$11,"Employee",$B$2,"JCJob",$C14,"JCExtra",$D14,"JCCostCode",$E14,"WCCode",$B14,"WCState",$G14,"State",$H14,"PayID",$BD$12,"Units",AR14,"UnionID",$B$3,"UnionLocal",$F14,"UnionClass",$I14,"CertifiedClass",$J14)),0) -> 0 | CP14: =IF(AND(NOT(ISBLANK($C14)),NOT(ISBLANK($E14)),$A14="x"),IF(AS14=0,0,[2]!TSImport("PRTime","","Time_NINE","","Date",$CM$11,"Employee",$B$2,"JCJob",$C14,"JCExtra",$D14,"JCCostCode",$E14,"WCCode",$B14,"WCState",$G14,"State",$H14,"PayID",$BE$12,"Units",AS14,"UnionID",$B$3,"UnionLocal",$F14,"UnionClass",$I14,"CertifiedClass",$J14)),0) -> 0 | CQ14: =IF(AND(NOT(ISBLANK($C14)),NOT(ISBLANK($E14)),$A14="x"),IF(AT14=0,0,[2]!TSImport("PRTime","","Time_NINE","","Date",$CM$11,"Employee",$B$2,"JCJob",$C14,"JCExtra",$D14,"JCCostCode",$E14,"WCCode",$B14,"WCState",$G14,"State",$H14,"PayID",$BF$12,"Units",AT14,"UnionID",$B$3,"UnionLocal",$F14,"UnionClass",$I14,"CertifiedClass",$J14)),0) -> 0 | CR14: =IF(AND(NOT(ISBLANK($C14)),NOT(ISBLANK($E14)),$A14="x"),IF(AU14=0,0,[2]!TSImport("PRTime","","Time_NINE","","Date",$CM$11,"Employee",$B$2,"JCJob",$C14,"JCExtra",$D14,"JCCostCode",$E14,"WCCode",$B14,"WCState",$G14,"State",$H14,"PayID",$BG$12,"Units",AU14,"UnionID",$B$3,"UnionLocal",$F14,"UnionClass",$I14,"CertifiedClass",$J14)),0) -> 0 | CS14: =IF(AND(NOT(ISBLANK($C14)),NOT(ISBLANK($E14)),$A14="x"),IF(AV14=0,0,[2]!TSImport("PRTime","","Time_NINE","","Date",$CS$11,"Employee",$B$2,"JCJob",$C14,"JCExtra",$D14,"JCCostCode",$E14,"WCCode",$B14,"WCState",$G14,"State",$H14,"PayID",$BB$12,"Units",AV14,"UnionID",$B$3,"UnionLocal",$F14,"UnionClass",$I14,"CertifiedClass",$J14)),0) -> 0 | CT14: =IF(AND(NOT(ISBLANK($C14)),NOT(ISBLANK($E14)),$A14="x"),IF(AW14=0,0,[2]!TSImport("PRTime","","Time_NINE","","Date",$CS$11,"Employee",$B$2,"JCJob",$C14,"JCExtra",$D14,"JCCostCode",$E14,"WCCode",$B14,"WCState",$G14,"State",$H14,"PayID",$BC$12,"Units",AW14,"UnionID",$B$3,"UnionLocal",$F14,"UnionClass",$I14,"CertifiedClass",$J14)),0) -> 0 | CU14: =IF(AND(NOT(ISBLANK($C14)),NOT(ISBLANK($E14)),$A14="x"),IF(AX14=0,0,[2]!TSImport("PRTime","","Time_NINE","","Date",$CS$11,"Employee",$B$2,"JCJob",$C14,"JCExtra",$D14,"JCCostCode",$E14,"WCCode",$B14,"WCState",$G14,"State",$H14,"PayID",$BD$12,"Units",AX14,"UnionID",$B$3,"UnionLocal",$F14,"UnionClass",$I14,"CertifiedClass",$J14)),0) -> 0 | CV14: =IF(AND(NOT(ISBLANK($C14)),NOT(ISBLANK($E14)),$A14="x"),IF(AY14=0,0,[2]!TSImport("PRTime","","Time_NINE","","Date",$CS$11,"Employee",$B$2,"JCJob",$C14,"JCExtra",$D14,"JCCostCode",$E14,"WCCode",$B14,"WCState",$G14,"State",$H14,"PayID",$BE$12,"Units",AY14,"UnionID",$B$3,"UnionLocal",$F14,"UnionClass",$I14,"CertifiedClass",$J14)),0) -> 0 | CW14: =IF(AND(NOT(ISBLANK($C14)),NOT(ISBLANK($E14)),$A14="x"),IF(AZ14=0,0,[2]!TSImport("PRTime","","Time_NINE","","Date",$CS$11,"Employee",$B$2,"JCJob",$C14,"JCExtra",$D14,"JCCostCode",$E14,"WCCode",$B14,"WCState",$G14,"State",$H14,"PayID",$BF$12,"Units",AZ14,"UnionID",$B$3,"UnionLocal",$F14,"UnionClass",$I14,"CertifiedClass",$J14)),0) -> 0 | CX14: =IF(AND(NOT(ISBLANK($C14)),NOT(ISBLANK($E14)),$A14="x"),IF(BA14=0,0,[2]!TSImport("PRTime","","Time_NINE","","Date",$CS$11,"Employee",$B$2,"JCJob",$C14,"JCExtra",$D14,"JCCostCode",$E14,"WCCode",$B14,"WCState",$G14,"State",$H14,"PayID",$BG$12,"Units",BA14,"UnionID",$B$3,"UnionLocal",$F14,"UnionClass",$I14,"CertifiedClass",$J14)),0) -> 0
A15: =IF(ISBLANK(C15),"",IF(ISBLANK($D$3),"",$D$3)) | F15: =IF(ISBLANK($B$4),"",$B$4) | J15: =IF($K15=0,"",IF($K15<10,"0"&$K15,$K15)) | BB15: =SUM(AV15,AP15,AJ15,AD15,X15,R15,L15) -> 0 | BC15: =SUM(AW15,AQ15,AK15,AE15,Y15,S15,M15) -> 0 | BD15: =SUM(AX15,AR15,AL15,AF15,Z15,T15,N15) -> 0 | BE15: =SUM(AY15,AS15,AM15,AG15,AA15,U15,O15) -> 0 | BF15: =SUM(AZ15,AT15,AN15,AH15,AB15,V15,P15) -> 0 | BG15: =SUM(BA15,AU15,AO15,AI15,AC15,W15,Q15) -> 0 | BH15: =SUM(TimeSheet34[[#This Row],[1]:[4A]]) -> 0 | BI15: =IF(AND(NOT(ISBLANK($C15)),NOT(ISBLANK($E15)),$A15="x"),IF(L15=0,0,[2]!TSImport("PRTime","","Time_NINE","","Date",$BI$11,"Employee",$B$2,"JCJob",$C15,"JCExtra",$D15,"JCCostCode",$E15,"WCCode",$B15,"WCState",$G15,"State",$H15,"PayID",$BB$12,"Units",L15,"UnionID",$B$3,"UnionLocal",$F15,"UnionClass",$I15,"CertifiedClass",$J15)),0) -> 0 | BJ15: =IF(AND(NOT(ISBLANK($C15)),NOT(ISBLANK($E15)),$A15="x"),IF(M15=0,0,[2]!TSImport("PRTime","","Time_NINE","","Date",$BI$11,"Employee",$B$2,"JCJob",$C15,"JCExtra",$D15,"JCCostCode",$E15,"WCCode",$B15,"WCState",$G15,"State",$H15,"PayID",$BC$12,"Units",M15,"UnionID",$B$3,"UnionLocal",$F15,"UnionClass",$I15,"CertifiedClass",$J15)),0) -> 0 | BK15: =IF(AND(NOT(ISBLANK($C15)),NOT(ISBLANK($E15)),$A15="x"),IF(N15=0,0,[2]!TSImport("PRTime","","Time_NINE","","Date",$BI$11,"Employee",$B$2,"JCJob",$C15,"JCExtra",$D15,"JCCostCode",$E15,"WCCode",$B15,"WCState",$G15,"State",$H15,"PayID",$BD$12,"Units",N15,"UnionID",$B$3,"UnionLocal",$F15,"UnionClass",$I15,"CertifiedClass",$J15)),0) -> 0 | BL15: =IF(AND(NOT(ISBLANK($C15)),NOT(ISBLANK($E15)),$A15="x"),IF(O15=0,0,[2]!TSImport("PRTime","","Time_NINE","","Date",$BI$11,"Employee",$B$2,"JCJob",$C15,"JCExtra",$D15,"JCCostCode",$E15,"WCCode",$B15,"WCState",$G15,"State",$H15,"PayID",$BE$12,"Units",O15,"UnionID",$B$3,"UnionLocal",$F15,"UnionClass",$I15,"CertifiedClass",$J15)),0) -> 0 | BM15: =IF(AND(NOT(ISBLANK($C15)),NOT(ISBLANK($E15)),$A15="x"),IF(P15=0,0,[2]!TSImport("PRTime","","Time_NINE","","Date",$BI$11,"Employee",$B$2,"JCJob",$C15,"JCExtra",$D15,"JCCostCode",$E15,"WCCode",$B15,"WCState",$G15,"State",$H15,"PayID",$BF$12,"Units",P15,"UnionID",$B$3,"UnionLocal",$F15,"UnionClass",$I15,"CertifiedClass",$J15)),0) -> 0 | BN15: =IF(AND(NOT(ISBLANK($C15)),NOT(ISBLANK($E15)),$A15="x"),IF(Q15=0,0,[2]!TSImport("PRTime","","Time_NINE","","Date",$BI$11,"Employee",$B$2,"JCJob",$C15,"JCExtra",$D15,"JCCostCode",$E15,"WCCode",$B15,"WCState",$G15,"State",$H15,"PayID",$BG$12,"Units",Q15,"UnionID",$B$3,"UnionLocal",$F15,"UnionClass",$I15,"CertifiedClass",$J15)),0) -> 0 | BO15: =IF(AND(NOT(ISBLANK($C15)),NOT(ISBLANK($E15)),$A15="x"),IF(R15=0,0,[2]!TSImport("PRTime","","Time_NINE","","Date",$BO$11,"Employee",$B$2,"JCJob",$C15,"JCExtra",$D15,"JCCostCode",$E15,"WCCode",$B15,"WCState",$G15,"State",$H15,"PayID",$BB$12,"Units",R15,"UnionID",$B$3,"UnionLocal",$F15,"UnionClass",$I15,"CertifiedClass",$J15)),0) -> 0 | BP15: =IF(AND(NOT(ISBLANK($C15)),NOT(ISBLANK($E15)),$A15="x"),IF(S15=0,0,[2]!TSImport("PRTime","","Time_NINE","","Date",$BO$11,"Employee",$B$2,"JCJob",$C15,"JCExtra",$D15,"JCCostCode",$E15,"WCCode",$B15,"WCState",$G15,"State",$H15,"PayID",$BC$12,"Units",S15,"UnionID",$B$3,"UnionLocal",$F15,"UnionClass",$I15,"CertifiedClass",$J15)),0) -> 0 | BQ15: =IF(AND(NOT(ISBLANK($C15)),NOT(ISBLANK($E15)),$A15="x"),IF(T15=0,0,[2]!TSImport("PRTime","","Time_NINE","","Date",$BO$11,"Employee",$B$2,"JCJob",$C15,"JCExtra",$D15,"JCCostCode",$E15,"WCCode",$B15,"WCState",$G15,"State",$H15,"PayID",$BD$12,"Units",T15,"UnionID",$B$3,"UnionLocal",$F15,"UnionClass",$I15,"CertifiedClass",$J15)),0) -> 0 | BR15: =IF(AND(NOT(ISBLANK($C15)),NOT(ISBLANK($E15)),$A15="x"),IF(U15=0,0,[2]!TSImport("PRTime","","Time_NINE","","Date",$BO$11,"Employee",$B$2,"JCJob",$C15,"JCExtra",$D15,"JCCostCode",$E15,"WCCode",$B15,"WCState",$G15,"State",$H15,"PayID",$BE$12,"Units",U15,"UnionID",$B$3,"UnionLocal",$F15,"UnionClass",$I15,"CertifiedClass",$J15)),0) -> 0 | BS15: =IF(AND(NOT(ISBLANK($C15)),NOT(ISBLANK($E15)),$A15="x"),IF(V15=0,0,[2]!TSImport("PRTime","","Time_NINE","","Date",$BO$11,"Employee",$B$2,"JCJob",$C15,"JCExtra",$D15,"JCCostCode",$E15,"WCCode",$B15,"WCState",$G15,"State",$H15,"PayID",$BF$12,"Units",V15,"UnionID",$B$3,"UnionLocal",$F15,"UnionClass",$I15,"CertifiedClass",$J15)),0) -> 0 | BT15: =IF(AND(NOT(ISBLANK($C15)),NOT(ISBLANK($E15)),$A15="x"),IF(W15=0,0,[2]!TSImport("PRTime","","Time_NINE","","Date",$BO$11,"Employee",$B$2,"JCJob",$C15,"JCExtra",$D15,"JCCostCode",$E15,"WCCode",$B15,"WCState",$G15,"State",$H15,"PayID",$BG$12,"Units",W15,"UnionID",$B$3,"UnionLocal",$F15,"UnionClass",$I15,"CertifiedClass",$J15)),0) -> 0 | BU15: =IF(AND(NOT(ISBLANK($C15)),NOT(ISBLANK($E15)),$A15="x"),IF(X15=0,0,[2]!TSImport("PRTime","","Time_NINE","","Date",$BU$11,"Employee",$B$2,"JCJob",$C15,"JCExtra",$D15,"JCCostCode",$E15,"WCCode",$B15,"WCState",$G15,"State",$H15,"PayID",$BB$12,"Units",X15,"UnionID",$B$3,"UnionLocal",$F15,"UnionClass",$I15,"CertifiedClass",$J15)),0) -> 0 | BV15: =IF(AND(NOT(ISBLANK($C15)),NOT(ISBLANK($E15)),$A15="x"),IF(Y15=0,0,[2]!TSImport("PRTime","","Time_NINE","","Date",$BU$11,"Employee",$B$2,"JCJob",$C15,"JCExtra",$D15,"JCCostCode",$E15,"WCCode",$B15,"WCState",$G15,"State",$H15,"PayID",$BC$12,"Units",Y15,"UnionID",$B$3,"UnionLocal",$F15,"UnionClass",$I15,"CertifiedClass",$J15)),0) -> 0 | BW15: =IF(AND(NOT(ISBLANK($C15)),NOT(ISBLANK($E15)),$A15="x"),IF(Z15=0,0,[2]!TSImport("PRTime","","Time_NINE","","Date",$BU$11,"Employee",$B$2,"JCJob",$C15,"JCExtra",$D15,"JCCostCode",$E15,"WCCode",$B15,"WCState",$G15,"State",$H15,"PayID",$BD$12,"Units",Z15,"UnionID",$B$3,"UnionLocal",$F15,"UnionClass",$I15,"CertifiedClass",$J15)),0) -> 0 | BX15: =IF(AND(NOT(ISBLANK($C15)),NOT(ISBLANK($E15)),$A15="x"),IF(AA15=0,0,[2]!TSImport("PRTime","","Time_NINE","","Date",$BU$11,"Employee",$B$2,"JCJob",$C15,"JCExtra",$D15,"JCCostCode",$E15,"WCCode",$B15,"WCState",$G15,"State",$H15,"PayID",$BE$12,"Units",AA15,"UnionID",$B$3,"UnionLocal",$F15,"UnionClass",$I15,"CertifiedClass",$J15)),0) -> 0 | BY15: =IF(AND(NOT(ISBLANK($C15)),NOT(ISBLANK($E15)),$A15="x"),IF(AB15=0,0,[2]!TSImport("PRTime","","Time_NINE","","Date",$BU$11,"Employee",$B$2,"JCJob",$C15,"JCExtra",$D15,"JCCostCode",$E15,"WCCode",$B15,"WCState",$G15,"State",$H15,"PayID",$BF$12,"Units",AB15,"UnionID",$B$3,"UnionLocal",$F15,"UnionClass",$I15,"CertifiedClass",$J15)),0) -> 0 | BZ15: =IF(AND(NOT(ISBLANK($C15)),NOT(ISBLANK($E15)),$A15="x"),IF(AC15=0,0,[2]!TSImport("PRTime","","Time_NINE","","Date",$BU$11,"Employee",$B$2,"JCJob",$C15,"JCExtra",$D15,"JCCostCode",$E15,"WCCode",$B15,"WCState",$G15,"State",$H15,"PayID",$BG$12,"Units",AC15,"UnionID",$B$3,"UnionLocal",$F15,"UnionClass",$I15,"CertifiedClass",$J15)),0) -> 0 | CA15: =IF(AND(NOT(ISBLANK($C15)),NOT(ISBLANK($E15)),$A15="x"),IF(AD15=0,0,[2]!TSImport("PRTime","","Time_NINE","","Date",$CA$11,"Employee",$B$2,"JCJob",$C15,"JCExtra",$D15,"JCCostCode",$E15,"WCCode",$B15,"WCState",$G15,"State",$H15,"PayID",$BB$12,"Units",AD15,"UnionID",$B$3,"UnionLocal",$F15,"UnionClass",$I15,"CertifiedClass",$J15)),0) -> 0 | CB15: =IF(AND(NOT(ISBLANK($C15)),NOT(ISBLANK($E15)),$A15="x"),IF(AE15=0,0,[2]!TSImport("PRTime","","Time_NINE","","Date",$CA$11,"Employee",$B$2,"JCJob",$C15,"JCExtra",$D15,"JCCostCode",$E15,"WCCode",$B15,"WCState",$G15,"State",$H15,"PayID",$BC$12,"Units",AE15,"UnionID",$B$3,"UnionLocal",$F15,"UnionClass",$I15,"CertifiedClass",$J15)),0) -> 0 | CC15: =IF(AND(NOT(ISBLANK($C15)),NOT(ISBLANK($E15)),$A15="x"),IF(AF15=0,0,[2]!TSImport("PRTime","","Time_NINE","","Date",$CA$11,"Employee",$B$2,"JCJob",$C15,"JCExtra",$D15,"JCCostCode",$E15,"WCCode",$B15,"WCState",$G15,"State",$H15,"PayID",$BD$12,"Units",AF15,"UnionID",$B$3,"UnionLocal",$F15,"UnionClass",$I15,"CertifiedClass",$J15)),0) -> 0 | CD15: =IF(AND(NOT(ISBLANK($C15)),NOT(ISBLANK($E15)),$A15="x"),IF(AG15=0,0,[2]!TSImport("PRTime","","Time_NINE","","Date",$CA$11,"Employee",$B$2,"JCJob",$C15,"JCExtra",$D15,"JCCostCode",$E15,"WCCode",$B15,"WCState",$G15,"State",$H15,"PayID",$BE$12,"Units",AG15,"UnionID",$B$3,"UnionLocal",$F15,"UnionClass",$I15,"CertifiedClass",$J15)),0) -> 0 | CE15: =IF(AND(NOT(ISBLANK($C15)),NOT(ISBLANK($E15)),$A15="x"),IF(AH15=0,0,[2]!TSImport("PRTime","","Time_NINE","","Date",$CA$11,"Employee",$B$2,"JCJob",$C15,"JCExtra",$D15,"JCCostCode",$E15,"WCCode",$B15,"WCState",$G15,"State",$H15,"PayID",$BF$12,"Units",AH15,"UnionID",$B$3,"UnionLocal",$F15,"UnionClass",$I15,"CertifiedClass",$J15)),0) -> 0 | CF15: =IF(AND(NOT(ISBLANK($C15)),NOT(ISBLANK($E15)),$A15="x"),IF(AI15=0,0,[2]!TSImport("PRTime","","Time_NINE","","Date",$CA$11,"Employee",$B$2,"JCJob",$C15,"JCExtra",$D15,"JCCostCode",$E15,"WCCode",$B15,"WCState",$G15,"State",$H15,"PayID",$BG$12,"Units",AI15,"UnionID",$B$3,"UnionLocal",$F15,"UnionClass",$I15,"CertifiedClass",$J15)),0) -> 0 | CG15: =IF(AND(NOT(ISBLANK($C15)),NOT(ISBLANK($E15)),$A15="x"),IF(AJ15=0,0,[2]!TSImport("PRTime","","Time_NINE","","Date",$CG$11,"Employee",$B$2,"JCJob",$C15,"JCExtra",$D15,"JCCostCode",$E15,"WCCode",$B15,"WCState",$G15,"State",$H15,"PayID",$BB$12,"Units",AJ15,"UnionID",$B$3,"UnionLocal",$F15,"UnionClass",$I15,"CertifiedClass",$J15)),0) -> 0 | CH15: =IF(AND(NOT(ISBLANK($C15)),NOT(ISBLANK($E15)),$A15="x"),IF(AK15=0,0,[2]!TSImport("PRTime","","Time_NINE","","Date",$CG$11,"Employee",$B$2,"JCJob",$C15,"JCExtra",$D15,"JCCostCode",$E15,"WCCode",$B15,"WCState",$G15,"State",$H15,"PayID",$BC$12,"Units",AK15,"UnionID",$B$3,"UnionLocal",$F15,"UnionClass",$I15,"CertifiedClass",$J15)),0) -> 0 | CI15: =IF(AND(NOT(ISBLANK($C15)),NOT(ISBLANK($E15)),$A15="x"),IF(AL15=0,0,[2]!TSImport("PRTime","","Time_NINE","","Date",$CG$11,"Employee",$B$2,"JCJob",$C15,"JCExtra",$D15,"JCCostCode",$E15,"WCCode",$B15,"WCState",$G15,"State",$H15,"PayID",$BD$12,"Units",AL15,"UnionID",$B$3,"UnionLocal",$F15,"UnionClass",$I15,"CertifiedClass",$J15)),0) -> 0 | CJ15: =IF(AND(NOT(ISBLANK($C15)),NOT(ISBLANK($E15)),$A15="x"),IF(AM15=0,0,[2]!TSImport("PRTime","","Time_NINE","","Date",$CG$11,"Employee",$B$2,"JCJob",$C15,"JCExtra",$D15,"JCCostCode",$E15,"WCCode",$B15,"WCState",$G15,"State",$H15,"PayID",$BE$12,"Units",AM15,"UnionID",$B$3,"UnionLocal",$F15,"UnionClass",$I15,"CertifiedClass",$J15)),0) -> 0 | CK15: =IF(AND(NOT(ISBLANK($C15)),NOT(ISBLANK($E15)),$A15="x"),IF(AN15=0,0,[2]!TSImport("PRTime","","Time_NINE","","Date",$CG$11,"Employee",$B$2,"JCJob",$C15,"JCExtra",$D15,"JCCostCode",$E15,"WCCode",$B15,"WCState",$G15,"State",$H15,"PayID",$BF$12,"Units",AN15,"UnionID",$B$3,"UnionLocal",$F15,"UnionClass",$I15,"CertifiedClass",$J15)),0) -> 0 | CL15: =IF(AND(NOT(ISBLANK($C15)),NOT(ISBLANK($E15)),$A15="x"),IF(AO15=0,0,[2]!TSImport("PRTime","","Time_NINE","","Date",$CG$11,"Employee",$B$2,"JCJob",$C15,"JCExtra",$D15,"JCCostCode",$E15,"WCCode",$B15,"WCState",$G15,"State",$H15,"PayID",$BG$12,"Units",AO15,"UnionID",$B$3,"UnionLocal",$F15,"UnionClass",$I15,"CertifiedClass",$J15)),0) -> 0 | CM15: =IF(AND(NOT(ISBLANK($C15)),NOT(ISBLANK($E15)),$A15="x"),IF(AP15=0,0,[2]!TSImport("PRTime","","Time_NINE","","Date",$CM$11,"Employee",$B$2,"JCJob",$C15,"JCExtra",$D15,"JCCostCode",$E15,"WCCode",$B15,"WCState",$G15,"State",$H15,"PayID",$BB$12,"Units",AP15,"UnionID",$B$3,"UnionLocal",$F15,"UnionClass",$I15,"CertifiedClass",$J15)),0) -> 0 | CN15: =IF(AND(NOT(ISBLANK($C15)),NOT(ISBLANK($E15)),$A15="x"),IF(AQ15=0,0,[2]!TSImport("PRTime","","Time_NINE","","Date",$CM$11,"Employee",$B$2,"JCJob",$C15,"JCExtra",$D15,"JCCostCode",$E15,"WCCode",$B15,"WCState",$G15,"State",$H15,"PayID",$BC$12,"Units",AQ15,"UnionID",$B$3,"UnionLocal",$F15,"UnionClass",$I15,"CertifiedClass",$J15)),0) -> 0 | CO15: =IF(AND(NOT(ISBLANK($C15)),NOT(ISBLANK($E15)),$A15="x"),IF(AR15=0,0,[2]!TSImport("PRTime","","Time_NINE","","Date",$CM$11,"Employee",$B$2,"JCJob",$C15,"JCExtra",$D15,"JCCostCode",$E15,"WCCode",$B15,"WCState",$G15,"State",$H15,"PayID",$BD$12,"Units",AR15,"UnionID",$B$3,"UnionLocal",$F15,"UnionClass",$I15,"CertifiedClass",$J15)),0) -> 0 | CP15: =IF(AND(NOT(ISBLANK($C15)),NOT(ISBLANK($E15)),$A15="x"),IF(AS15=0,0,[2]!TSImport("PRTime","","Time_NINE","","Date",$CM$11,"Employee",$B$2,"JCJob",$C15,"JCExtra",$D15,"JCCostCode",$E15,"WCCode",$B15,"WCState",$G15,"State",$H15,"PayID",$BE$12,"Units",AS15,"UnionID",$B$3,"UnionLocal",$F15,"UnionClass",$I15,"CertifiedClass",$J15)),0) -> 0 | CQ15: =IF(AND(NOT(ISBLANK($C15)),NOT(ISBLANK($E15)),$A15="x"),IF(AT15=0,0,[2]!TSImport("PRTime","","Time_NINE","","Date",$CM$11,"Employee",$B$2,"JCJob",$C15,"JCExtra",$D15,"JCCostCode",$E15,"WCCode",$B15,"WCState",$G15,"State",$H15,"PayID",$BF$12,"Units",AT15,"UnionID",$B$3,"UnionLocal",$F15,"UnionClass",$I15,"CertifiedClass",$J15)),0) -> 0 | CR15: =IF(AND(NOT(ISBLANK($C15)),NOT(ISBLANK($E15)),$A15="x"),IF(AU15=0,0,[2]!TSImport("PRTime","","Time_NINE","","Date",$CM$11,"Employee",$B$2,"JCJob",$C15,"JCExtra",$D15,"JCCostCode",$E15,"WCCode",$B15,"WCState",$G15,"State",$H15,"PayID",$BG$12,"Units",AU15,"UnionID",$B$3,"UnionLocal",$F15,"UnionClass",$I15,"CertifiedClass",$J15)),0) -> 0 | CS15: =IF(AND(NOT(ISBLANK($C15)),NOT(ISBLANK($E15)),$A15="x"),IF(AV15=0,0,[2]!TSImport("PRTime","","Time_NINE","","Date",$CS$11,"Employee",$B$2,"JCJob",$C15,"JCExtra",$D15,"JCCostCode",$E15,"WCCode",$B15,"WCState",$G15,"State",$H15,"PayID",$BB$12,"Units",AV15,"UnionID",$B$3,"UnionLocal",$F15,"UnionClass",$I15,"CertifiedClass",$J15)),0) -> 0 | CT15: =IF(AND(NOT(ISBLANK($C15)),NOT(ISBLANK($E15)),$A15="x"),IF(AW15=0,0,[2]!TSImport("PRTime","","Time_NINE","","Date",$CS$11,"Employee",$B$2,"JCJob",$C15,"JCExtra",$D15,"JCCostCode",$E15,"WCCode",$B15,"WCState",$G15,"State",$H15,"PayID",$BC$12,"Units",AW15,"UnionID",$B$3,"UnionLocal",$F15,"UnionClass",$I15,"CertifiedClass",$J15)),0) -> 0 | CU15: =IF(AND(NOT(ISBLANK($C15)),NOT(ISBLANK($E15)),$A15="x"),IF(AX15=0,0,[2]!TSImport("PRTime","","Time_NINE","","Date",$CS$11,"Employee",$B$2,"JCJob",$C15,"JCExtra",$D15,"JCCostCode",$E15,"WCCode",$B15,"WCState",$G15,"State",$H15,"PayID",$BD$12,"Units",AX15,"UnionID",$B$3,"UnionLocal",$F15,"UnionClass",$I15,"CertifiedClass",$J15)),0) -> 0 | CV15: =IF(AND(NOT(ISBLANK($C15)),NOT(ISBLANK($E15)),$A15="x"),IF(AY15=0,0,[2]!TSImport("PRTime","","Time_NINE","","Date",$CS$11,"Employee",$B$2,"JCJob",$C15,"JCExtra",$D15,"JCCostCode",$E15,"WCCode",$B15,"WCState",$G15,"State",$H15,"PayID",$BE$12,"Units",AY15,"UnionID",$B$3,"UnionLocal",$F15,"UnionClass",$I15,"CertifiedClass",$J15)),0) -> 0 | CW15: =IF(AND(NOT(ISBLANK($C15)),NOT(ISBLANK($E15)),$A15="x"),IF(AZ15=0,0,[2]!TSImport("PRTime","","Time_NINE","","Date",$CS$11,"Employee",$B$2,"JCJob",$C15,"JCExtra",$D15,"JCCostCode",$E15,"WCCode",$B15,"WCState",$G15,"State",$H15,"PayID",$BF$12,"Units",AZ15,"UnionID",$B$3,"UnionLocal",$F15,"UnionClass",$I15,"CertifiedClass",$J15)),0) -> 0 | CX15: =IF(AND(NOT(ISBLANK($C15)),NOT(ISBLANK($E15)),$A15="x"),IF(BA15=0,0,[2]!TSImport("PRTime","","Time_NINE","","Date",$CS$11,"Employee",$B$2,"JCJob",$C15,"JCExtra",$D15,"JCCostCode",$E15,"WCCode",$B15,"WCState",$G15,"State",$H15,"PayID",$BG$12,"Units",BA15,"UnionID",$B$3,"UnionLocal",$F15,"UnionClass",$I15,"CertifiedClass",$J15)),0) -> 0
A16: =IF(ISBLANK(C16),"",IF(ISBLANK($D$3),"",$D$3)) | F16: =IF(ISBLANK($B$4),"",$B$4) | J16: =IF($K16=0,"",IF($K16<10,"0"&$K16,$K16)) | BB16: =SUM(AV16,AP16,AJ16,AD16,X16,R16,L16) -> 0 | BC16: =SUM(AW16,AQ16,AK16,AE16,Y16,S16,M16) -> 0 | BD16: =SUM(AX16,AR16,AL16,AF16,Z16,T16,N16) -> 0 | BE16: =SUM(AY16,AS16,AM16,AG16,AA16,U16,O16) -> 0 | BF16: =SUM(AZ16,AT16,AN16,AH16,AB16,V16,P16) -> 0 | BG16: =SUM(BA16,AU16,AO16,AI16,AC16,W16,Q16) -> 0 | BH16: =SUM(TimeSheet34[[#This Row],[1]:[4A]]) -> 0 | BI16: =IF(AND(NOT(ISBLANK($C16)),NOT(ISBLANK($E16)),$A16="x"),IF(L16=0,0,[2]!TSImport("PRTime","","Time_NINE","","Date",$BI$11,"Employee",$B$2,"JCJob",$C16,"JCExtra",$D16,"JCCostCode",$E16,"WCCode",$B16,"WCState",$G16,"State",$H16,"PayID",$BB$12,"Units",L16,"UnionID",$B$3,"UnionLocal",$F16,"UnionClass",$I16,"CertifiedClass",$J16)),0) -> 0 | BJ16: =IF(AND(NOT(ISBLANK($C16)),NOT(ISBLANK($E16)),$A16="x"),IF(M16=0,0,[2]!TSImport("PRTime","","Time_NINE","","Date",$BI$11,"Employee",$B$2,"JCJob",$C16,"JCExtra",$D16,"JCCostCode",$E16,"WCCode",$B16,"WCState",$G16,"State",$H16,"PayID",$BC$12,"Units",M16,"UnionID",$B$3,"UnionLocal",$F16,"UnionClass",$I16,"CertifiedClass",$J16)),0) -> 0 | BK16: =IF(AND(NOT(ISBLANK($C16)),NOT(ISBLANK($E16)),$A16="x"),IF(N16=0,0,[2]!TSImport("PRTime","","Time_NINE","","Date",$BI$11,"Employee",$B$2,"JCJob",$C16,"JCExtra",$D16,"JCCostCode",$E16,"WCCode",$B16,"WCState",$G16,"State",$H16,"PayID",$BD$12,"Units",N16,"UnionID",$B$3,"UnionLocal",$F16,"UnionClass",$I16,"CertifiedClass",$J16)),0) -> 0 | BL16: =IF(AND(NOT(ISBLANK($C16)),NOT(ISBLANK($E16)),$A16="x"),IF(O16=0,0,[2]!TSImport("PRTime","","Time_NINE","","Date",$BI$11,"Employee",$B$2,"JCJob",$C16,"JCExtra",$D16,"JCCostCode",$E16,"WCCode",$B16,"WCState",$G16,"State",$H16,"PayID",$BE$12,"Units",O16,"UnionID",$B$3,"UnionLocal",$F16,"UnionClass",$I16,"CertifiedClass",$J16)),0) -> 0 | BM16: =IF(AND(NOT(ISBLANK($C16)),NOT(ISBLANK($E16)),$A16="x"),IF(P16=0,0,[2]!TSImport("PRTime","","Time_NINE","","Date",$BI$11,"Employee",$B$2,"JCJob",$C16,"JCExtra",$D16,"JCCostCode",$E16,"WCCode",$B16,"WCState",$G16,"State",$H16,"PayID",$BF$12,"Units",P16,"UnionID",$B$3,"UnionLocal",$F16,"UnionClass",$I16,"CertifiedClass",$J16)),0) -> 0 | BN16: =IF(AND(NOT(ISBLANK($C16)),NOT(ISBLANK($E16)),$A16="x"),IF(Q16=0,0,[2]!TSImport("PRTime","","Time_NINE","","Date",$BI$11,"Employee",$B$2,"JCJob",$C16,"JCExtra",$D16,"JCCostCode",$E16,"WCCode",$B16,"WCState",$G16,"State",$H16,"PayID",$BG$12,"Units",Q16,"UnionID",$B$3,"UnionLocal",$F16,"UnionClass",$I16,"CertifiedClass",$J16)),0) -> 0 | BO16: =IF(AND(NOT(ISBLANK($C16)),NOT(ISBLANK($E16)),$A16="x"),IF(R16=0,0,[2]!TSImport("PRTime","","Time_NINE","","Date",$BO$11,"Employee",$B$2,"JCJob",$C16,"JCExtra",$D16,"JCCostCode",$E16,"WCCode",$B16,"WCState",$G16,"State",$H16,"PayID",$BB$12,"Units",R16,"UnionID",$B$3,"UnionLocal",$F16,"UnionClass",$I16,"CertifiedClass",$J16)),0) -> 0 | BP16: =IF(AND(NOT(ISBLANK($C16)),NOT(ISBLANK($E16)),$A16="x"),IF(S16=0,0,[2]!TSImport("PRTime","","Time_NINE","","Date",$BO$11,"Employee",$B$2,"JCJob",$C16,"JCExtra",$D16,"JCCostCode",$E16,"WCCode",$B16,"WCState",$G16,"State",$H16,"PayID",$BC$12,"Units",S16,"UnionID",$B$3,"UnionLocal",$F16,"UnionClass",$I16,"CertifiedClass",$J16)),0) -> 0 | BQ16: =IF(AND(NOT(ISBLANK($C16)),NOT(ISBLANK($E16)),$A16="x"),IF(T16=0,0,[2]!TSImport("PRTime","","Time_NINE","","Date",$BO$11,"Employee",$B$2,"JCJob",$C16,"JCExtra",$D16,"JCCostCode",$E16,"WCCode",$B16,"WCState",$G16,"State",$H16,"PayID",$BD$12,"Units",T16,"UnionID",$B$3,"UnionLocal",$F16,"UnionClass",$I16,"CertifiedClass",$J16)),0) -> 0 | BR16: =IF(AND(NOT(ISBLANK($C16)),NOT(ISBLANK($E16)),$A16="x"),IF(U16=0,0,[2]!TSImport("PRTime","","Time_NINE","","Date",$BO$11,"Employee",$B$2,"JCJob",$C16,"JCExtra",$D16,"JCCostCode",$E16,"WCCode",$B16,"WCState",$G16,"State",$H16,"PayID",$BE$12,"Units",U16,"UnionID",$B$3,"UnionLocal",$F16,"UnionClass",$I16,"CertifiedClass",$J16)),0) -> 0 | BS16: =IF(AND(NOT(ISBLANK($C16)),NOT(ISBLANK($E16)),$A16="x"),IF(V16=0,0,[2]!TSImport("PRTime","","Time_NINE","","Date",$BO$11,"Employee",$B$2,"JCJob",$C16,"JCExtra",$D16,"JCCostCode",$E16,"WCCode",$B16,"WCState",$G16,"State",$H16,"PayID",$BF$12,"Units",V16,"UnionID",$B$3,"UnionLocal",$F16,"UnionClass",$I16,"CertifiedClass",$J16)),0) -> 0 | BT16: =IF(AND(NOT(ISBLANK($C16)),NOT(ISBLANK($E16)),$A16="x"),IF(W16=0,0,[2]!TSImport("PRTime","","Time_NINE","","Date",$BO$11,"Employee",$B$2,"JCJob",$C16,"JCExtra",$D16,"JCCostCode",$E16,"WCCode",$B16,"WCState",$G16,"State",$H16,"PayID",$BG$12,"Units",W16,"UnionID",$B$3,"UnionLocal",$F16,"UnionClass",$I16,"CertifiedClass",$J16)),0) -> 0 | BU16: =IF(AND(NOT(ISBLANK($C16)),NOT(ISBLANK($E16)),$A16="x"),IF(X16=0,0,[2]!TSImport("PRTime","","Time_NINE","","Date",$BU$11,"Employee",$B$2,"JCJob",$C16,"JCExtra",$D16,"JCCostCode",$E16,"WCCode",$B16,"WCState",$G16,"State",$H16,"PayID",$BB$12,"Units",X16,"UnionID",$B$3,"UnionLocal",$F16,"UnionClass",$I16,"CertifiedClass",$J16)),0) -> 0 | BV16: =IF(AND(NOT(ISBLANK($C16)),NOT(ISBLANK($E16)),$A16="x"),IF(Y16=0,0,[2]!TSImport("PRTime","","Time_NINE","","Date",$BU$11,"Employee",$B$2,"JCJob",$C16,"JCExtra",$D16,"JCCostCode",$E16,"WCCode",$B16,"WCState",$G16,"State",$H16,"PayID",$BC$12,"Units",Y16,"UnionID",$B$3,"UnionLocal",$F16,"UnionClass",$I16,"CertifiedClass",$J16)),0) -> 0 | BW16: =IF(AND(NOT(ISBLANK($C16)),NOT(ISBLANK($E16)),$A16="x"),IF(Z16=0,0,[2]!TSImport("PRTime","","Time_NINE","","Date",$BU$11,"Employee",$B$2,"JCJob",$C16,"JCExtra",$D16,"JCCostCode",$E16,"WCCode",$B16,"WCState",$G16,"State",$H16,"PayID",$BD$12,"Units",Z16,"UnionID",$B$3,"UnionLocal",$F16,"UnionClass",$I16,"CertifiedClass",$J16)),0) -> 0 | BX16: =IF(AND(NOT(ISBLANK($C16)),NOT(ISBLANK($E16)),$A16="x"),IF(AA16=0,0,[2]!TSImport("PRTime","","Time_NINE","","Date",$BU$11,"Employee",$B$2,"JCJob",$C16,"JCExtra",$D16,"JCCostCode",$E16,"WCCode",$B16,"WCState",$G16,"State",$H16,"PayID",$BE$12,"Units",AA16,"UnionID",$B$3,"UnionLocal",$F16,"UnionClass",$I16,"CertifiedClass",$J16)),0) -> 0 | BY16: =IF(AND(NOT(ISBLANK($C16)),NOT(ISBLANK($E16)),$A16="x"),IF(AB16=0,0,[2]!TSImport("PRTime","","Time_NINE","","Date",$BU$11,"Employee",$B$2,"JCJob",$C16,"JCExtra",$D16,"JCCostCode",$E16,"WCCode",$B16,"WCState",$G16,"State",$H16,"PayID",$BF$12,"Units",AB16,"UnionID",$B$3,"UnionLocal",$F16,"UnionClass",$I16,"CertifiedClass",$J16)),0) -> 0 | BZ16: =IF(AND(NOT(ISBLANK($C16)),NOT(ISBLANK($E16)),$A16="x"),IF(AC16=0,0,[2]!TSImport("PRTime","","Time_NINE","","Date",$BU$11,"Employee",$B$2,"JCJob",$C16,"JCExtra",$D16,"JCCostCode",$E16,"WCCode",$B16,"WCState",$G16,"State",$H16,"PayID",$BG$12,"Units",AC16,"UnionID",$B$3,"UnionLocal",$F16,"UnionClass",$I16,"CertifiedClass",$J16)),0) -> 0 | CA16: =IF(AND(NOT(ISBLANK($C16)),NOT(ISBLANK($E16)),$A16="x"),IF(AD16=0,0,[2]!TSImport("PRTime","","Time_NINE","","Date",$CA$11,"Employee",$B$2,"JCJob",$C16,"JCExtra",$D16,"JCCostCode",$E16,"WCCode",$B16,"WCState",$G16,"State",$H16,"PayID",$BB$12,"Units",AD16,"UnionID",$B$3,"UnionLocal",$F16,"UnionClass",$I16,"CertifiedClass",$J16)),0) -> 0 | CB16: =IF(AND(NOT(ISBLANK($C16)),NOT(ISBLANK($E16)),$A16="x"),IF(AE16=0,0,[2]!TSImport("PRTime","","Time_NINE","","Date",$CA$11,"Employee",$B$2,"JCJob",$C16,"JCExtra",$D16,"JCCostCode",$E16,"WCCode",$B16,"WCState",$G16,"State",$H16,"PayID",$BC$12,"Units",AE16,"UnionID",$B$3,"UnionLocal",$F16,"UnionClass",$I16,"CertifiedClass",$J16)),0) -> 0 | CC16: =IF(AND(NOT(ISBLANK($C16)),NOT(ISBLANK($E16)),$A16="x"),IF(AF16=0,0,[2]!TSImport("PRTime","","Time_NINE","","Date",$CA$11,"Employee",$B$2,"JCJob",$C16,"JCExtra",$D16,"JCCostCode",$E16,"WCCode",$B16,"WCState",$G16,"State",$H16,"PayID",$BD$12,"Units",AF16,"UnionID",$B$3,"UnionLocal",$F16,"UnionClass",$I16,"CertifiedClass",$J16)),0) -> 0 | CD16: =IF(AND(NOT(ISBLANK($C16)),NOT(ISBLANK($E16)),$A16="x"),IF(AG16=0,0,[2]!TSImport("PRTime","","Time_NINE","","Date",$CA$11,"Employee",$B$2,"JCJob",$C16,"JCExtra",$D16,"JCCostCode",$E16,"WCCode",$B16,"WCState",$G16,"State",$H16,"PayID",$BE$12,"Units",AG16,"UnionID",$B$3,"UnionLocal",$F16,"UnionClass",$I16,"CertifiedClass",$J16)),0) -> 0 | CE16: =IF(AND(NOT(ISBLANK($C16)),NOT(ISBLANK($E16)),$A16="x"),IF(AH16=0,0,[2]!TSImport("PRTime","","Time_NINE","","Date",$CA$11,"Employee",$B$2,"JCJob",$C16,"JCExtra",$D16,"JCCostCode",$E16,"WCCode",$B16,"WCState",$G16,"State",$H16,"PayID",$BF$12,"Units",AH16,"UnionID",$B$3,"UnionLocal",$F16,"UnionClass",$I16,"CertifiedClass",$J16)),0) -> 0 | CF16: =IF(AND(NOT(ISBLANK($C16)),NOT(ISBLANK($E16)),$A16="x"),IF(AI16=0,0,[2]!TSImport("PRTime","","Time_NINE","","Date",$CA$11,"Employee",$B$2,"JCJob",$C16,"JCExtra",$D16,"JCCostCode",$E16,"WCCode",$B16,"WCState",$G16,"State",$H16,"PayID",$BG$12,"Units",AI16,"UnionID",$B$3,"UnionLocal",$F16,"UnionClass",$I16,"CertifiedClass",$J16)),0) -> 0 | CG16: =IF(AND(NOT(ISBLANK($C16)),NOT(ISBLANK($E16)),$A16="x"),IF(AJ16=0,0,[2]!TSImport("PRTime","","Time_NINE","","Date",$CG$11,"Employee",$B$2,"JCJob",$C16,"JCExtra",$D16,"JCCostCode",$E16,"WCCode",$B16,"WCState",$G16,"State",$H16,"PayID",$BB$12,"Units",AJ16,"UnionID",$B$3,"UnionLocal",$F16,"UnionClass",$I16,"CertifiedClass",$J16)),0) -> 0 | CH16: =IF(AND(NOT(ISBLANK($C16)),NOT(ISBLANK($E16)),$A16="x"),IF(AK16=0,0,[2]!TSImport("PRTime","","Time_NINE","","Date",$CG$11,"Employee",$B$2,"JCJob",$C16,"JCExtra",$D16,"JCCostCode",$E16,"WCCode",$B16,"WCState",$G16,"State",$H16,"PayID",$BC$12,"Units",AK16,"UnionID",$B$3,"UnionLocal",$F16,"UnionClass",$I16,"CertifiedClass",$J16)),0) -> 0 | CI16: =IF(AND(NOT(ISBLANK($C16)),NOT(ISBLANK($E16)),$A16="x"),IF(AL16=0,0,[2]!TSImport("PRTime","","Time_NINE","","Date",$CG$11,"Employee",$B$2,"JCJob",$C16,"JCExtra",$D16,"JCCostCode",$E16,"WCCode",$B16,"WCState",$G16,"State",$H16,"PayID",$BD$12,"Units",AL16,"UnionID",$B$3,"UnionLocal",$F16,"UnionClass",$I16,"CertifiedClass",$J16)),0) -> 0 | CJ16: =IF(AND(NOT(ISBLANK($C16)),NOT(ISBLANK($E16)),$A16="x"),IF(AM16=0,0,[2]!TSImport("PRTime","","Time_NINE","","Date",$CG$11,"Employee",$B$2,"JCJob",$C16,"JCExtra",$D16,"JCCostCode",$E16,"WCCode",$B16,"WCState",$G16,"State",$H16,"PayID",$BE$12,"Units",AM16,"UnionID",$B$3,"UnionLocal",$F16,"UnionClass",$I16,"CertifiedClass",$J16)),0) -> 0 | CK16: =IF(AND(NOT(ISBLANK($C16)),NOT(ISBLANK($E16)),$A16="x"),IF(AN16=0,0,[2]!TSImport("PRTime","","Time_NINE","","Date",$CG$11,"Employee",$B$2,"JCJob",$C16,"JCExtra",$D16,"JCCostCode",$E16,"WCCode",$B16,"WCState",$G16,"State",$H16,"PayID",$BF$12,"Units",AN16,"UnionID",$B$3,"UnionLocal",$F16,"UnionClass",$I16,"CertifiedClass",$J16)),0) -> 0 | CL16: =IF(AND(NOT(ISBLANK($C16)),NOT(ISBLANK($E16)),$A16="x"),IF(AO16=0,0,[2]!TSImport("PRTime","","Time_NINE","","Date",$CG$11,"Employee",$B$2,"JCJob",$C16,"JCExtra",$D16,"JCCostCode",$E16,"WCCode",$B16,"WCState",$G16,"State",$H16,"PayID",$BG$12,"Units",AO16,"UnionID",$B$3,"UnionLocal",$F16,"UnionClass",$I16,"CertifiedClass",$J16)),0) -> 0 | CM16: =IF(AND(NOT(ISBLANK($C16)),NOT(ISBLANK($E16)),$A16="x"),IF(AP16=0,0,[2]!TSImport("PRTime","","Time_NINE","","Date",$CM$11,"Employee",$B$2,"JCJob",$C16,"JCExtra",$D16,"JCCostCode",$E16,"WCCode",$B16,"WCState",$G16,"State",$H16,"PayID",$BB$12,"Units",AP16,"UnionID",$B$3,"UnionLocal",$F16,"UnionClass",$I16,"CertifiedClass",$J16)),0) -> 0 | CN16: =IF(AND(NOT(ISBLANK($C16)),NOT(ISBLANK($E16)),$A16="x"),IF(AQ16=0,0,[2]!TSImport("PRTime","","Time_NINE","","Date",$CM$11,"Employee",$B$2,"JCJob",$C16,"JCExtra",$D16,"JCCostCode",$E16,"WCCode",$B16,"WCState",$G16,"State",$H16,"PayID",$BC$12,"Units",AQ16,"UnionID",$B$3,"UnionLocal",$F16,"UnionClass",$I16,"CertifiedClass",$J16)),0) -> 0 | CO16: =IF(AND(NOT(ISBLANK($C16)),NOT(ISBLANK($E16)),$A16="x"),IF(AR16=0,0,[2]!TSImport("PRTime","","Time_NINE","","Date",$CM$11,"Employee",$B$2,"JCJob",$C16,"JCExtra",$D16,"JCCostCode",$E16,"WCCode",$B16,"WCState",$G16,"State",$H16,"PayID",$BD$12,"Units",AR16,"UnionID",$B$3,"UnionLocal",$F16,"UnionClass",$I16,"CertifiedClass",$J16)),0) -> 0 | CP16: =IF(AND(NOT(ISBLANK($C16)),NOT(ISBLANK($E16)),$A16="x"),IF(AS16=0,0,[2]!TSImport("PRTime","","Time_NINE","","Date",$CM$11,"Employee",$B$2,"JCJob",$C16,"JCExtra",$D16,"JCCostCode",$E16,"WCCode",$B16,"WCState",$G16,"State",$H16,"PayID",$BE$12,"Units",AS16,"UnionID",$B$3,"UnionLocal",$F16,"UnionClass",$I16,"CertifiedClass",$J16)),0) -> 0 | CQ16: =IF(AND(NOT(ISBLANK($C16)),NOT(ISBLANK($E16)),$A16="x"),IF(AT16=0,0,[2]!TSImport("PRTime","","Time_NINE","","Date",$CM$11,"Employee",$B$2,"JCJob",$C16,"JCExtra",$D16,"JCCostCode",$E16,"WCCode",$B16,"WCState",$G16,"State",$H16,"PayID",$BF$12,"Units",AT16,"UnionID",$B$3,"UnionLocal",$F16,"UnionClass",$I16,"CertifiedClass",$J16)),0) -> 0 | CR16: =IF(AND(NOT(ISBLANK($C16)),NOT(ISBLANK($E16)),$A16="x"),IF(AU16=0,0,[2]!TSImport("PRTime","","Time_NINE","","Date",$CM$11,"Employee",$B$2,"JCJob",$C16,"JCExtra",$D16,"JCCostCode",$E16,"WCCode",$B16,"WCState",$G16,"State",$H16,"PayID",$BG$12,"Units",AU16,"UnionID",$B$3,"UnionLocal",$F16,"UnionClass",$I16,"CertifiedClass",$J16)),0) -> 0 | CS16: =IF(AND(NOT(ISBLANK($C16)),NOT(ISBLANK($E16)),$A16="x"),IF(AV16=0,0,[2]!TSImport("PRTime","","Time_NINE","","Date",$CS$11,"Employee",$B$2,"JCJob",$C16,"JCExtra",$D16,"JCCostCode",$E16,"WCCode",$B16,"WCState",$G16,"State",$H16,"PayID",$BB$12,"Units",AV16,"UnionID",$B$3,"UnionLocal",$F16,"UnionClass",$I16,"CertifiedClass",$J16)),0) -> 0 | CT16: =IF(AND(NOT(ISBLANK($C16)),NOT(ISBLANK($E16)),$A16="x"),IF(AW16=0,0,[2]!TSImport("PRTime","","Time_NINE","","Date",$CS$11,"Employee",$B$2,"JCJob",$C16,"JCExtra",$D16,"JCCostCode",$E16,"WCCode",$B16,"WCState",$G16,"State",$H16,"PayID",$BC$12,"Units",AW16,"UnionID",$B$3,"UnionLocal",$F16,"UnionClass",$I16,"CertifiedClass",$J16)),0) -> 0 | CU16: =IF(AND(NOT(ISBLANK($C16)),NOT(ISBLANK($E16)),$A16="x"),IF(AX16=0,0,[2]!TSImport("PRTime","","Time_NINE","","Date",$CS$11,"Employee",$B$2,"JCJob",$C16,"JCExtra",$D16,"JCCostCode",$E16,"WCCode",$B16,"WCState",$G16,"State",$H16,"PayID",$BD$12,"Units",AX16,"UnionID",$B$3,"UnionLocal",$F16,"UnionClass",$I16,"CertifiedClass",$J16)),0) -> 0 | CV16: =IF(AND(NOT(ISBLANK($C16)),NOT(ISBLANK($E16)),$A16="x"),IF(AY16=0,0,[2]!TSImport("PRTime","","Time_NINE","","Date",$CS$11,"Employee",$B$2,"JCJob",$C16,"JCExtra",$D16,"JCCostCode",$E16,"WCCode",$B16,"WCState",$G16,"State",$H16,"PayID",$BE$12,"Units",AY16,"UnionID",$B$3,"UnionLocal",$F16,"UnionClass",$I16,"CertifiedClass",$J16)),0) -> 0 | CW16: =IF(AND(NOT(ISBLANK($C16)),NOT(ISBLANK($E16)),$A16="x"),IF(AZ16=0,0,[2]!TSImport("PRTime","","Time_NINE","","Date",$CS$11,"Employee",$B$2,"JCJob",$C16,"JCExtra",$D16,"JCCostCode",$E16,"WCCode",$B16,"WCState",$G16,"State",$H16,"PayID",$BF$12,"Units",AZ16,"UnionID",$B$3,"UnionLocal",$F16,"UnionClass",$I16,"CertifiedClass",$J16)),0) -> 0 | CX16: =IF(AND(NOT(ISBLANK($C16)),NOT(ISBLANK($E16)),$A16="x"),IF(BA16=0,0,[2]!TSImport("PRTime","","Time_NINE","","Date",$CS$11,"Employee",$B$2,"JCJob",$C16,"JCExtra",$D16,"JCCostCode",$E16,"WCCode",$B16,"WCState",$G16,"State",$H16,"PayID",$BG$12,"Units",BA16,"UnionID",$B$3,"UnionLocal",$F16,"UnionClass",$I16,"CertifiedClass",$J16)),0) -> 0
A17: =IF(ISBLANK(C17),"",IF(ISBLANK($D$3),"",$D$3)) | F17: =IF(ISBLANK($B$4),"",$B$4) | J17: =IF($K17=0,"",IF($K17<10,"0"&$K17,$K17)) | BB17: =SUM(AV17,AP17,AJ17,AD17,X17,R17,L17) -> 0 | BC17: =SUM(AW17,AQ17,AK17,AE17,Y17,S17,M17) -> 0 | BD17: =SUM(AX17,AR17,AL17,AF17,Z17,T17,N17) -> 0 | BE17: =SUM(AY17,AS17,AM17,AG17,AA17,U17,O17) -> 0 | BF17: =SUM(AZ17,AT17,AN17,AH17,AB17,V17,P17) -> 0 | BG17: =SUM(BA17,AU17,AO17,AI17,AC17,W17,Q17) -> 0 | BH17: =SUM(TimeSheet34[[#This Row],[1]:[4A]]) -> 0 | BI17: =IF(AND(NOT(ISBLANK($C17)),NOT(ISBLANK($E17)),$A17="x"),IF(L17=0,0,[2]!TSImport("PRTime","","Time_NINE","","Date",$BI$11,"Employee",$B$2,"JCJob",$C17,"JCExtra",$D17,"JCCostCode",$E17,"WCCode",$B17,"WCState",$G17,"State",$H17,"PayID",$BB$12,"Units",L17,"UnionID",$B$3,"UnionLocal",$F17,"UnionClass",$I17,"CertifiedClass",$J17)),0) -> 0 | BJ17: =IF(AND(NOT(ISBLANK($C17)),NOT(ISBLANK($E17)),$A17="x"),IF(M17=0,0,[2]!TSImport("PRTime","","Time_NINE","","Date",$BI$11,"Employee",$B$2,"JCJob",$C17,"JCExtra",$D17,"JCCostCode",$E17,"WCCode",$B17,"WCState",$G17,"State",$H17,"PayID",$BC$12,"Units",M17,"UnionID",$B$3,"UnionLocal",$F17,"UnionClass",$I17,"CertifiedClass",$J17)),0) -> 0 | BK17: =IF(AND(NOT(ISBLANK($C17)),NOT(ISBLANK($E17)),$A17="x"),IF(N17=0,0,[2]!TSImport("PRTime","","Time_NINE","","Date",$BI$11,"Employee",$B$2,"JCJob",$C17,"JCExtra",$D17,"JCCostCode",$E17,"WCCode",$B17,"WCState",$G17,"State",$H17,"PayID",$BD$12,"Units",N17,"UnionID",$B$3,"UnionLocal",$F17,"UnionClass",$I17,"CertifiedClass",$J17)),0) -> 0 | BL17: =IF(AND(NOT(ISBLANK($C17)),NOT(ISBLANK($E17)),$A17="x"),IF(O17=0,0,[2]!TSImport("PRTime","","Time_NINE","","Date",$BI$11,"Employee",$B$2,"JCJob",$C17,"JCExtra",$D17,"JCCostCode",$E17,"WCCode",$B17,"WCState",$G17,"State",$H17,"PayID",$BE$12,"Units",O17,"UnionID",$B$3,"UnionLocal",$F17,"UnionClass",$I17,"CertifiedClass",$J17)),0) -> 0 | BM17: =IF(AND(NOT(ISBLANK($C17)),NOT(ISBLANK($E17)),$A17="x"),IF(P17=0,0,[2]!TSImport("PRTime","","Time_NINE","","Date",$BI$11,"Employee",$B$2,"JCJob",$C17,"JCExtra",$D17,"JCCostCode",$E17,"WCCode",$B17,"WCState",$G17,"State",$H17,"PayID",$BF$12,"Units",P17,"UnionID",$B$3,"UnionLocal",$F17,"UnionClass",$I17,"CertifiedClass",$J17)),0) -> 0 | BN17: =IF(AND(NOT(ISBLANK($C17)),NOT(ISBLANK($E17)),$A17="x"),IF(Q17=0,0,[2]!TSImport("PRTime","","Time_NINE","","Date",$BI$11,"Employee",$B$2,"JCJob",$C17,"JCExtra",$D17,"JCCostCode",$E17,"WCCode",$B17,"WCState",$G17,"State",$H17,"PayID",$BG$12,"Units",Q17,"UnionID",$B$3,"UnionLocal",$F17,"UnionClass",$I17,"CertifiedClass",$J17)),0) -> 0 | BO17: =IF(AND(NOT(ISBLANK($C17)),NOT(ISBLANK($E17)),$A17="x"),IF(R17=0,0,[2]!TSImport("PRTime","","Time_NINE","","Date",$BO$11,"Employee",$B$2,"JCJob",$C17,"JCExtra",$D17,"JCCostCode",$E17,"WCCode",$B17,"WCState",$G17,"State",$H17,"PayID",$BB$12,"Units",R17,"UnionID",$B$3,"UnionLocal",$F17,"UnionClass",$I17,"CertifiedClass",$J17)),0) -> 0 | BP17: =IF(AND(NOT(ISBLANK($C17)),NOT(ISBLANK($E17)),$A17="x"),IF(S17=0,0,[2]!TSImport("PRTime","","Time_NINE","","Date",$BO$11,"Employee",$B$2,"JCJob",$C17,"JCExtra",$D17,"JCCostCode",$E17,"WCCode",$B17,"WCState",$G17,"State",$H17,"PayID",$BC$12,"Units",S17,"UnionID",$B$3,"UnionLocal",$F17,"UnionClass",$I17,"CertifiedClass",$J17)),0) -> 0 | BQ17: =IF(AND(NOT(ISBLANK($C17)),NOT(ISBLANK($E17)),$A17="x"),IF(T17=0,0,[2]!TSImport("PRTime","","Time_NINE","","Date",$BO$11,"Employee",$B$2,"JCJob",$C17,"JCExtra",$D17,"JCCostCode",$E17,"WCCode",$B17,"WCState",$G17,"State",$H17,"PayID",$BD$12,"Units",T17,"UnionID",$B$3,"UnionLocal",$F17,"UnionClass",$I17,"CertifiedClass",$J17)),0) -> 0 | BR17: =IF(AND(NOT(ISBLANK($C17)),NOT(ISBLANK($E17)),$A17="x"),IF(U17=0,0,[2]!TSImport("PRTime","","Time_NINE","","Date",$BO$11,"Employee",$B$2,"JCJob",$C17,"JCExtra",$D17,"JCCostCode",$E17,"WCCode",$B17,"WCState",$G17,"State",$H17,"PayID",$BE$12,"Units",U17,"UnionID",$B$3,"UnionLocal",$F17,"UnionClass",$I17,"CertifiedClass",$J17)),0) -> 0 | BS17: =IF(AND(NOT(ISBLANK($C17)),NOT(ISBLANK($E17)),$A17="x"),IF(V17=0,0,[2]!TSImport("PRTime","","Time_NINE","","Date",$BO$11,"Employee",$B$2,"JCJob",$C17,"JCExtra",$D17,"JCCostCode",$E17,"WCCode",$B17,"WCState",$G17,"State",$H17,"PayID",$BF$12,"Units",V17,"UnionID",$B$3,"UnionLocal",$F17,"UnionClass",$I17,"CertifiedClass",$J17)),0) -> 0 | BT17: =IF(AND(NOT(ISBLANK($C17)),NOT(ISBLANK($E17)),$A17="x"),IF(W17=0,0,[2]!TSImport("PRTime","","Time_NINE","","Date",$BO$11,"Employee",$B$2,"JCJob",$C17,"JCExtra",$D17,"JCCostCode",$E17,"WCCode",$B17,"WCState",$G17,"State",$H17,"PayID",$BG$12,"Units",W17,"UnionID",$B$3,"UnionLocal",$F17,"UnionClass",$I17,"CertifiedClass",$J17)),0) -> 0 | BU17: =IF(AND(NOT(ISBLANK($C17)),NOT(ISBLANK($E17)),$A17="x"),IF(X17=0,0,[2]!TSImport("PRTime","","Time_NINE","","Date",$BU$11,"Employee",$B$2,"JCJob",$C17,"JCExtra",$D17,"JCCostCode",$E17,"WCCode",$B17,"WCState",$G17,"State",$H17,"PayID",$BB$12,"Units",X17,"UnionID",$B$3,"UnionLocal",$F17,"UnionClass",$I17,"CertifiedClass",$J17)),0) -> 0 | BV17: =IF(AND(NOT(ISBLANK($C17)),NOT(ISBLANK($E17)),$A17="x"),IF(Y17=0,0,[2]!TSImport("PRTime","","Time_NINE","","Date",$BU$11,"Employee",$B$2,"JCJob",$C17,"JCExtra",$D17,"JCCostCode",$E17,"WCCode",$B17,"WCState",$G17,"State",$H17,"PayID",$BC$12,"Units",Y17,"UnionID",$B$3,"UnionLocal",$F17,"UnionClass",$I17,"CertifiedClass",$J17)),0) -> 0 | BW17: =IF(AND(NOT(ISBLANK($C17)),NOT(ISBLANK($E17)),$A17="x"),IF(Z17=0,0,[2]!TSImport("PRTime","","Time_NINE","","Date",$BU$11,"Employee",$B$2,"JCJob",$C17,"JCExtra",$D17,"JCCostCode",$E17,"WCCode",$B17,"WCState",$G17,"State",$H17,"PayID",$BD$12,"Units",Z17,"UnionID",$B$3,"UnionLocal",$F17,"UnionClass",$I17,"CertifiedClass",$J17)),0) -> 0 | BX17: =IF(AND(NOT(ISBLANK($C17)),NOT(ISBLANK($E17)),$A17="x"),IF(AA17=0,0,[2]!TSImport("PRTime","","Time_NINE","","Date",$BU$11,"Employee",$B$2,"JCJob",$C17,"JCExtra",$D17,"JCCostCode",$E17,"WCCode",$B17,"WCState",$G17,"State",$H17,"PayID",$BE$12,"Units",AA17,"UnionID",$B$3,"UnionLocal",$F17,"UnionClass",$I17,"CertifiedClass",$J17)),0) -> 0 | BY17: =IF(AND(NOT(ISBLANK($C17)),NOT(ISBLANK($E17)),$A17="x"),IF(AB17=0,0,[2]!TSImport("PRTime","","Time_NINE","","Date",$BU$11,"Employee",$B$2,"JCJob",$C17,"JCExtra",$D17,"JCCostCode",$E17,"WCCode",$B17,"WCState",$G17,"State",$H17,"PayID",$BF$12,"Units",AB17,"UnionID",$B$3,"UnionLocal",$F17,"UnionClass",$I17,"CertifiedClass",$J17)),0) -> 0 | BZ17: =IF(AND(NOT(ISBLANK($C17)),NOT(ISBLANK($E17)),$A17="x"),IF(AC17=0,0,[2]!TSImport("PRTime","","Time_NINE","","Date",$BU$11,"Employee",$B$2,"JCJob",$C17,"JCExtra",$D17,"JCCostCode",$E17,"WCCode",$B17,"WCState",$G17,"State",$H17,"PayID",$BG$12,"Units",AC17,"UnionID",$B$3,"UnionLocal",$F17,"UnionClass",$I17,"CertifiedClass",$J17)),0) -> 0 | CA17: =IF(AND(NOT(ISBLANK($C17)),NOT(ISBLANK($E17)),$A17="x"),IF(AD17=0,0,[2]!TSImport("PRTime","","Time_NINE","","Date",$CA$11,"Employee",$B$2,"JCJob",$C17,"JCExtra",$D17,"JCCostCode",$E17,"WCCode",$B17,"WCState",$G17,"State",$H17,"PayID",$BB$12,"Units",AD17,"UnionID",$B$3,"UnionLocal",$F17,"UnionClass",$I17,"CertifiedClass",$J17)),0) -> 0 | CB17: =IF(AND(NOT(ISBLANK($C17)),NOT(ISBLANK($E17)),$A17="x"),IF(AE17=0,0,[2]!TSImport("PRTime","","Time_NINE","","Date",$CA$11,"Employee",$B$2,"JCJob",$C17,"JCExtra",$D17,"JCCostCode",$E17,"WCCode",$B17,"WCState",$G17,"State",$H17,"PayID",$BC$12,"Units",AE17,"UnionID",$B$3,"UnionLocal",$F17,"UnionClass",$I17,"CertifiedClass",$J17)),0) -> 0 | CC17: =IF(AND(NOT(ISBLANK($C17)),NOT(ISBLANK($E17)),$A17="x"),IF(AF17=0,0,[2]!TSImport("PRTime","","Time_NINE","","Date",$CA$11,"Employee",$B$2,"JCJob",$C17,"JCExtra",$D17,"JCCostCode",$E17,"WCCode",$B17,"WCState",$G17,"State",$H17,"PayID",$BD$12,"Units",AF17,"UnionID",$B$3,"UnionLocal",$F17,"UnionClass",$I17,"CertifiedClass",$J17)),0) -> 0 | CD17: =IF(AND(NOT(ISBLANK($C17)),NOT(ISBLANK($E17)),$A17="x"),IF(AG17=0,0,[2]!TSImport("PRTime","","Time_NINE","","Date",$CA$11,"Employee",$B$2,"JCJob",$C17,"JCExtra",$D17,"JCCostCode",$E17,"WCCode",$B17,"WCState",$G17,"State",$H17,"PayID",$BE$12,"Units",AG17,"UnionID",$B$3,"UnionLocal",$F17,"UnionClass",$I17,"CertifiedClass",$J17)),0) -> 0 | CE17: =IF(AND(NOT(ISBLANK($C17)),NOT(ISBLANK($E17)),$A17="x"),IF(AH17=0,0,[2]!TSImport("PRTime","","Time_NINE","","Date",$CA$11,"Employee",$B$2,"JCJob",$C17,"JCExtra",$D17,"JCCostCode",$E17,"WCCode",$B17,"WCState",$G17,"State",$H17,"PayID",$BF$12,"Units",AH17,"UnionID",$B$3,"UnionLocal",$F17,"UnionClass",$I17,"CertifiedClass",$J17)),0) -> 0 | CF17: =IF(AND(NOT(ISBLANK($C17)),NOT(ISBLANK($E17)),$A17="x"),IF(AI17=0,0,[2]!TSImport("PRTime","","Time_NINE","","Date",$CA$11,"Employee",$B$2,"JCJob",$C17,"JCExtra",$D17,"JCCostCode",$E17,"WCCode",$B17,"WCState",$G17,"State",$H17,"PayID",$BG$12,"Units",AI17,"UnionID",$B$3,"UnionLocal",$F17,"UnionClass",$I17,"CertifiedClass",$J17)),0) -> 0 | CG17: =IF(AND(NOT(ISBLANK($C17)),NOT(ISBLANK($E17)),$A17="x"),IF(AJ17=0,0,[2]!TSImport("PRTime","","Time_NINE","","Date",$CG$11,"Employee",$B$2,"JCJob",$C17,"JCExtra",$D17,"JCCostCode",$E17,"WCCode",$B17,"WCState",$G17,"State",$H17,"PayID",$BB$12,"Units",AJ17,"UnionID",$B$3,"UnionLocal",$F17,"UnionClass",$I17,"CertifiedClass",$J17)),0) -> 0 | CH17: =IF(AND(NOT(ISBLANK($C17)),NOT(ISBLANK($E17)),$A17="x"),IF(AK17=0,0,[2]!TSImport("PRTime","","Time_NINE","","Date",$CG$11,"Employee",$B$2,"JCJob",$C17,"JCExtra",$D17,"JCCostCode",$E17,"WCCode",$B17,"WCState",$G17,"State",$H17,"PayID",$BC$12,"Units",AK17,"UnionID",$B$3,"UnionLocal",$F17,"UnionClass",$I17,"CertifiedClass",$J17)),0) -> 0 | CI17: =IF(AND(NOT(ISBLANK($C17)),NOT(ISBLANK($E17)),$A17="x"),IF(AL17=0,0,[2]!TSImport("PRTime","","Time_NINE","","Date",$CG$11,"Employee",$B$2,"JCJob",$C17,"JCExtra",$D17,"JCCostCode",$E17,"WCCode",$B17,"WCState",$G17,"State",$H17,"PayID",$BD$12,"Units",AL17,"UnionID",$B$3,"UnionLocal",$F17,"UnionClass",$I17,"CertifiedClass",$J17)),0) -> 0 | CJ17: =IF(AND(NOT(ISBLANK($C17)),NOT(ISBLANK($E17)),$A17="x"),IF(AM17=0,0,[2]!TSImport("PRTime","","Time_NINE","","Date",$CG$11,"Employee",$B$2,"JCJob",$C17,"JCExtra",$D17,"JCCostCode",$E17,"WCCode",$B17,"WCState",$G17,"State",$H17,"PayID",$BE$12,"Units",AM17,"UnionID",$B$3,"UnionLocal",$F17,"UnionClass",$I17,"CertifiedClass",$J17)),0) -> 0 | CK17: =IF(AND(NOT(ISBLANK($C17)),NOT(ISBLANK($E17)),$A17="x"),IF(AN17=0,0,[2]!TSImport("PRTime","","Time_NINE","","Date",$CG$11,"Employee",$B$2,"JCJob",$C17,"JCExtra",$D17,"JCCostCode",$E17,"WCCode",$B17,"WCState",$G17,"State",$H17,"PayID",$BF$12,"Units",AN17,"UnionID",$B$3,"UnionLocal",$F17,"UnionClass",$I17,"CertifiedClass",$J17)),0) -> 0 | CL17: =IF(AND(NOT(ISBLANK($C17)),NOT(ISBLANK($E17)),$A17="x"),IF(AO17=0,0,[2]!TSImport("PRTime","","Time_NINE","","Date",$CG$11,"Employee",$B$2,"JCJob",$C17,"JCExtra",$D17,"JCCostCode",$E17,"WCCode",$B17,"WCState",$G17,"State",$H17,"PayID",$BG$12,"Units",AO17,"UnionID",$B$3,"UnionLocal",$F17,"UnionClass",$I17,"CertifiedClass",$J17)),0) -> 0 | CM17: =IF(AND(NOT(ISBLANK($C17)),NOT(ISBLANK($E17)),$A17="x"),IF(AP17=0,0,[2]!TSImport("PRTime","","Time_NINE","","Date",$CM$11,"Employee",$B$2,"JCJob",$C17,"JCExtra",$D17,"JCCostCode",$E17,"WCCode",$B17,"WCState",$G17,"State",$H17,"PayID",$BB$12,"Units",AP17,"UnionID",$B$3,"UnionLocal",$F17,"UnionClass",$I17,"CertifiedClass",$J17)),0) -> 0 | CN17: =IF(AND(NOT(ISBLANK($C17)),NOT(ISBLANK($E17)),$A17="x"),IF(AQ17=0,0,[2]!TSImport("PRTime","","Time_NINE","","Date",$CM$11,"Employee",$B$2,"JCJob",$C17,"JCExtra",$D17,"JCCostCode",$E17,"WCCode",$B17,"WCState",$G17,"State",$H17,"PayID",$BC$12,"Units",AQ17,"UnionID",$B$3,"UnionLocal",$F17,"UnionClass",$I17,"CertifiedClass",$J17)),0) -> 0 | CO17: =IF(AND(NOT(ISBLANK($C17)),NOT(ISBLANK($E17)),$A17="x"),IF(AR17=0,0,[2]!TSImport("PRTime","","Time_NINE","","Date",$CM$11,"Employee",$B$2,"JCJob",$C17,"JCExtra",$D17,"JCCostCode",$E17,"WCCode",$B17,"WCState",$G17,"State",$H17,"PayID",$BD$12,"Units",AR17,"UnionID",$B$3,"UnionLocal",$F17,"UnionClass",$I17,"CertifiedClass",$J17)),0) -> 0 | CP17: =IF(AND(NOT(ISBLANK($C17)),NOT(ISBLANK($E17)),$A17="x"),IF(AS17=0,0,[2]!TSImport("PRTime","","Time_NINE","","Date",$CM$11,"Employee",$B$2,"JCJob",$C17,"JCExtra",$D17,"JCCostCode",$E17,"WCCode",$B17,"WCState",$G17,"State",$H17,"PayID",$BE$12,"Units",AS17,"UnionID",$B$3,"UnionLocal",$F17,"UnionClass",$I17,"CertifiedClass",$J17)),0) -> 0 | CQ17: =IF(AND(NOT(ISBLANK($C17)),NOT(ISBLANK($E17)),$A17="x"),IF(AT17=0,0,[2]!TSImport("PRTime","","Time_NINE","","Date",$CM$11,"Employee",$B$2,"JCJob",$C17,"JCExtra",$D17,"JCCostCode",$E17,"WCCode",$B17,"WCState",$G17,"State",$H17,"PayID",$BF$12,"Units",AT17,"UnionID",$B$3,"UnionLocal",$F17,"UnionClass",$I17,"CertifiedClass",$J17)),0) -> 0 | CR17: =IF(AND(NOT(ISBLANK($C17)),NOT(ISBLANK($E17)),$A17="x"),IF(AU17=0,0,[2]!TSImport("PRTime","","Time_NINE","","Date",$CM$11,"Employee",$B$2,"JCJob",$C17,"JCExtra",$D17,"JCCostCode",$E17,"WCCode",$B17,"WCState",$G17,"State",$H17,"PayID",$BG$12,"Units",AU17,"UnionID",$B$3,"UnionLocal",$F17,"UnionClass",$I17,"CertifiedClass",$J17)),0) -> 0 | CS17: =IF(AND(NOT(ISBLANK($C17)),NOT(ISBLANK($E17)),$A17="x"),IF(AV17=0,0,[2]!TSImport("PRTime","","Time_NINE","","Date",$CS$11,"Employee",$B$2,"JCJob",$C17,"JCExtra",$D17,"JCCostCode",$E17,"WCCode",$B17,"WCState",$G17,"State",$H17,"PayID",$BB$12,"Units",AV17,"UnionID",$B$3,"UnionLocal",$F17,"UnionClass",$I17,"CertifiedClass",$J17)),0) -> 0 | CT17: =IF(AND(NOT(ISBLANK($C17)),NOT(ISBLANK($E17)),$A17="x"),IF(AW17=0,0,[2]!TSImport("PRTime","","Time_NINE","","Date",$CS$11,"Employee",$B$2,"JCJob",$C17,"JCExtra",$D17,"JCCostCode",$E17,"WCCode",$B17,"WCState",$G17,"State",$H17,"PayID",$BC$12,"Units",AW17,"UnionID",$B$3,"UnionLocal",$F17,"UnionClass",$I17,"CertifiedClass",$J17)),0) -> 0 | CU17: =IF(AND(NOT(ISBLANK($C17)),NOT(ISBLANK($E17)),$A17="x"),IF(AX17=0,0,[2]!TSImport("PRTime","","Time_NINE","","Date",$CS$11,"Employee",$B$2,"JCJob",$C17,"JCExtra",$D17,"JCCostCode",$E17,"WCCode",$B17,"WCState",$G17,"State",$H17,"PayID",$BD$12,"Units",AX17,"UnionID",$B$3,"UnionLocal",$F17,"UnionClass",$I17,"CertifiedClass",$J17)),0) -> 0 | CV17: =IF(AND(NOT(ISBLANK($C17)),NOT(ISBLANK($E17)),$A17="x"),IF(AY17=0,0,[2]!TSImport("PRTime","","Time_NINE","","Date",$CS$11,"Employee",$B$2,"JCJob",$C17,"JCExtra",$D17,"JCCostCode",$E17,"WCCode",$B17,"WCState",$G17,"State",$H17,"PayID",$BE$12,"Units",AY17,"UnionID",$B$3,"UnionLocal",$F17,"UnionClass",$I17,"CertifiedClass",$J17)),0) -> 0 | CW17: =IF(AND(NOT(ISBLANK($C17)),NOT(ISBLANK($E17)),$A17="x"),IF(AZ17=0,0,[2]!TSImport("PRTime","","Time_NINE","","Date",$CS$11,"Employee",$B$2,"JCJob",$C17,"JCExtra",$D17,"JCCostCode",$E17,"WCCode",$B17,"WCState",$G17,"State",$H17,"PayID",$BF$12,"Units",AZ17,"UnionID",$B$3,"UnionLocal",$F17,"UnionClass",$I17,"CertifiedClass",$J17)),0) -> 0 | CX17: =IF(AND(NOT(ISBLANK($C17)),NOT(ISBLANK($E17)),$A17="x"),IF(BA17=0,0,[2]!TSImport("PRTime","","Time_NINE","","Date",$CS$11,"Employee",$B$2,"JCJob",$C17,"JCExtra",$D17,"JCCostCode",$E17,"WCCode",$B17,"WCState",$G17,"State",$H17,"PayID",$BG$12,"Units",BA17,"UnionID",$B$3,"UnionLocal",$F17,"UnionClass",$I17,"CertifiedClass",$J17)),0) -> 0
A18: =IF(ISBLANK(C18),"",IF(ISBLANK($D$3),"",$D$3)) | F18: =IF(ISBLANK($B$4),"",$B$4) | J18: =IF($K18=0,"",IF($K18<10,"0"&$K18,$K18)) | BB18: =SUM(AV18,AP18,AJ18,AD18,X18,R18,L18) -> 0 | BC18: =SUM(AW18,AQ18,AK18,AE18,Y18,S18,M18) -> 0 | BD18: =SUM(AX18,AR18,AL18,AF18,Z18,T18,N18) -> 0 | BE18: =SUM(AY18,AS18,AM18,AG18,AA18,U18,O18) -> 0 | BF18: =SUM(AZ18,AT18,AN18,AH18,AB18,V18,P18) -> 0 | BG18: =SUM(BA18,AU18,AO18,AI18,AC18,W18,Q18) -> 0 | BH18: =SUM(TimeSheet34[[#This Row],[1]:[4A]]) -> 0 | BI18: =IF(AND(NOT(ISBLANK($C18)),NOT(ISBLANK($E18)),$A18="x"),IF(L18=0,0,[2]!TSImport("PRTime","","Time_NINE","","Date",$BI$11,"Employee",$B$2,"JCJob",$C18,"JCExtra",$D18,"JCCostCode",$E18,"WCCode",$B18,"WCState",$G18,"State",$H18,"PayID",$BB$12,"Units",L18,"UnionID",$B$3,"UnionLocal",$F18,"UnionClass",$I18,"CertifiedClass",$J18)),0) -> 0 | BJ18: =IF(AND(NOT(ISBLANK($C18)),NOT(ISBLANK($E18)),$A18="x"),IF(M18=0,0,[2]!TSImport("PRTime","","Time_NINE","","Date",$BI$11,"Employee",$B$2,"JCJob",$C18,"JCExtra",$D18,"JCCostCode",$E18,"WCCode",$B18,"WCState",$G18,"State",$H18,"PayID",$BC$12,"Units",M18,"UnionID",$B$3,"UnionLocal",$F18,"UnionClass",$I18,"CertifiedClass",$J18)),0) -> 0 | BK18: =IF(AND(NOT(ISBLANK($C18)),NOT(ISBLANK($E18)),$A18="x"),IF(N18=0,0,[2]!TSImport("PRTime","","Time_NINE","","Date",$BI$11,"Employee",$B$2,"JCJob",$C18,"JCExtra",$D18,"JCCostCode",$E18,"WCCode",$B18,"WCState",$G18,"State",$H18,"PayID",$BD$12,"Units",N18,"UnionID",$B$3,"UnionLocal",$F18,"UnionClass",$I18,"CertifiedClass",$J18)),0) -> 0 | BL18: =IF(AND(NOT(ISBLANK($C18)),NOT(ISBLANK($E18)),$A18="x"),IF(O18=0,0,[2]!TSImport("PRTime","","Time_NINE","","Date",$BI$11,"Employee",$B$2,"JCJob",$C18,"JCExtra",$D18,"JCCostCode",$E18,"WCCode",$B18,"WCState",$G18,"State",$H18,"PayID",$BE$12,"Units",O18,"UnionID",$B$3,"UnionLocal",$F18,"UnionClass",$I18,"CertifiedClass",$J18)),0) -> 0 | BM18: =IF(AND(NOT(ISBLANK($C18)),NOT(ISBLANK($E18)),$A18="x"),IF(P18=0,0,[2]!TSImport("PRTime","","Time_NINE","","Date",$BI$11,"Employee",$B$2,"JCJob",$C18,"JCExtra",$D18,"JCCostCode",$E18,"WCCode",$B18,"WCState",$G18,"State",$H18,"PayID",$BF$12,"Units",P18,"UnionID",$B$3,"UnionLocal",$F18,"UnionClass",$I18,"CertifiedClass",$J18)),0) -> 0 | BN18: =IF(AND(NOT(ISBLANK($C18)),NOT(ISBLANK($E18)),$A18="x"),IF(Q18=0,0,[2]!TSImport("PRTime","","Time_NINE","","Date",$BI$11,"Employee",$B$2,"JCJob",$C18,"JCExtra",$D18,"JCCostCode",$E18,"WCCode",$B18,"WCState",$G18,"State",$H18,"PayID",$BG$12,"Units",Q18,"UnionID",$B$3,"UnionLocal",$F18,"UnionClass",$I18,"CertifiedClass",$J18)),0) -> 0 | BO18: =IF(AND(NOT(ISBLANK($C18)),NOT(ISBLANK($E18)),$A18="x"),IF(R18=0,0,[2]!TSImport("PRTime","","Time_NINE","","Date",$BO$11,"Employee",$B$2,"JCJob",$C18,"JCExtra",$D18,"JCCostCode",$E18,"WCCode",$B18,"WCState",$G18,"State",$H18,"PayID",$BB$12,"Units",R18,"UnionID",$B$3,"UnionLocal",$F18,"UnionClass",$I18,"CertifiedClass",$J18)),0) -> 0 | BP18: =IF(AND(NOT(ISBLANK($C18)),NOT(ISBLANK($E18)),$A18="x"),IF(S18=0,0,[2]!TSImport("PRTime","","Time_NINE","","Date",$BO$11,"Employee",$B$2,"JCJob",$C18,"JCExtra",$D18,"JCCostCode",$E18,"WCCode",$B18,"WCState",$G18,"State",$H18,"PayID",$BC$12,"Units",S18,"UnionID",$B$3,"UnionLocal",$F18,"UnionClass",$I18,"CertifiedClass",$J18)),0) -> 0 | BQ18: =IF(AND(NOT(ISBLANK($C18)),NOT(ISBLANK($E18)),$A18="x"),IF(T18=0,0,[2]!TSImport("PRTime","","Time_NINE","","Date",$BO$11,"Employee",$B$2,"JCJob",$C18,"JCExtra",$D18,"JCCostCode",$E18,"WCCode",$B18,"WCState",$G18,"State",$H18,"PayID",$BD$12,"Units",T18,"UnionID",$B$3,"UnionLocal",$F18,"UnionClass",$I18,"CertifiedClass",$J18)),0) -> 0 | BR18: =IF(AND(NOT(ISBLANK($C18)),NOT(ISBLANK($E18)),$A18="x"),IF(U18=0,0,[2]!TSImport("PRTime","","Time_NINE","","Date",$BO$11,"Employee",$B$2,"JCJob",$C18,"JCExtra",$D18,"JCCostCode",$E18,"WCCode",$B18,"WCState",$G18,"State",$H18,"PayID",$BE$12,"Units",U18,"UnionID",$B$3,"UnionLocal",$F18,"UnionClass",$I18,"CertifiedClass",$J18)),0) -> 0 | BS18: =IF(AND(NOT(ISBLANK($C18)),NOT(ISBLANK($E18)),$A18="x"),IF(V18=0,0,[2]!TSImport("PRTime","","Time_NINE","","Date",$BO$11,"Employee",$B$2,"JCJob",$C18,"JCExtra",$D18,"JCCostCode",$E18,"WCCode",$B18,"WCState",$G18,"State",$H18,"PayID",$BF$12,"Units",V18,"UnionID",$B$3,"UnionLocal",$F18,"UnionClass",$I18,"CertifiedClass",$J18)),0) -> 0 | BT18: =IF(AND(NOT(ISBLANK($C18)),NOT(ISBLANK($E18)),$A18="x"),IF(W18=0,0,[2]!TSImport("PRTime","","Time_NINE","","Date",$BO$11,"Employee",$B$2,"JCJob",$C18,"JCExtra",$D18,"JCCostCode",$E18,"WCCode",$B18,"WCState",$G18,"State",$H18,"PayID",$BG$12,"Units",W18,"UnionID",$B$3,"UnionLocal",$F18,"UnionClass",$I18,"CertifiedClass",$J18)),0) -> 0 | BU18: =IF(AND(NOT(ISBLANK($C18)),NOT(ISBLANK($E18)),$A18="x"),IF(X18=0,0,[2]!TSImport("PRTime","","Time_NINE","","Date",$BU$11,"Employee",$B$2,"JCJob",$C18,"JCExtra",$D18,"JCCostCode",$E18,"WCCode",$B18,"WCState",$G18,"State",$H18,"PayID",$BB$12,"Units",X18,"UnionID",$B$3,"UnionLocal",$F18,"UnionClass",$I18,"CertifiedClass",$J18)),0) -> 0 | BV18: =IF(AND(NOT(ISBLANK($C18)),NOT(ISBLANK($E18)),$A18="x"),IF(Y18=0,0,[2]!TSImport("PRTime","","Time_NINE","","Date",$BU$11,"Employee",$B$2,"JCJob",$C18,"JCExtra",$D18,"JCCostCode",$E18,"WCCode",$B18,"WCState",$G18,"State",$H18,"PayID",$BC$12,"Units",Y18,"UnionID",$B$3,"UnionLocal",$F18,"UnionClass",$I18,"CertifiedClass",$J18)),0) -> 0 | BW18: =IF(AND(NOT(ISBLANK($C18)),NOT(ISBLANK($E18)),$A18="x"),IF(Z18=0,0,[2]!TSImport("PRTime","","Time_NINE","","Date",$BU$11,"Employee",$B$2,"JCJob",$C18,"JCExtra",$D18,"JCCostCode",$E18,"WCCode",$B18,"WCState",$G18,"State",$H18,"PayID",$BD$12,"Units",Z18,"UnionID",$B$3,"UnionLocal",$F18,"UnionClass",$I18,"CertifiedClass",$J18)),0) -> 0 | BX18: =IF(AND(NOT(ISBLANK($C18)),NOT(ISBLANK($E18)),$A18="x"),IF(AA18=0,0,[2]!TSImport("PRTime","","Time_NINE","","Date",$BU$11,"Employee",$B$2,"JCJob",$C18,"JCExtra",$D18,"JCCostCode",$E18,"WCCode",$B18,"WCState",$G18,"State",$H18,"PayID",$BE$12,"Units",AA18,"UnionID",$B$3,"UnionLocal",$F18,"UnionClass",$I18,"CertifiedClass",$J18)),0) -> 0 | BY18: =IF(AND(NOT(ISBLANK($C18)),NOT(ISBLANK($E18)),$A18="x"),IF(AB18=0,0,[2]!TSImport("PRTime","","Time_NINE","","Date",$BU$11,"Employee",$B$2,"JCJob",$C18,"JCExtra",$D18,"JCCostCode",$E18,"WCCode",$B18,"WCState",$G18,"State",$H18,"PayID",$BF$12,"Units",AB18,"UnionID",$B$3,"UnionLocal",$F18,"UnionClass",$I18,"CertifiedClass",$J18)),0) -> 0 | BZ18: =IF(AND(NOT(ISBLANK($C18)),NOT(ISBLANK($E18)),$A18="x"),IF(AC18=0,0,[2]!TSImport("PRTime","","Time_NINE","","Date",$BU$11,"Employee",$B$2,"JCJob",$C18,"JCExtra",$D18,"JCCostCode",$E18,"WCCode",$B18,"WCState",$G18,"State",$H18,"PayID",$BG$12,"Units",AC18,"UnionID",$B$3,"UnionLocal",$F18,"UnionClass",$I18,"CertifiedClass",$J18)),0) -> 0 | CA18: =IF(AND(NOT(ISBLANK($C18)),NOT(ISBLANK($E18)),$A18="x"),IF(AD18=0,0,[2]!TSImport("PRTime","","Time_NINE","","Date",$CA$11,"Employee",$B$2,"JCJob",$C18,"JCExtra",$D18,"JCCostCode",$E18,"WCCode",$B18,"WCState",$G18,"State",$H18,"PayID",$BB$12,"Units",AD18,"UnionID",$B$3,"UnionLocal",$F18,"UnionClass",$I18,"CertifiedClass",$J18)),0) -> 0 | CB18: =IF(AND(NOT(ISBLANK($C18)),NOT(ISBLANK($E18)),$A18="x"),IF(AE18=0,0,[2]!TSImport("PRTime","","Time_NINE","","Date",$CA$11,"Employee",$B$2,"JCJob",$C18,"JCExtra",$D18,"JCCostCode",$E18,"WCCode",$B18,"WCState",$G18,"State",$H18,"PayID",$BC$12,"Units",AE18,"UnionID",$B$3,"UnionLocal",$F18,"UnionClass",$I18,"CertifiedClass",$J18)),0) -> 0 | CC18: =IF(AND(NOT(ISBLANK($C18)),NOT(ISBLANK($E18)),$A18="x"),IF(AF18=0,0,[2]!TSImport("PRTime","","Time_NINE","","Date",$CA$11,"Employee",$B$2,"JCJob",$C18,"JCExtra",$D18,"JCCostCode",$E18,"WCCode",$B18,"WCState",$G18,"State",$H18,"PayID",$BD$12,"Units",AF18,"UnionID",$B$3,"UnionLocal",$F18,"UnionClass",$I18,"CertifiedClass",$J18)),0) -> 0 | CD18: =IF(AND(NOT(ISBLANK($C18)),NOT(ISBLANK($E18)),$A18="x"),IF(AG18=0,0,[2]!TSImport("PRTime","","Time_NINE","","Date",$CA$11,"Employee",$B$2,"JCJob",$C18,"JCExtra",$D18,"JCCostCode",$E18,"WCCode",$B18,"WCState",$G18,"State",$H18,"PayID",$BE$12,"Units",AG18,"UnionID",$B$3,"UnionLocal",$F18,"UnionClass",$I18,"CertifiedClass",$J18)),0) -> 0 | CE18: =IF(AND(NOT(ISBLANK($C18)),NOT(ISBLANK($E18)),$A18="x"),IF(AH18=0,0,[2]!TSImport("PRTime","","Time_NINE","","Date",$CA$11,"Employee",$B$2,"JCJob",$C18,"JCExtra",$D18,"JCCostCode",$E18,"WCCode",$B18,"WCState",$G18,"State",$H18,"PayID",$BF$12,"Units",AH18,"UnionID",$B$3,"UnionLocal",$F18,"UnionClass",$I18,"CertifiedClass",$J18)),0) -> 0 | CF18: =IF(AND(NOT(ISBLANK($C18)),NOT(ISBLANK($E18)),$A18="x"),IF(AI18=0,0,[2]!TSImport("PRTime","","Time_NINE","","Date",$CA$11,"Employee",$B$2,"JCJob",$C18,"JCExtra",$D18,"JCCostCode",$E18,"WCCode",$B18,"WCState",$G18,"State",$H18,"PayID",$BG$12,"Units",AI18,"UnionID",$B$3,"UnionLocal",$F18,"UnionClass",$I18,"CertifiedClass",$J18)),0) -> 0 | CG18: =IF(AND(NOT(ISBLANK($C18)),NOT(ISBLANK($E18)),$A18="x"),IF(AJ18=0,0,[2]!TSImport("PRTime","","Time_NINE","","Date",$CG$11,"Employee",$B$2,"JCJob",$C18,"JCExtra",$D18,"JCCostCode",$E18,"WCCode",$B18,"WCState",$G18,"State",$H18,"PayID",$BB$12,"Units",AJ18,"UnionID",$B$3,"UnionLocal",$F18,"UnionClass",$I18,"CertifiedClass",$J18)),0) -> 0 | CH18: =IF(AND(NOT(ISBLANK($C18)),NOT(ISBLANK($E18)),$A18="x"),IF(AK18=0,0,[2]!TSImport("PRTime","","Time_NINE","","Date",$CG$11,"Employee",$B$2,"JCJob",$C18,"JCExtra",$D18,"JCCostCode",$E18,"WCCode",$B18,"WCState",$G18,"State",$H18,"PayID",$BC$12,"Units",AK18,"UnionID",$B$3,"UnionLocal",$F18,"UnionClass",$I18,"CertifiedClass",$J18)),0) -> 0 | CI18: =IF(AND(NOT(ISBLANK($C18)),NOT(ISBLANK($E18)),$A18="x"),IF(AL18=0,0,[2]!TSImport("PRTime","","Time_NINE","","Date",$CG$11,"Employee",$B$2,"JCJob",$C18,"JCExtra",$D18,"JCCostCode",$E18,"WCCode",$B18,"WCState",$G18,"State",$H18,"PayID",$BD$12,"Units",AL18,"UnionID",$B$3,"UnionLocal",$F18,"UnionClass",$I18,"CertifiedClass",$J18)),0) -> 0 | CJ18: =IF(AND(NOT(ISBLANK($C18)),NOT(ISBLANK($E18)),$A18="x"),IF(AM18=0,0,[2]!TSImport("PRTime","","Time_NINE","","Date",$CG$11,"Employee",$B$2,"JCJob",$C18,"JCExtra",$D18,"JCCostCode",$E18,"WCCode",$B18,"WCState",$G18,"State",$H18,"PayID",$BE$12,"Units",AM18,"UnionID",$B$3,"UnionLocal",$F18,"UnionClass",$I18,"CertifiedClass",$J18)),0) -> 0 | CK18: =IF(AND(NOT(ISBLANK($C18)),NOT(ISBLANK($E18)),$A18="x"),IF(AN18=0,0,[2]!TSImport("PRTime","","Time_NINE","","Date",$CG$11,"Employee",$B$2,"JCJob",$C18,"JCExtra",$D18,"JCCostCode",$E18,"WCCode",$B18,"WCState",$G18,"State",$H18,"PayID",$BF$12,"Units",AN18,"UnionID",$B$3,"UnionLocal",$F18,"UnionClass",$I18,"CertifiedClass",$J18)),0) -> 0 | CL18: =IF(AND(NOT(ISBLANK($C18)),NOT(ISBLANK($E18)),$A18="x"),IF(AO18=0,0,[2]!TSImport("PRTime","","Time_NINE","","Date",$CG$11,"Employee",$B$2,"JCJob",$C18,"JCExtra",$D18,"JCCostCode",$E18,"WCCode",$B18,"WCState",$G18,"State",$H18,"PayID",$BG$12,"Units",AO18,"UnionID",$B$3,"UnionLocal",$F18,"UnionClass",$I18,"CertifiedClass",$J18)),0) -> 0 | CM18: =IF(AND(NOT(ISBLANK($C18)),NOT(ISBLANK($E18)),$A18="x"),IF(AP18=0,0,[2]!TSImport("PRTime","","Time_NINE","","Date",$CM$11,"Employee",$B$2,"JCJob",$C18,"JCExtra",$D18,"JCCostCode",$E18,"WCCode",$B18,"WCState",$G18,"State",$H18,"PayID",$BB$12,"Units",AP18,"UnionID",$B$3,"UnionLocal",$F18,"UnionClass",$I18,"CertifiedClass",$J18)),0) -> 0 | CN18: =IF(AND(NOT(ISBLANK($C18)),NOT(ISBLANK($E18)),$A18="x"),IF(AQ18=0,0,[2]!TSImport("PRTime","","Time_NINE","","Date",$CM$11,"Employee",$B$2,"JCJob",$C18,"JCExtra",$D18,"JCCostCode",$E18,"WCCode",$B18,"WCState",$G18,"State",$H18,"PayID",$BC$12,"Units",AQ18,"UnionID",$B$3,"UnionLocal",$F18,"UnionClass",$I18,"CertifiedClass",$J18)),0) -> 0 | CO18: =IF(AND(NOT(ISBLANK($C18)),NOT(ISBLANK($E18)),$A18="x"),IF(AR18=0,0,[2]!TSImport("PRTime","","Time_NINE","","Date",$CM$11,"Employee",$B$2,"JCJob",$C18,"JCExtra",$D18,"JCCostCode",$E18,"WCCode",$B18,"WCState",$G18,"State",$H18,"PayID",$BD$12,"Units",AR18,"UnionID",$B$3,"UnionLocal",$F18,"UnionClass",$I18,"CertifiedClass",$J18)),0) -> 0 | CP18: =IF(AND(NOT(ISBLANK($C18)),NOT(ISBLANK($E18)),$A18="x"),IF(AS18=0,0,[2]!TSImport("PRTime","","Time_NINE","","Date",$CM$11,"Employee",$B$2,"JCJob",$C18,"JCExtra",$D18,"JCCostCode",$E18,"WCCode",$B18,"WCState",$G18,"State",$H18,"PayID",$BE$12,"Units",AS18,"UnionID",$B$3,"UnionLocal",$F18,"UnionClass",$I18,"CertifiedClass",$J18)),0) -> 0 | CQ18: =IF(AND(NOT(ISBLANK($C18)),NOT(ISBLANK($E18)),$A18="x"),IF(AT18=0,0,[2]!TSImport("PRTime","","Time_NINE","","Date",$CM$11,"Employee",$B$2,"JCJob",$C18,"JCExtra",$D18,"JCCostCode",$E18,"WCCode",$B18,"WCState",$G18,"State",$H18,"PayID",$BF$12,"Units",AT18,"UnionID",$B$3,"UnionLocal",$F18,"UnionClass",$I18,"CertifiedClass",$J18)),0) -> 0 | CR18: =IF(AND(NOT(ISBLANK($C18)),NOT(ISBLANK($E18)),$A18="x"),IF(AU18=0,0,[2]!TSImport("PRTime","","Time_NINE","","Date",$CM$11,"Employee",$B$2,"JCJob",$C18,"JCExtra",$D18,"JCCostCode",$E18,"WCCode",$B18,"WCState",$G18,"State",$H18,"PayID",$BG$12,"Units",AU18,"UnionID",$B$3,"UnionLocal",$F18,"UnionClass",$I18,"CertifiedClass",$J18)),0) -> 0 | CS18: =IF(AND(NOT(ISBLANK($C18)),NOT(ISBLANK($E18)),$A18="x"),IF(AV18=0,0,[2]!TSImport("PRTime","","Time_NINE","","Date",$CS$11,"Employee",$B$2,"JCJob",$C18,"JCExtra",$D18,"JCCostCode",$E18,"WCCode",$B18,"WCState",$G18,"State",$H18,"PayID",$BB$12,"Units",AV18,"UnionID",$B$3,"UnionLocal",$F18,"UnionClass",$I18,"CertifiedClass",$J18)),0) -> 0 | CT18: =IF(AND(NOT(ISBLANK($C18)),NOT(ISBLANK($E18)),$A18="x"),IF(AW18=0,0,[2]!TSImport("PRTime","","Time_NINE","","Date",$CS$11,"Employee",$B$2,"JCJob",$C18,"JCExtra",$D18,"JCCostCode",$E18,"WCCode",$B18,"WCState",$G18,"State",$H18,"PayID",$BC$12,"Units",AW18,"UnionID",$B$3,"UnionLocal",$F18,"UnionClass",$I18,"CertifiedClass",$J18)),0) -> 0 | CU18: =IF(AND(NOT(ISBLANK($C18)),NOT(ISBLANK($E18)),$A18="x"),IF(AX18=0,0,[2]!TSImport("PRTime","","Time_NINE","","Date",$CS$11,"Employee",$B$2,"JCJob",$C18,"JCExtra",$D18,"JCCostCode",$E18,"WCCode",$B18,"WCState",$G18,"State",$H18,"PayID",$BD$12,"Units",AX18,"UnionID",$B$3,"UnionLocal",$F18,"UnionClass",$I18,"CertifiedClass",$J18)),0) -> 0 | CV18: =IF(AND(NOT(ISBLANK($C18)),NOT(ISBLANK($E18)),$A18="x"),IF(AY18=0,0,[2]!TSImport("PRTime","","Time_NINE","","Date",$CS$11,"Employee",$B$2,"JCJob",$C18,"JCExtra",$D18,"JCCostCode",$E18,"WCCode",$B18,"WCState",$G18,"State",$H18,"PayID",$BE$12,"Units",AY18,"UnionID",$B$3,"UnionLocal",$F18,"UnionClass",$I18,"CertifiedClass",$J18)),0) -> 0 | CW18: =IF(AND(NOT(ISBLANK($C18)),NOT(ISBLANK($E18)),$A18="x"),IF(AZ18=0,0,[2]!TSImport("PRTime","","Time_NINE","","Date",$CS$11,"Employee",$B$2,"JCJob",$C18,"JCExtra",$D18,"JCCostCode",$E18,"WCCode",$B18,"WCState",$G18,"State",$H18,"PayID",$BF$12,"Units",AZ18,"UnionID",$B$3,"UnionLocal",$F18,"UnionClass",$I18,"CertifiedClass",$J18)),0) -> 0 | CX18: =IF(AND(NOT(ISBLANK($C18)),NOT(ISBLANK($E18)),$A18="x"),IF(BA18=0,0,[2]!TSImport("PRTime","","Time_NINE","","Date",$CS$11,"Employee",$B$2,"JCJob",$C18,"JCExtra",$D18,"JCCostCode",$E18,"WCCode",$B18,"WCState",$G18,"State",$H18,"PayID",$BG$12,"Units",BA18,"UnionID",$B$3,"UnionLocal",$F18,"UnionClass",$I18,"CertifiedClass",$J18)),0) -> 0
A19: =IF(ISBLANK(C19),"",IF(ISBLANK($D$3),"",$D$3)) | F19: =IF(ISBLANK($B$4),"",$B$4) | J19: =IF($K19=0,"",IF($K19<10,"0"&$K19,$K19)) | BB19: =SUM(AV19,AP19,AJ19,AD19,X19,R19,L19) -> 0 | BC19: =SUM(AW19,AQ19,AK19,AE19,Y19,S19,M19) -> 0 | BD19: =SUM(AX19,AR19,AL19,AF19,Z19,T19,N19) -> 0 | BE19: =SUM(AY19,AS19,AM19,AG19,AA19,U19,O19) -> 0 | BF19: =SUM(AZ19,AT19,AN19,AH19,AB19,V19,P19) -> 0 | BG19: =SUM(BA19,AU19,AO19,AI19,AC19,W19,Q19) -> 0 | BH19: =SUM(TimeSheet34[[#This Row],[1]:[4A]]) -> 0 | BI19: =IF(AND(NOT(ISBLANK($C19)),NOT(ISBLANK($E19)),$A19="x"),IF(L19=0,0,[2]!TSImport("PRTime","","Time_NINE","","Date",$BI$11,"Employee",$B$2,"JCJob",$C19,"JCExtra",$D19,"JCCostCode",$E19,"WCCode",$B19,"WCState",$G19,"State",$H19,"PayID",$BB$12,"Units",L19,"UnionID",$B$3,"UnionLocal",$F19,"UnionClass",$I19,"CertifiedClass",$J19)),0) -> 0 | BJ19: =IF(AND(NOT(ISBLANK($C19)),NOT(ISBLANK($E19)),$A19="x"),IF(M19=0,0,[2]!TSImport("PRTime","","Time_NINE","","Date",$BI$11,"Employee",$B$2,"JCJob",$C19,"JCExtra",$D19,"JCCostCode",$E19,"WCCode",$B19,"WCState",$G19,"State",$H19,"PayID",$BC$12,"Units",M19,"UnionID",$B$3,"UnionLocal",$F19,"UnionClass",$I19,"CertifiedClass",$J19)),0) -> 0 | BK19: =IF(AND(NOT(ISBLANK($C19)),NOT(ISBLANK($E19)),$A19="x"),IF(N19=0,0,[2]!TSImport("PRTime","","Time_NINE","","Date",$BI$11,"Employee",$B$2,"JCJob",$C19,"JCExtra",$D19,"JCCostCode",$E19,"WCCode",$B19,"WCState",$G19,"State",$H19,"PayID",$BD$12,"Units",N19,"UnionID",$B$3,"UnionLocal",$F19,"UnionClass",$I19,"CertifiedClass",$J19)),0) -> 0 | BL19: =IF(AND(NOT(ISBLANK($C19)),NOT(ISBLANK($E19)),$A19="x"),IF(O19=0,0,[2]!TSImport("PRTime","","Time_NINE","","Date",$BI$11,"Employee",$B$2,"JCJob",$C19,"JCExtra",$D19,"JCCostCode",$E19,"WCCode",$B19,"WCState",$G19,"State",$H19,"PayID",$BE$12,"Units",O19,"UnionID",$B$3,"UnionLocal",$F19,"UnionClass",$I19,"CertifiedClass",$J19)),0) -> 0 | BM19: =IF(AND(NOT(ISBLANK($C19)),NOT(ISBLANK($E19)),$A19="x"),IF(P19=0,0,[2]!TSImport("PRTime","","Time_NINE","","Date",$BI$11,"Employee",$B$2,"JCJob",$C19,"JCExtra",$D19,"JCCostCode",$E19,"WCCode",$B19,"WCState",$G19,"State",$H19,"PayID",$BF$12,"Units",P19,"UnionID",$B$3,"UnionLocal",$F19,"UnionClass",$I19,"CertifiedClass",$J19)),0) -> 0 | BN19: =IF(AND(NOT(ISBLANK($C19)),NOT(ISBLANK($E19)),$A19="x"),IF(Q19=0,0,[2]!TSImport("PRTime","","Time_NINE","","Date",$BI$11,"Employee",$B$2,"JCJob",$C19,"JCExtra",$D19,"JCCostCode",$E19,"WCCode",$B19,"WCState",$G19,"State",$H19,"PayID",$BG$12,"Units",Q19,"UnionID",$B$3,"UnionLocal",$F19,"UnionClass",$I19,"CertifiedClass",$J19)),0) -> 0 | BO19: =IF(AND(NOT(ISBLANK($C19)),NOT(ISBLANK($E19)),$A19="x"),IF(R19=0,0,[2]!TSImport("PRTime","","Time_NINE","","Date",$BO$11,"Employee",$B$2,"JCJob",$C19,"JCExtra",$D19,"JCCostCode",$E19,"WCCode",$B19,"WCState",$G19,"State",$H19,"PayID",$BB$12,"Units",R19,"UnionID",$B$3,"UnionLocal",$F19,"UnionClass",$I19,"CertifiedClass",$J19)),0) -> 0 | BP19: =IF(AND(NOT(ISBLANK($C19)),NOT(ISBLANK($E19)),$A19="x"),IF(S19=0,0,[2]!TSImport("PRTime","","Time_NINE","","Date",$BO$11,"Employee",$B$2,"JCJob",$C19,"JCExtra",$D19,"JCCostCode",$E19,"WCCode",$B19,"WCState",$G19,"State",$H19,"PayID",$BC$12,"Units",S19,"UnionID",$B$3,"UnionLocal",$F19,"UnionClass",$I19,"CertifiedClass",$J19)),0) -> 0 | BQ19: =IF(AND(NOT(ISBLANK($C19)),NOT(ISBLANK($E19)),$A19="x"),IF(T19=0,0,[2]!TSImport("PRTime","","Time_NINE","","Date",$BO$11,"Employee",$B$2,"JCJob",$C19,"JCExtra",$D19,"JCCostCode",$E19,"WCCode",$B19,"WCState",$G19,"State",$H19,"PayID",$BD$12,"Units",T19,"UnionID",$B$3,"UnionLocal",$F19,"UnionClass",$I19,"CertifiedClass",$J19)),0) -> 0 | BR19: =IF(AND(NOT(ISBLANK($C19)),NOT(ISBLANK($E19)),$A19="x"),IF(U19=0,0,[2]!TSImport("PRTime","","Time_NINE","","Date",$BO$11,"Employee",$B$2,"JCJob",$C19,"JCExtra",$D19,"JCCostCode",$E19,"WCCode",$B19,"WCState",$G19,"State",$H19,"PayID",$BE$12,"Units",U19,"UnionID",$B$3,"UnionLocal",$F19,"UnionClass",$I19,"CertifiedClass",$J19)),0) -> 0 | BS19: =IF(AND(NOT(ISBLANK($C19)),NOT(ISBLANK($E19)),$A19="x"),IF(V19=0,0,[2]!TSImport("PRTime","","Time_NINE","","Date",$BO$11,"Employee",$B$2,"JCJob",$C19,"JCExtra",$D19,"JCCostCode",$E19,"WCCode",$B19,"WCState",$G19,"State",$H19,"PayID",$BF$12,"Units",V19,"UnionID",$B$3,"UnionLocal",$F19,"UnionClass",$I19,"CertifiedClass",$J19)),0) -> 0 | BT19: =IF(AND(NOT(ISBLANK($C19)),NOT(ISBLANK($E19)),$A19="x"),IF(W19=0,0,[2]!TSImport("PRTime","","Time_NINE","","Date",$BO$11,"Employee",$B$2,"JCJob",$C19,"JCExtra",$D19,"JCCostCode",$E19,"WCCode",$B19,"WCState",$G19,"State",$H19,"PayID",$BG$12,"Units",W19,"UnionID",$B$3,"UnionLocal",$F19,"UnionClass",$I19,"CertifiedClass",$J19)),0) -> 0 | BU19: =IF(AND(NOT(ISBLANK($C19)),NOT(ISBLANK($E19)),$A19="x"),IF(X19=0,0,[2]!TSImport("PRTime","","Time_NINE","","Date",$BU$11,"Employee",$B$2,"JCJob",$C19,"JCExtra",$D19,"JCCostCode",$E19,"WCCode",$B19,"WCState",$G19,"State",$H19,"PayID",$BB$12,"Units",X19,"UnionID",$B$3,"UnionLocal",$F19,"UnionClass",$I19,"CertifiedClass",$J19)),0) -> 0 | BV19: =IF(AND(NOT(ISBLANK($C19)),NOT(ISBLANK($E19)),$A19="x"),IF(Y19=0,0,[2]!TSImport("PRTime","","Time_NINE","","Date",$BU$11,"Employee",$B$2,"JCJob",$C19,"JCExtra",$D19,"JCCostCode",$E19,"WCCode",$B19,"WCState",$G19,"State",$H19,"PayID",$BC$12,"Units",Y19,"UnionID",$B$3,"UnionLocal",$F19,"UnionClass",$I19,"CertifiedClass",$J19)),0) -> 0 | BW19: =IF(AND(NOT(ISBLANK($C19)),NOT(ISBLANK($E19)),$A19="x"),IF(Z19=0,0,[2]!TSImport("PRTime","","Time_NINE","","Date",$BU$11,"Employee",$B$2,"JCJob",$C19,"JCExtra",$D19,"JCCostCode",$E19,"WCCode",$B19,"WCState",$G19,"State",$H19,"PayID",$BD$12,"Units",Z19,"UnionID",$B$3,"UnionLocal",$F19,"UnionClass",$I19,"CertifiedClass",$J19)),0) -> 0 | BX19: =IF(AND(NOT(ISBLANK($C19)),NOT(ISBLANK($E19)),$A19="x"),IF(AA19=0,0,[2]!TSImport("PRTime","","Time_NINE","","Date",$BU$11,"Employee",$B$2,"JCJob",$C19,"JCExtra",$D19,"JCCostCode",$E19,"WCCode",$B19,"WCState",$G19,"State",$H19,"PayID",$BE$12,"Units",AA19,"UnionID",$B$3,"UnionLocal",$F19,"UnionClass",$I19,"CertifiedClass",$J19)),0) -> 0 | BY19: =IF(AND(NOT(ISBLANK($C19)),NOT(ISBLANK($E19)),$A19="x"),IF(AB19=0,0,[2]!TSImport("PRTime","","Time_NINE","","Date",$BU$11,"Employee",$B$2,"JCJob",$C19,"JCExtra",$D19,"JCCostCode",$E19,"WCCode",$B19,"WCState",$G19,"State",$H19,"PayID",$BF$12,"Units",AB19,"UnionID",$B$3,"UnionLocal",$F19,"UnionClass",$I19,"CertifiedClass",$J19)),0) -> 0 | BZ19: =IF(AND(NOT(ISBLANK($C19)),NOT(ISBLANK($E19)),$A19="x"),IF(AC19=0,0,[2]!TSImport("PRTime","","Time_NINE","","Date",$BU$11,"Employee",$B$2,"JCJob",$C19,"JCExtra",$D19,"JCCostCode",$E19,"WCCode",$B19,"WCState",$G19,"State",$H19,"PayID",$BG$12,"Units",AC19,"UnionID",$B$3,"UnionLocal",$F19,"UnionClass",$I19,"CertifiedClass",$J19)),0) -> 0 | CA19: =IF(AND(NOT(ISBLANK($C19)),NOT(ISBLANK($E19)),$A19="x"),IF(AD19=0,0,[2]!TSImport("PRTime","","Time_NINE","","Date",$CA$11,"Employee",$B$2,"JCJob",$C19,"JCExtra",$D19,"JCCostCode",$E19,"WCCode",$B19,"WCState",$G19,"State",$H19,"PayID",$BB$12,"Units",AD19,"UnionID",$B$3,"UnionLocal",$F19,"UnionClass",$I19,"CertifiedClass",$J19)),0) -> 0 | CB19: =IF(AND(NOT(ISBLANK($C19)),NOT(ISBLANK($E19)),$A19="x"),IF(AE19=0,0,[2]!TSImport("PRTime","","Time_NINE","","Date",$CA$11,"Employee",$B$2,"JCJob",$C19,"JCExtra",$D19,"JCCostCode",$E19,"WCCode",$B19,"WCState",$G19,"State",$H19,"PayID",$BC$12,"Units",AE19,"UnionID",$B$3,"UnionLocal",$F19,"UnionClass",$I19,"CertifiedClass",$J19)),0) -> 0 | CC19: =IF(AND(NOT(ISBLANK($C19)),NOT(ISBLANK($E19)),$A19="x"),IF(AF19=0,0,[2]!TSImport("PRTime","","Time_NINE","","Date",$CA$11,"Employee",$B$2,"JCJob",$C19,"JCExtra",$D19,"JCCostCode",$E19,"WCCode",$B19,"WCState",$G19,"State",$H19,"PayID",$BD$12,"Units",AF19,"UnionID",$B$3,"UnionLocal",$F19,"UnionClass",$I19,"CertifiedClass",$J19)),0) -> 0 | CD19: =IF(AND(NOT(ISBLANK($C19)),NOT(ISBLANK($E19)),$A19="x"),IF(AG19=0,0,[2]!TSImport("PRTime","","Time_NINE","","Date",$CA$11,"Employee",$B$2,"JCJob",$C19,"JCExtra",$D19,"JCCostCode",$E19,"WCCode",$B19,"WCState",$G19,"State",$H19,"PayID",$BE$12,"Units",AG19,"UnionID",$B$3,"UnionLocal",$F19,"UnionClass",$I19,"CertifiedClass",$J19)),0) -> 0 | CE19: =IF(AND(NOT(ISBLANK($C19)),NOT(ISBLANK($E19)),$A19="x"),IF(AH19=0,0,[2]!TSImport("PRTime","","Time_NINE","","Date",$CA$11,"Employee",$B$2,"JCJob",$C19,"JCExtra",$D19,"JCCostCode",$E19,"WCCode",$B19,"WCState",$G19,"State",$H19,"PayID",$BF$12,"Units",AH19,"UnionID",$B$3,"UnionLocal",$F19,"UnionClass",$I19,"CertifiedClass",$J19)),0) -> 0 | CF19: =IF(AND(NOT(ISBLANK($C19)),NOT(ISBLANK($E19)),$A19="x"),IF(AI19=0,0,[2]!TSImport("PRTime","","Time_NINE","","Date",$CA$11,"Employee",$B$2,"JCJob",$C19,"JCExtra",$D19,"JCCostCode",$E19,"WCCode",$B19,"WCState",$G19,"State",$H19,"PayID",$BG$12,"Units",AI19,"UnionID",$B$3,"UnionLocal",$F19,"UnionClass",$I19,"CertifiedClass",$J19)),0) -> 0 | CG19: =IF(AND(NOT(ISBLANK($C19)),NOT(ISBLANK($E19)),$A19="x"),IF(AJ19=0,0,[2]!TSImport("PRTime","","Time_NINE","","Date",$CG$11,"Employee",$B$2,"JCJob",$C19,"JCExtra",$D19,"JCCostCode",$E19,"WCCode",$B19,"WCState",$G19,"State",$H19,"PayID",$BB$12,"Units",AJ19,"UnionID",$B$3,"UnionLocal",$F19,"UnionClass",$I19,"CertifiedClass",$J19)),0) -> 0 | CH19: =IF(AND(NOT(ISBLANK($C19)),NOT(ISBLANK($E19)),$A19="x"),IF(AK19=0,0,[2]!TSImport("PRTime","","Time_NINE","","Date",$CG$11,"Employee",$B$2,"JCJob",$C19,"JCExtra",$D19,"JCCostCode",$E19,"WCCode",$B19,"WCState",$G19,"State",$H19,"PayID",$BC$12,"Units",AK19,"UnionID",$B$3,"UnionLocal",$F19,"UnionClass",$I19,"CertifiedClass",$J19)),0) -> 0 | CI19: =IF(AND(NOT(ISBLANK($C19)),NOT(ISBLANK($E19)),$A19="x"),IF(AL19=0,0,[2]!TSImport("PRTime","","Time_NINE","","Date",$CG$11,"Employee",$B$2,"JCJob",$C19,"JCExtra",$D19,"JCCostCode",$E19,"WCCode",$B19,"WCState",$G19,"State",$H19,"PayID",$BD$12,"Units",AL19,"UnionID",$B$3,"UnionLocal",$F19,"UnionClass",$I19,"CertifiedClass",$J19)),0) -> 0 | CJ19: =IF(AND(NOT(ISBLANK($C19)),NOT(ISBLANK($E19)),$A19="x"),IF(AM19=0,0,[2]!TSImport("PRTime","","Time_NINE","","Date",$CG$11,"Employee",$B$2,"JCJob",$C19,"JCExtra",$D19,"JCCostCode",$E19,"WCCode",$B19,"WCState",$G19,"State",$H19,"PayID",$BE$12,"Units",AM19,"UnionID",$B$3,"UnionLocal",$F19,"UnionClass",$I19,"CertifiedClass",$J19)),0) -> 0 | CK19: =IF(AND(NOT(ISBLANK($C19)),NOT(ISBLANK($E19)),$A19="x"),IF(AN19=0,0,[2]!TSImport("PRTime","","Time_NINE","","Date",$CG$11,"Employee",$B$2,"JCJob",$C19,"JCExtra",$D19,"JCCostCode",$E19,"WCCode",$B19,"WCState",$G19,"State",$H19,"PayID",$BF$12,"Units",AN19,"UnionID",$B$3,"UnionLocal",$F19,"UnionClass",$I19,"CertifiedClass",$J19)),0) -> 0 | CL19: =IF(AND(NOT(ISBLANK($C19)),NOT(ISBLANK($E19)),$A19="x"),IF(AO19=0,0,[2]!TSImport("PRTime","","Time_NINE","","Date",$CG$11,"Employee",$B$2,"JCJob",$C19,"JCExtra",$D19,"JCCostCode",$E19,"WCCode",$B19,"WCState",$G19,"State",$H19,"PayID",$BG$12,"Units",AO19,"UnionID",$B$3,"UnionLocal",$F19,"UnionClass",$I19,"CertifiedClass",$J19)),0) -> 0 | CM19: =IF(AND(NOT(ISBLANK($C19)),NOT(ISBLANK($E19)),$A19="x"),IF(AP19=0,0,[2]!TSImport("PRTime","","Time_NINE","","Date",$CM$11,"Employee",$B$2,"JCJob",$C19,"JCExtra",$D19,"JCCostCode",$E19,"WCCode",$B19,"WCState",$G19,"State",$H19,"PayID",$BB$12,"Units",AP19,"UnionID",$B$3,"UnionLocal",$F19,"UnionClass",$I19,"CertifiedClass",$J19)),0) -> 0 | CN19: =IF(AND(NOT(ISBLANK($C19)),NOT(ISBLANK($E19)),$A19="x"),IF(AQ19=0,0,[2]!TSImport("PRTime","","Time_NINE","","Date",$CM$11,"Employee",$B$2,"JCJob",$C19,"JCExtra",$D19,"JCCostCode",$E19,"WCCode",$B19,"WCState",$G19,"State",$H19,"PayID",$BC$12,"Units",AQ19,"UnionID",$B$3,"UnionLocal",$F19,"UnionClass",$I19,"CertifiedClass",$J19)),0) -> 0 | CO19: =IF(AND(NOT(ISBLANK($C19)),NOT(ISBLANK($E19)),$A19="x"),IF(AR19=0,0,[2]!TSImport("PRTime","","Time_NINE","","Date",$CM$11,"Employee",$B$2,"JCJob",$C19,"JCExtra",$D19,"JCCostCode",$E19,"WCCode",$B19,"WCState",$G19,"State",$H19,"PayID",$BD$12,"Units",AR19,"UnionID",$B$3,"UnionLocal",$F19,"UnionClass",$I19,"CertifiedClass",$J19)),0) -> 0 | CP19: =IF(AND(NOT(ISBLANK($C19)),NOT(ISBLANK($E19)),$A19="x"),IF(AS19=0,0,[2]!TSImport("PRTime","","Time_NINE","","Date",$CM$11,"Employee",$B$2,"JCJob",$C19,"JCExtra",$D19,"JCCostCode",$E19,"WCCode",$B19,"WCState",$G19,"State",$H19,"PayID",$BE$12,"Units",AS19,"UnionID",$B$3,"UnionLocal",$F19,"UnionClass",$I19,"CertifiedClass",$J19)),0) -> 0 | CQ19: =IF(AND(NOT(ISBLANK($C19)),NOT(ISBLANK($E19)),$A19="x"),IF(AT19=0,0,[2]!TSImport("PRTime","","Time_NINE","","Date",$CM$11,"Employee",$B$2,"JCJob",$C19,"JCExtra",$D19,"JCCostCode",$E19,"WCCode",$B19,"WCState",$G19,"State",$H19,"PayID",$BF$12,"Units",AT19,"UnionID",$B$3,"UnionLocal",$F19,"UnionClass",$I19,"CertifiedClass",$J19)),0) -> 0 | CR19: =IF(AND(NOT(ISBLANK($C19)),NOT(ISBLANK($E19)),$A19="x"),IF(AU19=0,0,[2]!TSImport("PRTime","","Time_NINE","","Date",$CM$11,"Employee",$B$2,"JCJob",$C19,"JCExtra",$D19,"JCCostCode",$E19,"WCCode",$B19,"WCState",$G19,"State",$H19,"PayID",$BG$12,"Units",AU19,"UnionID",$B$3,"UnionLocal",$F19,"UnionClass",$I19,"CertifiedClass",$J19)),0) -> 0 | CS19: =IF(AND(NOT(ISBLANK($C19)),NOT(ISBLANK($E19)),$A19="x"),IF(AV19=0,0,[2]!TSImport("PRTime","","Time_NINE","","Date",$CS$11,"Employee",$B$2,"JCJob",$C19,"JCExtra",$D19,"JCCostCode",$E19,"WCCode",$B19,"WCState",$G19,"State",$H19,"PayID",$BB$12,"Units",AV19,"UnionID",$B$3,"UnionLocal",$F19,"UnionClass",$I19,"CertifiedClass",$J19)),0) -> 0 | CT19: =IF(AND(NOT(ISBLANK($C19)),NOT(ISBLANK($E19)),$A19="x"),IF(AW19=0,0,[2]!TSImport("PRTime","","Time_NINE","","Date",$CS$11,"Employee",$B$2,"JCJob",$C19,"JCExtra",$D19,"JCCostCode",$E19,"WCCode",$B19,"WCState",$G19,"State",$H19,"PayID",$BC$12,"Units",AW19,"UnionID",$B$3,"UnionLocal",$F19,"UnionClass",$I19,"CertifiedClass",$J19)),0) -> 0 | CU19: =IF(AND(NOT(ISBLANK($C19)),NOT(ISBLANK($E19)),$A19="x"),IF(AX19=0,0,[2]!TSImport("PRTime","","Time_NINE","","Date",$CS$11,"Employee",$B$2,"JCJob",$C19,"JCExtra",$D19,"JCCostCode",$E19,"WCCode",$B19,"WCState",$G19,"State",$H19,"PayID",$BD$12,"Units",AX19,"UnionID",$B$3,"UnionLocal",$F19,"UnionClass",$I19,"CertifiedClass",$J19)),0) -> 0 | CV19: =IF(AND(NOT(ISBLANK($C19)),NOT(ISBLANK($E19)),$A19="x"),IF(AY19=0,0,[2]!TSImport("PRTime","","Time_NINE","","Date",$CS$11,"Employee",$B$2,"JCJob",$C19,"JCExtra",$D19,"JCCostCode",$E19,"WCCode",$B19,"WCState",$G19,"State",$H19,"PayID",$BE$12,"Units",AY19,"UnionID",$B$3,"UnionLocal",$F19,"UnionClass",$I19,"CertifiedClass",$J19)),0) -> 0 | CW19: =IF(AND(NOT(ISBLANK($C19)),NOT(ISBLANK($E19)),$A19="x"),IF(AZ19=0,0,[2]!TSImport("PRTime","","Time_NINE","","Date",$CS$11,"Employee",$B$2,"JCJob",$C19,"JCExtra",$D19,"JCCostCode",$E19,"WCCode",$B19,"WCState",$G19,"State",$H19,"PayID",$BF$12,"Units",AZ19,"UnionID",$B$3,"UnionLocal",$F19,"UnionClass",$I19,"CertifiedClass",$J19)),0) -> 0 | CX19: =IF(AND(NOT(ISBLANK($C19)),NOT(ISBLANK($E19)),$A19="x"),IF(BA19=0,0,[2]!TSImport("PRTime","","Time_NINE","","Date",$CS$11,"Employee",$B$2,"JCJob",$C19,"JCExtra",$D19,"JCCostCode",$E19,"WCCode",$B19,"WCState",$G19,"State",$H19,"PayID",$BG$12,"Units",BA19,"UnionID",$B$3,"UnionLocal",$F19,"UnionClass",$I19,"CertifiedClass",$J19)),0) -> 0
A20: =IF(ISBLANK(C20),"",IF(ISBLANK($D$3),"",$D$3)) | F20: =IF(ISBLANK($B$4),"",$B$4) | J20: =IF($K20=0,"",IF($K20<10,"0"&$K20,$K20)) | BB20: =SUM(AV20,AP20,AJ20,AD20,X20,R20,L20) -> 0 | BC20: =SUM(AW20,AQ20,AK20,AE20,Y20,S20,M20) -> 0 | BD20: =SUM(AX20,AR20,AL20,AF20,Z20,T20,N20) -> 0 | BE20: =SUM(AY20,AS20,AM20,AG20,AA20,U20,O20) -> 0 | BF20: =SUM(AZ20,AT20,AN20,AH20,AB20,V20,P20) -> 0 | BG20: =SUM(BA20,AU20,AO20,AI20,AC20,W20,Q20) -> 0 | BH20: =SUM(TimeSheet34[[#This Row],[1]:[4A]]) -> 0 | BI20: =IF(AND(NOT(ISBLANK($C20)),NOT(ISBLANK($E20)),$A20="x"),IF(L20=0,0,[2]!TSImport("PRTime","","Time_NINE","","Date",$BI$11,"Employee",$B$2,"JCJob",$C20,"JCExtra",$D20,"JCCostCode",$E20,"WCCode",$B20,"WCState",$G20,"State",$H20,"PayID",$BB$12,"Units",L20,"UnionID",$B$3,"UnionLocal",$F20,"UnionClass",$I20,"CertifiedClass",$J20)),0) -> 0 | BJ20: =IF(AND(NOT(ISBLANK($C20)),NOT(ISBLANK($E20)),$A20="x"),IF(M20=0,0,[2]!TSImport("PRTime","","Time_NINE","","Date",$BI$11,"Employee",$B$2,"JCJob",$C20,"JCExtra",$D20,"JCCostCode",$E20,"WCCode",$B20,"WCState",$G20,"State",$H20,"PayID",$BC$12,"Units",M20,"UnionID",$B$3,"UnionLocal",$F20,"UnionClass",$I20,"CertifiedClass",$J20)),0) -> 0 | BK20: =IF(AND(NOT(ISBLANK($C20)),NOT(ISBLANK($E20)),$A20="x"),IF(N20=0,0,[2]!TSImport("PRTime","","Time_NINE","","Date",$BI$11,"Employee",$B$2,"JCJob",$C20,"JCExtra",$D20,"JCCostCode",$E20,"WCCode",$B20,"WCState",$G20,"State",$H20,"PayID",$BD$12,"Units",N20,"UnionID",$B$3,"UnionLocal",$F20,"UnionClass",$I20,"CertifiedClass",$J20)),0) -> 0 | BL20: =IF(AND(NOT(ISBLANK($C20)),NOT(ISBLANK($E20)),$A20="x"),IF(O20=0,0,[2]!TSImport("PRTime","","Time_NINE","","Date",$BI$11,"Employee",$B$2,"JCJob",$C20,"JCExtra",$D20,"JCCostCode",$E20,"WCCode",$B20,"WCState",$G20,"State",$H20,"PayID",$BE$12,"Units",O20,"UnionID",$B$3,"UnionLocal",$F20,"UnionClass",$I20,"CertifiedClass",$J20)),0) -> 0 | BM20: =IF(AND(NOT(ISBLANK($C20)),NOT(ISBLANK($E20)),$A20="x"),IF(P20=0,0,[2]!TSImport("PRTime","","Time_NINE","","Date",$BI$11,"Employee",$B$2,"JCJob",$C20,"JCExtra",$D20,"JCCostCode",$E20,"WCCode",$B20,"WCState",$G20,"State",$H20,"PayID",$BF$12,"Units",P20,"UnionID",$B$3,"UnionLocal",$F20,"UnionClass",$I20,"CertifiedClass",$J20)),0) -> 0 | BN20: =IF(AND(NOT(ISBLANK($C20)),NOT(ISBLANK($E20)),$A20="x"),IF(Q20=0,0,[2]!TSImport("PRTime","","Time_NINE","","Date",$BI$11,"Employee",$B$2,"JCJob",$C20,"JCExtra",$D20,"JCCostCode",$E20,"WCCode",$B20,"WCState",$G20,"State",$H20,"PayID",$BG$12,"Units",Q20,"UnionID",$B$3,"UnionLocal",$F20,"UnionClass",$I20,"CertifiedClass",$J20)),0) -> 0 | BO20: =IF(AND(NOT(ISBLANK($C20)),NOT(ISBLANK($E20)),$A20="x"),IF(R20=0,0,[2]!TSImport("PRTime","","Time_NINE","","Date",$BO$11,"Employee",$B$2,"JCJob",$C20,"JCExtra",$D20,"JCCostCode",$E20,"WCCode",$B20,"WCState",$G20,"State",$H20,"PayID",$BB$12,"Units",R20,"UnionID",$B$3,"UnionLocal",$F20,"UnionClass",$I20,"CertifiedClass",$J20)),0) -> 0 | BP20: =IF(AND(NOT(ISBLANK($C20)),NOT(ISBLANK($E20)),$A20="x"),IF(S20=0,0,[2]!TSImport("PRTime","","Time_NINE","","Date",$BO$11,"Employee",$B$2,"JCJob",$C20,"JCExtra",$D20,"JCCostCode",$E20,"WCCode",$B20,"WCState",$G20,"State",$H20,"PayID",$BC$12,"Units",S20,"UnionID",$B$3,"UnionLocal",$F20,"UnionClass",$I20,"CertifiedClass",$J20)),0) -> 0 | BQ20: =IF(AND(NOT(ISBLANK($C20)),NOT(ISBLANK($E20)),$A20="x"),IF(T20=0,0,[2]!TSImport("PRTime","","Time_NINE","","Date",$BO$11,"Employee",$B$2,"JCJob",$C20,"JCExtra",$D20,"JCCostCode",$E20,"WCCode",$B20,"WCState",$G20,"State",$H20,"PayID",$BD$12,"Units",T20,"UnionID",$B$3,"UnionLocal",$F20,"UnionClass",$I20,"CertifiedClass",$J20)),0) -> 0 | BR20: =IF(AND(NOT(ISBLANK($C20)),NOT(ISBLANK($E20)),$A20="x"),IF(U20=0,0,[2]!TSImport("PRTime","","Time_NINE","","Date",$BO$11,"Employee",$B$2,"JCJob",$C20,"JCExtra",$D20,"JCCostCode",$E20,"WCCode",$B20,"WCState",$G20,"State",$H20,"PayID",$BE$12,"Units",U20,"UnionID",$B$3,"UnionLocal",$F20,"UnionClass",$I20,"CertifiedClass",$J20)),0) -> 0 | BS20: =IF(AND(NOT(ISBLANK($C20)),NOT(ISBLANK($E20)),$A20="x"),IF(V20=0,0,[2]!TSImport("PRTime","","Time_NINE","","Date",$BO$11,"Employee",$B$2,"JCJob",$C20,"JCExtra",$D20,"JCCostCode",$E20,"WCCode",$B20,"WCState",$G20,"State",$H20,"PayID",$BF$12,"Units",V20,"UnionID",$B$3,"UnionLocal",$F20,"UnionClass",$I20,"CertifiedClass",$J20)),0) -> 0 | BT20: =IF(AND(NOT(ISBLANK($C20)),NOT(ISBLANK($E20)),$A20="x"),IF(W20=0,0,[2]!TSImport("PRTime","","Time_NINE","","Date",$BO$11,"Employee",$B$2,"JCJob",$C20,"JCExtra",$D20,"JCCostCode",$E20,"WCCode",$B20,"WCState",$G20,"State",$H20,"PayID",$BG$12,"Units",W20,"UnionID",$B$3,"UnionLocal",$F20,"UnionClass",$I20,"CertifiedClass",$J20)),0) -> 0 | BU20: =IF(AND(NOT(ISBLANK($C20)),NOT(ISBLANK($E20)),$A20="x"),IF(X20=0,0,[2]!TSImport("PRTime","","Time_NINE","","Date",$BU$11,"Employee",$B$2,"JCJob",$C20,"JCExtra",$D20,"JCCostCode",$E20,"WCCode",$B20,"WCState",$G20,"State",$H20,"PayID",$BB$12,"Units",X20,"UnionID",$B$3,"UnionLocal",$F20,"UnionClass",$I20,"CertifiedClass",$J20)),0) -> 0 | BV20: =IF(AND(NOT(ISBLANK($C20)),NOT(ISBLANK($E20)),$A20="x"),IF(Y20=0,0,[2]!TSImport("PRTime","","Time_NINE","","Date",$BU$11,"Employee",$B$2,"JCJob",$C20,"JCExtra",$D20,"JCCostCode",$E20,"WCCode",$B20,"WCState",$G20,"State",$H20,"PayID",$BC$12,"Units",Y20,"UnionID",$B$3,"UnionLocal",$F20,"UnionClass",$I20,"CertifiedClass",$J20)),0) -> 0 | BW20: =IF(AND(NOT(ISBLANK($C20)),NOT(ISBLANK($E20)),$A20="x"),IF(Z20=0,0,[2]!TSImport("PRTime","","Time_NINE","","Date",$BU$11,"Employee",$B$2,"JCJob",$C20,"JCExtra",$D20,"JCCostCode",$E20,"WCCode",$B20,"WCState",$G20,"State",$H20,"PayID",$BD$12,"Units",Z20,"UnionID",$B$3,"UnionLocal",$F20,"UnionClass",$I20,"CertifiedClass",$J20)),0) -> 0 | BX20: =IF(AND(NOT(ISBLANK($C20)),NOT(ISBLANK($E20)),$A20="x"),IF(AA20=0,0,[2]!TSImport("PRTime","","Time_NINE","","Date",$BU$11,"Employee",$B$2,"JCJob",$C20,"JCExtra",$D20,"JCCostCode",$E20,"WCCode",$B20,"WCState",$G20,"State",$H20,"PayID",$BE$12,"Units",AA20,"UnionID",$B$3,"UnionLocal",$F20,"UnionClass",$I20,"CertifiedClass",$J20)),0) -> 0 | BY20: =IF(AND(NOT(ISBLANK($C20)),NOT(ISBLANK($E20)),$A20="x"),IF(AB20=0,0,[2]!TSImport("PRTime","","Time_NINE","","Date",$BU$11,"Employee",$B$2,"JCJob",$C20,"JCExtra",$D20,"JCCostCode",$E20,"WCCode",$B20,"WCState",$G20,"State",$H20,"PayID",$BF$12,"Units",AB20,"UnionID",$B$3,"UnionLocal",$F20,"UnionClass",$I20,"CertifiedClass",$J20)),0) -> 0 | BZ20: =IF(AND(NOT(ISBLANK($C20)),NOT(ISBLANK($E20)),$A20="x"),IF(AC20=0,0,[2]!TSImport("PRTime","","Time_NINE","","Date",$BU$11,"Employee",$B$2,"JCJob",$C20,"JCExtra",$D20,"JCCostCode",$E20,"WCCode",$B20,"WCState",$G20,"State",$H20,"PayID",$BG$12,"Units",AC20,"UnionID",$B$3,"UnionLocal",$F20,"UnionClass",$I20,"CertifiedClass",$J20)),0) -> 0 | CA20: =IF(AND(NOT(ISBLANK($C20)),NOT(ISBLANK($E20)),$A20="x"),IF(AD20=0,0,[2]!TSImport("PRTime","","Time_NINE","","Date",$CA$11,"Employee",$B$2,"JCJob",$C20,"JCExtra",$D20,"JCCostCode",$E20,"WCCode",$B20,"WCState",$G20,"State",$H20,"PayID",$BB$12,"Units",AD20,"UnionID",$B$3,"UnionLocal",$F20,"UnionClass",$I20,"CertifiedClass",$J20)),0) -> 0 | CB20: =IF(AND(NOT(ISBLANK($C20)),NOT(ISBLANK($E20)),$A20="x"),IF(AE20=0,0,[2]!TSImport("PRTime","","Time_NINE","","Date",$CA$11,"Employee",$B$2,"JCJob",$C20,"JCExtra",$D20,"JCCostCode",$E20,"WCCode",$B20,"WCState",$G20,"State",$H20,"PayID",$BC$12,"Units",AE20,"UnionID",$B$3,"UnionLocal",$F20,"UnionClass",$I20,"CertifiedClass",$J20)),0) -> 0 | CC20: =IF(AND(NOT(ISBLANK($C20)),NOT(ISBLANK($E20)),$A20="x"),IF(AF20=0,0,[2]!TSImport("PRTime","","Time_NINE","","Date",$CA$11,"Employee",$B$2,"JCJob",$C20,"JCExtra",$D20,"JCCostCode",$E20,"WCCode",$B20,"WCState",$G20,"State",$H20,"PayID",$BD$12,"Units",AF20,"UnionID",$B$3,"UnionLocal",$F20,"UnionClass",$I20,"CertifiedClass",$J20)),0) -> 0 | CD20: =IF(AND(NOT(ISBLANK($C20)),NOT(ISBLANK($E20)),$A20="x"),IF(AG20=0,0,[2]!TSImport("PRTime","","Time_NINE","","Date",$CA$11,"Employee",$B$2,"JCJob",$C20,"JCExtra",$D20,"JCCostCode",$E20,"WCCode",$B20,"WCState",$G20,"State",$H20,"PayID",$BE$12,"Units",AG20,"UnionID",$B$3,"UnionLocal",$F20,"UnionClass",$I20,"CertifiedClass",$J20)),0) -> 0 | CE20: =IF(AND(NOT(ISBLANK($C20)),NOT(ISBLANK($E20)),$A20="x"),IF(AH20=0,0,[2]!TSImport("PRTime","","Time_NINE","","Date",$CA$11,"Employee",$B$2,"JCJob",$C20,"JCExtra",$D20,"JCCostCode",$E20,"WCCode",$B20,"WCState",$G20,"State",$H20,"PayID",$BF$12,"Units",AH20,"UnionID",$B$3,"UnionLocal",$F20,"UnionClass",$I20,"CertifiedClass",$J20)),0) -> 0 | CF20: =IF(AND(NOT(ISBLANK($C20)),NOT(ISBLANK($E20)),$A20="x"),IF(AI20=0,0,[2]!TSImport("PRTime","","Time_NINE","","Date",$CA$11,"Employee",$B$2,"JCJob",$C20,"JCExtra",$D20,"JCCostCode",$E20,"WCCode",$B20,"WCState",$G20,"State",$H20,"PayID",$BG$12,"Units",AI20,"UnionID",$B$3,"UnionLocal",$F20,"UnionClass",$I20,"CertifiedClass",$J20)),0) -> 0 | CG20: =IF(AND(NOT(ISBLANK($C20)),NOT(ISBLANK($E20)),$A20="x"),IF(AJ20=0,0,[2]!TSImport("PRTime","","Time_NINE","","Date",$CG$11,"Employee",$B$2,"JCJob",$C20,"JCExtra",$D20,"JCCostCode",$E20,"WCCode",$B20,"WCState",$G20,"State",$H20,"PayID",$BB$12,"Units",AJ20,"UnionID",$B$3,"UnionLocal",$F20,"UnionClass",$I20,"CertifiedClass",$J20)),0) -> 0 | CH20: =IF(AND(NOT(ISBLANK($C20)),NOT(ISBLANK($E20)),$A20="x"),IF(AK20=0,0,[2]!TSImport("PRTime","","Time_NINE","","Date",$CG$11,"Employee",$B$2,"JCJob",$C20,"JCExtra",$D20,"JCCostCode",$E20,"WCCode",$B20,"WCState",$G20,"State",$H20,"PayID",$BC$12,"Units",AK20,"UnionID",$B$3,"UnionLocal",$F20,"UnionClass",$I20,"CertifiedClass",$J20)),0) -> 0 | CI20: =IF(AND(NOT(ISBLANK($C20)),NOT(ISBLANK($E20)),$A20="x"),IF(AL20=0,0,[2]!TSImport("PRTime","","Time_NINE","","Date",$CG$11,"Employee",$B$2,"JCJob",$C20,"JCExtra",$D20,"JCCostCode",$E20,"WCCode",$B20,"WCState",$G20,"State",$H20,"PayID",$BD$12,"Units",AL20,"UnionID",$B$3,"UnionLocal",$F20,"UnionClass",$I20,"CertifiedClass",$J20)),0) -> 0 | CJ20: =IF(AND(NOT(ISBLANK($C20)),NOT(ISBLANK($E20)),$A20="x"),IF(AM20=0,0,[2]!TSImport("PRTime","","Time_NINE","","Date",$CG$11,"Employee",$B$2,"JCJob",$C20,"JCExtra",$D20,"JCCostCode",$E20,"WCCode",$B20,"WCState",$G20,"State",$H20,"PayID",$BE$12,"Units",AM20,"UnionID",$B$3,"UnionLocal",$F20,"UnionClass",$I20,"CertifiedClass",$J20)),0) -> 0 | CK20: =IF(AND(NOT(ISBLANK($C20)),NOT(ISBLANK($E20)),$A20="x"),IF(AN20=0,0,[2]!TSImport("PRTime","","Time_NINE","","Date",$CG$11,"Employee",$B$2,"JCJob",$C20,"JCExtra",$D20,"JCCostCode",$E20,"WCCode",$B20,"WCState",$G20,"State",$H20,"PayID",$BF$12,"Units",AN20,"UnionID",$B$3,"UnionLocal",$F20,"UnionClass",$I20,"CertifiedClass",$J20)),0) -> 0 | CL20: =IF(AND(NOT(ISBLANK($C20)),NOT(ISBLANK($E20)),$A20="x"),IF(AO20=0,0,[2]!TSImport("PRTime","","Time_NINE","","Date",$CG$11,"Employee",$B$2,"JCJob",$C20,"JCExtra",$D20,"JCCostCode",$E20,"WCCode",$B20,"WCState",$G20,"State",$H20,"PayID",$BG$12,"Units",AO20,"UnionID",$B$3,"UnionLocal",$F20,"UnionClass",$I20,"CertifiedClass",$J20)),0) -> 0 | CM20: =IF(AND(NOT(ISBLANK($C20)),NOT(ISBLANK($E20)),$A20="x"),IF(AP20=0,0,[2]!TSImport("PRTime","","Time_NINE","","Date",$CM$11,"Employee",$B$2,"JCJob",$C20,"JCExtra",$D20,"JCCostCode",$E20,"WCCode",$B20,"WCState",$G20,"State",$H20,"PayID",$BB$12,"Units",AP20,"UnionID",$B$3,"UnionLocal",$F20,"UnionClass",$I20,"CertifiedClass",$J20)),0) -> 0 | CN20: =IF(AND(NOT(ISBLANK($C20)),NOT(ISBLANK($E20)),$A20="x"),IF(AQ20=0,0,[2]!TSImport("PRTime","","Time_NINE","","Date",$CM$11,"Employee",$B$2,"JCJob",$C20,"JCExtra",$D20,"JCCostCode",$E20,"WCCode",$B20,"WCState",$G20,"State",$H20,"PayID",$BC$12,"Units",AQ20,"UnionID",$B$3,"UnionLocal",$F20,"UnionClass",$I20,"CertifiedClass",$J20)),0) -> 0 | CO20: =IF(AND(NOT(ISBLANK($C20)),NOT(ISBLANK($E20)),$A20="x"),IF(AR20=0,0,[2]!TSImport("PRTime","","Time_NINE","","Date",$CM$11,"Employee",$B$2,"JCJob",$C20,"JCExtra",$D20,"JCCostCode",$E20,"WCCode",$B20,"WCState",$G20,"State",$H20,"PayID",$BD$12,"Units",AR20,"UnionID",$B$3,"UnionLocal",$F20,"UnionClass",$I20,"CertifiedClass",$J20)),0) -> 0 | CP20: =IF(AND(NOT(ISBLANK($C20)),NOT(ISBLANK($E20)),$A20="x"),IF(AS20=0,0,[2]!TSImport("PRTime","","Time_NINE","","Date",$CM$11,"Employee",$B$2,"JCJob",$C20,"JCExtra",$D20,"JCCostCode",$E20,"WCCode",$B20,"WCState",$G20,"State",$H20,"PayID",$BE$12,"Units",AS20,"UnionID",$B$3,"UnionLocal",$F20,"UnionClass",$I20,"CertifiedClass",$J20)),0) -> 0 | CQ20: =IF(AND(NOT(ISBLANK($C20)),NOT(ISBLANK($E20)),$A20="x"),IF(AT20=0,0,[2]!TSImport("PRTime","","Time_NINE","","Date",$CM$11,"Employee",$B$2,"JCJob",$C20,"JCExtra",$D20,"JCCostCode",$E20,"WCCode",$B20,"WCState",$G20,"State",$H20,"PayID",$BF$12,"Units",AT20,"UnionID",$B$3,"UnionLocal",$F20,"UnionClass",$I20,"CertifiedClass",$J20)),0) -> 0 | CR20: =IF(AND(NOT(ISBLANK($C20)),NOT(ISBLANK($E20)),$A20="x"),IF(AU20=0,0,[2]!TSImport("PRTime","","Time_NINE","","Date",$CM$11,"Employee",$B$2,"JCJob",$C20,"JCExtra",$D20,"JCCostCode",$E20,"WCCode",$B20,"WCState",$G20,"State",$H20,"PayID",$BG$12,"Units",AU20,"UnionID",$B$3,"UnionLocal",$F20,"UnionClass",$I20,"CertifiedClass",$J20)),0) -> 0 | CS20: =IF(AND(NOT(ISBLANK($C20)),NOT(ISBLANK($E20)),$A20="x"),IF(AV20=0,0,[2]!TSImport("PRTime","","Time_NINE","","Date",$CS$11,"Employee",$B$2,"JCJob",$C20,"JCExtra",$D20,"JCCostCode",$E20,"WCCode",$B20,"WCState",$G20,"State",$H20,"PayID",$BB$12,"Units",AV20,"UnionID",$B$3,"UnionLocal",$F20,"UnionClass",$I20,"CertifiedClass",$J20)),0) -> 0 | CT20: =IF(AND(NOT(ISBLANK($C20)),NOT(ISBLANK($E20)),$A20="x"),IF(AW20=0,0,[2]!TSImport("PRTime","","Time_NINE","","Date",$CS$11,"Employee",$B$2,"JCJob",$C20,"JCExtra",$D20,"JCCostCode",$E20,"WCCode",$B20,"WCState",$G20,"State",$H20,"PayID",$BC$12,"Units",AW20,"UnionID",$B$3,"UnionLocal",$F20,"UnionClass",$I20,"CertifiedClass",$J20)),0) -> 0 | CU20: =IF(AND(NOT(ISBLANK($C20)),NOT(ISBLANK($E20)),$A20="x"),IF(AX20=0,0,[2]!TSImport("PRTime","","Time_NINE","","Date",$CS$11,"Employee",$B$2,"JCJob",$C20,"JCExtra",$D20,"JCCostCode",$E20,"WCCode",$B20,"WCState",$G20,"State",$H20,"PayID",$BD$12,"Units",AX20,"UnionID",$B$3,"UnionLocal",$F20,"UnionClass",$I20,"CertifiedClass",$J20)),0) -> 0 | CV20: =IF(AND(NOT(ISBLANK($C20)),NOT(ISBLANK($E20)),$A20="x"),IF(AY20=0,0,[2]!TSImport("PRTime","","Time_NINE","","Date",$CS$11,"Employee",$B$2,"JCJob",$C20,"JCExtra",$D20,"JCCostCode",$E20,"WCCode",$B20,"WCState",$G20,"State",$H20,"PayID",$BE$12,"Units",AY20,"UnionID",$B$3,"UnionLocal",$F20,"UnionClass",$I20,"CertifiedClass",$J20)),0) -> 0 | CW20: =IF(AND(NOT(ISBLANK($C20)),NOT(ISBLANK($E20)),$A20="x"),IF(AZ20=0,0,[2]!TSImport("PRTime","","Time_NINE","","Date",$CS$11,"Employee",$B$2,"JCJob",$C20,"JCExtra",$D20,"JCCostCode",$E20,"WCCode",$B20,"WCState",$G20,"State",$H20,"PayID",$BF$12,"Units",AZ20,"UnionID",$B$3,"UnionLocal",$F20,"UnionClass",$I20,"CertifiedClass",$J20)),0) -> 0 | CX20: =IF(AND(NOT(ISBLANK($C20)),NOT(ISBLANK($E20)),$A20="x"),IF(BA20=0,0,[2]!TSImport("PRTime","","Time_NINE","","Date",$CS$11,"Employee",$B$2,"JCJob",$C20,"JCExtra",$D20,"JCCostCode",$E20,"WCCode",$B20,"WCState",$G20,"State",$H20,"PayID",$BG$12,"Units",BA20,"UnionID",$B$3,"UnionLocal",$F20,"UnionClass",$I20,"CertifiedClass",$J20)),0) -> 0
A21: =IF(ISBLANK(C21),"",IF(ISBLANK($D$3),"",$D$3)) | F21: =IF(ISBLANK($B$4),"",$B$4) | J21: =IF($K21=0,"",IF($K21<10,"0"&$K21,$K21)) | BB21: =SUM(AV21,AP21,AJ21,AD21,X21,R21,L21) -> 0 | BC21: =SUM(AW21,AQ21,AK21,AE21,Y21,S21,M21) -> 0 | BD21: =SUM(AX21,AR21,AL21,AF21,Z21,T21,N21) -> 0 | BE21: =SUM(AY21,AS21,AM21,AG21,AA21,U21,O21) -> 0 | BF21: =SUM(AZ21,AT21,AN21,AH21,AB21,V21,P21) -> 0 | BG21: =SUM(BA21,AU21,AO21,AI21,AC21,W21,Q21) -> 0 | BH21: =SUM(TimeSheet34[[#This Row],[1]:[4A]]) -> 0 | BI21: =IF(AND(NOT(ISBLANK($C21)),NOT(ISBLANK($E21)),$A21="x"),IF(L21=0,0,[2]!TSImport("PRTime","","Time_NINE","","Date",$BI$11,"Employee",$B$2,"JCJob",$C21,"JCExtra",$D21,"JCCostCode",$E21,"WCCode",$B21,"WCState",$G21,"State",$H21,"PayID",$BB$12,"Units",L21,"UnionID",$B$3,"UnionLocal",$F21,"UnionClass",$I21,"CertifiedClass",$J21)),0) -> 0 | BJ21: =IF(AND(NOT(ISBLANK($C21)),NOT(ISBLANK($E21)),$A21="x"),IF(M21=0,0,[2]!TSImport("PRTime","","Time_NINE","","Date",$BI$11,"Employee",$B$2,"JCJob",$C21,"JCExtra",$D21,"JCCostCode",$E21,"WCCode",$B21,"WCState",$G21,"State",$H21,"PayID",$BC$12,"Units",M21,"UnionID",$B$3,"UnionLocal",$F21,"UnionClass",$I21,"CertifiedClass",$J21)),0) -> 0 | BK21: =IF(AND(NOT(ISBLANK($C21)),NOT(ISBLANK($E21)),$A21="x"),IF(N21=0,0,[2]!TSImport("PRTime","","Time_NINE","","Date",$BI$11,"Employee",$B$2,"JCJob",$C21,"JCExtra",$D21,"JCCostCode",$E21,"WCCode",$B21,"WCState",$G21,"State",$H21,"PayID",$BD$12,"Units",N21,"UnionID",$B$3,"UnionLocal",$F21,"UnionClass",$I21,"CertifiedClass",$J21)),0) -> 0 | BL21: =IF(AND(NOT(ISBLANK($C21)),NOT(ISBLANK($E21)),$A21="x"),IF(O21=0,0,[2]!TSImport("PRTime","","Time_NINE","","Date",$BI$11,"Employee",$B$2,"JCJob",$C21,"JCExtra",$D21,"JCCostCode",$E21,"WCCode",$B21,"WCState",$G21,"State",$H21,"PayID",$BE$12,"Units",O21,"UnionID",$B$3,"UnionLocal",$F21,"UnionClass",$I21,"CertifiedClass",$J21)),0) -> 0 | BM21: =IF(AND(NOT(ISBLANK($C21)),NOT(ISBLANK($E21)),$A21="x"),IF(P21=0,0,[2]!TSImport("PRTime","","Time_NINE","","Date",$BI$11,"Employee",$B$2,"JCJob",$C21,"JCExtra",$D21,"JCCostCode",$E21,"WCCode",$B21,"WCState",$G21,"State",$H21,"PayID",$BF$12,"Units",P21,"UnionID",$B$3,"UnionLocal",$F21,"UnionClass",$I21,"CertifiedClass",$J21)),0) -> 0 | BN21: =IF(AND(NOT(ISBLANK($C21)),NOT(ISBLANK($E21)),$A21="x"),IF(Q21=0,0,[2]!TSImport("PRTime","","Time_NINE","","Date",$BI$11,"Employee",$B$2,"JCJob",$C21,"JCExtra",$D21,"JCCostCode",$E21,"WCCode",$B21,"WCState",$G21,"State",$H21,"PayID",$BG$12,"Units",Q21,"UnionID",$B$3,"UnionLocal",$F21,"UnionClass",$I21,"CertifiedClass",$J21)),0) -> 0 | BO21: =IF(AND(NOT(ISBLANK($C21)),NOT(ISBLANK($E21)),$A21="x"),IF(R21=0,0,[2]!TSImport("PRTime","","Time_NINE","","Date",$BO$11,"Employee",$B$2,"JCJob",$C21,"JCExtra",$D21,"JCCostCode",$E21,"WCCode",$B21,"WCState",$G21,"State",$H21,"PayID",$BB$12,"Units",R21,"UnionID",$B$3,"UnionLocal",$F21,"UnionClass",$I21,"CertifiedClass",$J21)),0) -> 0 | BP21: =IF(AND(NOT(ISBLANK($C21)),NOT(ISBLANK($E21)),$A21="x"),IF(S21=0,0,[2]!TSImport("PRTime","","Time_NINE","","Date",$BO$11,"Employee",$B$2,"JCJob",$C21,"JCExtra",$D21,"JCCostCode",$E21,"WCCode",$B21,"WCState",$G21,"State",$H21,"PayID",$BC$12,"Units",S21,"UnionID",$B$3,"UnionLocal",$F21,"UnionClass",$I21,"CertifiedClass",$J21)),0) -> 0 | BQ21: =IF(AND(NOT(ISBLANK($C21)),NOT(ISBLANK($E21)),$A21="x"),IF(T21=0,0,[2]!TSImport("PRTime","","Time_NINE","","Date",$BO$11,"Employee",$B$2,"JCJob",$C21,"JCExtra",$D21,"JCCostCode",$E21,"WCCode",$B21,"WCState",$G21,"State",$H21,"PayID",$BD$12,"Units",T21,"UnionID",$B$3,"UnionLocal",$F21,"UnionClass",$I21,"CertifiedClass",$J21)),0) -> 0 | BR21: =IF(AND(NOT(ISBLANK($C21)),NOT(ISBLANK($E21)),$A21="x"),IF(U21=0,0,[2]!TSImport("PRTime","","Time_NINE","","Date",$BO$11,"Employee",$B$2,"JCJob",$C21,"JCExtra",$D21,"JCCostCode",$E21,"WCCode",$B21,"WCState",$G21,"State",$H21,"PayID",$BE$12,"Units",U21,"UnionID",$B$3,"UnionLocal",$F21,"UnionClass",$I21,"CertifiedClass",$J21)),0) -> 0 | BS21: =IF(AND(NOT(ISBLANK($C21)),NOT(ISBLANK($E21)),$A21="x"),IF(V21=0,0,[2]!TSImport("PRTime","","Time_NINE","","Date",$BO$11,"Employee",$B$2,"JCJob",$C21,"JCExtra",$D21,"JCCostCode",$E21,"WCCode",$B21,"WCState",$G21,"State",$H21,"PayID",$BF$12,"Units",V21,"UnionID",$B$3,"UnionLocal",$F21,"UnionClass",$I21,"CertifiedClass",$J21)),0) -> 0 | BT21: =IF(AND(NOT(ISBLANK($C21)),NOT(ISBLANK($E21)),$A21="x"),IF(W21=0,0,[2]!TSImport("PRTime","","Time_NINE","","Date",$BO$11,"Employee",$B$2,"JCJob",$C21,"JCExtra",$D21,"JCCostCode",$E21,"WCCode",$B21,"WCState",$G21,"State",$H21,"PayID",$BG$12,"Units",W21,"UnionID",$B$3,"UnionLocal",$F21,"UnionClass",$I21,"CertifiedClass",$J21)),0) -> 0 | BU21: =IF(AND(NOT(ISBLANK($C21)),NOT(ISBLANK($E21)),$A21="x"),IF(X21=0,0,[2]!TSImport("PRTime","","Time_NINE","","Date",$BU$11,"Employee",$B$2,"JCJob",$C21,"JCExtra",$D21,"JCCostCode",$E21,"WCCode",$B21,"WCState",$G21,"State",$H21,"PayID",$BB$12,"Units",X21,"UnionID",$B$3,"UnionLocal",$F21,"UnionClass",$I21,"CertifiedClass",$J21)),0) -> 0 | BV21: =IF(AND(NOT(ISBLANK($C21)),NOT(ISBLANK($E21)),$A21="x"),IF(Y21=0,0,[2]!TSImport("PRTime","","Time_NINE","","Date",$BU$11,"Employee",$B$2,"JCJob",$C21,"JCExtra",$D21,"JCCostCode",$E21,"WCCode",$B21,"WCState",$G21,"State",$H21,"PayID",$BC$12,"Units",Y21,"UnionID",$B$3,"UnionLocal",$F21,"UnionClass",$I21,"CertifiedClass",$J21)),0) -> 0 | BW21: =IF(AND(NOT(ISBLANK($C21)),NOT(ISBLANK($E21)),$A21="x"),IF(Z21=0,0,[2]!TSImport("PRTime","","Time_NINE","","Date",$BU$11,"Employee",$B$2,"JCJob",$C21,"JCExtra",$D21,"JCCostCode",$E21,"WCCode",$B21,"WCState",$G21,"State",$H21,"PayID",$BD$12,"Units",Z21,"UnionID",$B$3,"UnionLocal",$F21,"UnionClass",$I21,"CertifiedClass",$J21)),0) -> 0 | BX21: =IF(AND(NOT(ISBLANK($C21)),NOT(ISBLANK($E21)),$A21="x"),IF(AA21=0,0,[2]!TSImport("PRTime","","Time_NINE","","Date",$BU$11,"Employee",$B$2,"JCJob",$C21,"JCExtra",$D21,"JCCostCode",$E21,"WCCode",$B21,"WCState",$G21,"State",$H21,"PayID",$BE$12,"Units",AA21,"UnionID",$B$3,"UnionLocal",$F21,"UnionClass",$I21,"CertifiedClass",$J21)),0) -> 0 | BY21: =IF(AND(NOT(ISBLANK($C21)),NOT(ISBLANK($E21)),$A21="x"),IF(AB21=0,0,[2]!TSImport("PRTime","","Time_NINE","","Date",$BU$11,"Employee",$B$2,"JCJob",$C21,"JCExtra",$D21,"JCCostCode",$E21,"WCCode",$B21,"WCState",$G21,"State",$H21,"PayID",$BF$12,"Units",AB21,"UnionID",$B$3,"UnionLocal",$F21,"UnionClass",$I21,"CertifiedClass",$J21)),0) -> 0 | BZ21: =IF(AND(NOT(ISBLANK($C21)),NOT(ISBLANK($E21)),$A21="x"),IF(AC21=0,0,[2]!TSImport("PRTime","","Time_NINE","","Date",$BU$11,"Employee",$B$2,"JCJob",$C21,"JCExtra",$D21,"JCCostCode",$E21,"WCCode",$B21,"WCState",$G21,"State",$H21,"PayID",$BG$12,"Units",AC21,"UnionID",$B$3,"UnionLocal",$F21,"UnionClass",$I21,"CertifiedClass",$J21)),0) -> 0 | CA21: =IF(AND(NOT(ISBLANK($C21)),NOT(ISBLANK($E21)),$A21="x"),IF(AD21=0,0,[2]!TSImport("PRTime","","Time_NINE","","Date",$CA$11,"Employee",$B$2,"JCJob",$C21,"JCExtra",$D21,"JCCostCode",$E21,"WCCode",$B21,"WCState",$G21,"State",$H21,"PayID",$BB$12,"Units",AD21,"UnionID",$B$3,"UnionLocal",$F21,"UnionClass",$I21,"CertifiedClass",$J21)),0) -> 0 | CB21: =IF(AND(NOT(ISBLANK($C21)),NOT(ISBLANK($E21)),$A21="x"),IF(AE21=0,0,[2]!TSImport("PRTime","","Time_NINE","","Date",$CA$11,"Employee",$B$2,"JCJob",$C21,"JCExtra",$D21,"JCCostCode",$E21,"WCCode",$B21,"WCState",$G21,"State",$H21,"PayID",$BC$12,"Units",AE21,"UnionID",$B$3,"UnionLocal",$F21,"UnionClass",$I21,"CertifiedClass",$J21)),0) -> 0 | CC21: =IF(AND(NOT(ISBLANK($C21)),NOT(ISBLANK($E21)),$A21="x"),IF(AF21=0,0,[2]!TSImport("PRTime","","Time_NINE","","Date",$CA$11,"Employee",$B$2,"JCJob",$C21,"JCExtra",$D21,"JCCostCode",$E21,"WCCode",$B21,"WCState",$G21,"State",$H21,"PayID",$BD$12,"Units",AF21,"UnionID",$B$3,"UnionLocal",$F21,"UnionClass",$I21,"CertifiedClass",$J21)),0) -> 0 | CD21: =IF(AND(NOT(ISBLANK($C21)),NOT(ISBLANK($E21)),$A21="x"),IF(AG21=0,0,[2]!TSImport("PRTime","","Time_NINE","","Date",$CA$11,"Employee",$B$2,"JCJob",$C21,"JCExtra",$D21,"JCCostCode",$E21,"WCCode",$B21,"WCState",$G21,"State",$H21,"PayID",$BE$12,"Units",AG21,"UnionID",$B$3,"UnionLocal",$F21,"UnionClass",$I21,"CertifiedClass",$J21)),0) -> 0 | CE21: =IF(AND(NOT(ISBLANK($C21)),NOT(ISBLANK($E21)),$A21="x"),IF(AH21=0,0,[2]!TSImport("PRTime","","Time_NINE","","Date",$CA$11,"Employee",$B$2,"JCJob",$C21,"JCExtra",$D21,"JCCostCode",$E21,"WCCode",$B21,"WCState",$G21,"State",$H21,"PayID",$BF$12,"Units",AH21,"UnionID",$B$3,"UnionLocal",$F21,"UnionClass",$I21,"CertifiedClass",$J21)),0) -> 0 | CF21: =IF(AND(NOT(ISBLANK($C21)),NOT(ISBLANK($E21)),$A21="x"),IF(AI21=0,0,[2]!TSImport("PRTime","","Time_NINE","","Date",$CA$11,"Employee",$B$2,"JCJob",$C21,"JCExtra",$D21,"JCCostCode",$E21,"WCCode",$B21,"WCState",$G21,"State",$H21,"PayID",$BG$12,"Units",AI21,"UnionID",$B$3,"UnionLocal",$F21,"UnionClass",$I21,"CertifiedClass",$J21)),0) -> 0 | CG21: =IF(AND(NOT(ISBLANK($C21)),NOT(ISBLANK($E21)),$A21="x"),IF(AJ21=0,0,[2]!TSImport("PRTime","","Time_NINE","","Date",$CG$11,"Employee",$B$2,"JCJob",$C21,"JCExtra",$D21,"JCCostCode",$E21,"WCCode",$B21,"WCState",$G21,"State",$H21,"PayID",$BB$12,"Units",AJ21,"UnionID",$B$3,"UnionLocal",$F21,"UnionClass",$I21,"CertifiedClass",$J21)),0) -> 0 | CH21: =IF(AND(NOT(ISBLANK($C21)),NOT(ISBLANK($E21)),$A21="x"),IF(AK21=0,0,[2]!TSImport("PRTime","","Time_NINE","","Date",$CG$11,"Employee",$B$2,"JCJob",$C21,"JCExtra",$D21,"JCCostCode",$E21,"WCCode",$B21,"WCState",$G21,"State",$H21,"PayID",$BC$12,"Units",AK21,"UnionID",$B$3,"UnionLocal",$F21,"UnionClass",$I21,"CertifiedClass",$J21)),0) -> 0 | CI21: =IF(AND(NOT(ISBLANK($C21)),NOT(ISBLANK($E21)),$A21="x"),IF(AL21=0,0,[2]!TSImport("PRTime","","Time_NINE","","Date",$CG$11,"Employee",$B$2,"JCJob",$C21,"JCExtra",$D21,"JCCostCode",$E21,"WCCode",$B21,"WCState",$G21,"State",$H21,"PayID",$BD$12,"Units",AL21,"UnionID",$B$3,"UnionLocal",$F21,"UnionClass",$I21,"CertifiedClass",$J21)),0) -> 0 | CJ21: =IF(AND(NOT(ISBLANK($C21)),NOT(ISBLANK($E21)),$A21="x"),IF(AM21=0,0,[2]!TSImport("PRTime","","Time_NINE","","Date",$CG$11,"Employee",$B$2,"JCJob",$C21,"JCExtra",$D21,"JCCostCode",$E21,"WCCode",$B21,"WCState",$G21,"State",$H21,"PayID",$BE$12,"Units",AM21,"UnionID",$B$3,"UnionLocal",$F21,"UnionClass",$I21,"CertifiedClass",$J21)),0) -> 0 | CK21: =IF(AND(NOT(ISBLANK($C21)),NOT(ISBLANK($E21)),$A21="x"),IF(AN21=0,0,[2]!TSImport("PRTime","","Time_NINE","","Date",$CG$11,"Employee",$B$2,"JCJob",$C21,"JCExtra",$D21,"JCCostCode",$E21,"WCCode",$B21,"WCState",$G21,"State",$H21,"PayID",$BF$12,"Units",AN21,"UnionID",$B$3,"UnionLocal",$F21,"UnionClass",$I21,"CertifiedClass",$J21)),0) -> 0 | CL21: =IF(AND(NOT(ISBLANK($C21)),NOT(ISBLANK($E21)),$A21="x"),IF(AO21=0,0,[2]!TSImport("PRTime","","Time_NINE","","Date",$CG$11,"Employee",$B$2,"JCJob",$C21,"JCExtra",$D21,"JCCostCode",$E21,"WCCode",$B21,"WCState",$G21,"State",$H21,"PayID",$BG$12,"Units",AO21,"UnionID",$B$3,"UnionLocal",$F21,"UnionClass",$I21,"CertifiedClass",$J21)),0) -> 0 | CM21: =IF(AND(NOT(ISBLANK($C21)),NOT(ISBLANK($E21)),$A21="x"),IF(AP21=0,0,[2]!TSImport("PRTime","","Time_NINE","","Date",$CM$11,"Employee",$B$2,"JCJob",$C21,"JCExtra",$D21,"JCCostCode",$E21,"WCCode",$B21,"WCState",$G21,"State",$H21,"PayID",$BB$12,"Units",AP21,"UnionID",$B$3,"UnionLocal",$F21,"UnionClass",$I21,"CertifiedClass",$J21)),0) -> 0 | CN21: =IF(AND(NOT(ISBLANK($C21)),NOT(ISBLANK($E21)),$A21="x"),IF(AQ21=0,0,[2]!TSImport("PRTime","","Time_NINE","","Date",$CM$11,"Employee",$B$2,"JCJob",$C21,"JCExtra",$D21,"JCCostCode",$E21,"WCCode",$B21,"WCState",$G21,"State",$H21,"PayID",$BC$12,"Units",AQ21,"UnionID",$B$3,"UnionLocal",$F21,"UnionClass",$I21,"CertifiedClass",$J21)),0) -> 0 | CO21: =IF(AND(NOT(ISBLANK($C21)),NOT(ISBLANK($E21)),$A21="x"),IF(AR21=0,0,[2]!TSImport("PRTime","","Time_NINE","","Date",$CM$11,"Employee",$B$2,"JCJob",$C21,"JCExtra",$D21,"JCCostCode",$E21,"WCCode",$B21,"WCState",$G21,"State",$H21,"PayID",$BD$12,"Units",AR21,"UnionID",$B$3,"UnionLocal",$F21,"UnionClass",$I21,"CertifiedClass",$J21)),0) -> 0 | CP21: =IF(AND(NOT(ISBLANK($C21)),NOT(ISBLANK($E21)),$A21="x"),IF(AS21=0,0,[2]!TSImport("PRTime","","Time_NINE","","Date",$CM$11,"Employee",$B$2,"JCJob",$C21,"JCExtra",$D21,"JCCostCode",$E21,"WCCode",$B21,"WCState",$G21,"State",$H21,"PayID",$BE$12,"Units",AS21,"UnionID",$B$3,"UnionLocal",$F21,"UnionClass",$I21,"CertifiedClass",$J21)),0) -> 0 | CQ21: =IF(AND(NOT(ISBLANK($C21)),NOT(ISBLANK($E21)),$A21="x"),IF(AT21=0,0,[2]!TSImport("PRTime","","Time_NINE","","Date",$CM$11,"Employee",$B$2,"JCJob",$C21,"JCExtra",$D21,"JCCostCode",$E21,"WCCode",$B21,"WCState",$G21,"State",$H21,"PayID",$BF$12,"Units",AT21,"UnionID",$B$3,"UnionLocal",$F21,"UnionClass",$I21,"CertifiedClass",$J21)),0) -> 0 | CR21: =IF(AND(NOT(ISBLANK($C21)),NOT(ISBLANK($E21)),$A21="x"),IF(AU21=0,0,[2]!TSImport("PRTime","","Time_NINE","","Date",$CM$11,"Employee",$B$2,"JCJob",$C21,"JCExtra",$D21,"JCCostCode",$E21,"WCCode",$B21,"WCState",$G21,"State",$H21,"PayID",$BG$12,"Units",AU21,"UnionID",$B$3,"UnionLocal",$F21,"UnionClass",$I21,"CertifiedClass",$J21)),0) -> 0 | CS21: =IF(AND(NOT(ISBLANK($C21)),NOT(ISBLANK($E21)),$A21="x"),IF(AV21=0,0,[2]!TSImport("PRTime","","Time_NINE","","Date",$CS$11,"Employee",$B$2,"JCJob",$C21,"JCExtra",$D21,"JCCostCode",$E21,"WCCode",$B21,"WCState",$G21,"State",$H21,"PayID",$BB$12,"Units",AV21,"UnionID",$B$3,"UnionLocal",$F21,"UnionClass",$I21,"CertifiedClass",$J21)),0) -> 0 | CT21: =IF(AND(NOT(ISBLANK($C21)),NOT(ISBLANK($E21)),$A21="x"),IF(AW21=0,0,[2]!TSImport("PRTime","","Time_NINE","","Date",$CS$11,"Employee",$B$2,"JCJob",$C21,"JCExtra",$D21,"JCCostCode",$E21,"WCCode",$B21,"WCState",$G21,"State",$H21,"PayID",$BC$12,"Units",AW21,"UnionID",$B$3,"UnionLocal",$F21,"UnionClass",$I21,"CertifiedClass",$J21)),0) -> 0 | CU21: =IF(AND(NOT(ISBLANK($C21)),NOT(ISBLANK($E21)),$A21="x"),IF(AX21=0,0,[2]!TSImport("PRTime","","Time_NINE","","Date",$CS$11,"Employee",$B$2,"JCJob",$C21,"JCExtra",$D21,"JCCostCode",$E21,"WCCode",$B21,"WCState",$G21,"State",$H21,"PayID",$BD$12,"Units",AX21,"UnionID",$B$3,"UnionLocal",$F21,"UnionClass",$I21,"CertifiedClass",$J21)),0) -> 0 | CV21: =IF(AND(NOT(ISBLANK($C21)),NOT(ISBLANK($E21)),$A21="x"),IF(AY21=0,0,[2]!TSImport("PRTime","","Time_NINE","","Date",$CS$11,"Employee",$B$2,"JCJob",$C21,"JCExtra",$D21,"JCCostCode",$E21,"WCCode",$B21,"WCState",$G21,"State",$H21,"PayID",$BE$12,"Units",AY21,"UnionID",$B$3,"UnionLocal",$F21,"UnionClass",$I21,"CertifiedClass",$J21)),0) -> 0 | CW21: =IF(AND(NOT(ISBLANK($C21)),NOT(ISBLANK($E21)),$A21="x"),IF(AZ21=0,0,[2]!TSImport("PRTime","","Time_NINE","","Date",$CS$11,"Employee",$B$2,"JCJob",$C21,"JCExtra",$D21,"JCCostCode",$E21,"WCCode",$B21,"WCState",$G21,"State",$H21,"PayID",$BF$12,"Units",AZ21,"UnionID",$B$3,"UnionLocal",$F21,"UnionClass",$I21,"CertifiedClass",$J21)),0) -> 0 | CX21: =IF(AND(NOT(ISBLANK($C21)),NOT(ISBLANK($E21)),$A21="x"),IF(BA21=0,0,[2]!TSImport("PRTime","","Time_NINE","","Date",$CS$11,"Employee",$B$2,"JCJob",$C21,"JCExtra",$D21,"JCCostCode",$E21,"WCCode",$B21,"WCState",$G21,"State",$H21,"PayID",$BG$12,"Units",BA21,"UnionID",$B$3,"UnionLocal",$F21,"UnionClass",$I21,"CertifiedClass",$J21)),0) -> 0
A22: =IF(ISBLANK(C22),"",IF(ISBLANK($D$3),"",$D$3)) | F22: =IF(ISBLANK($B$4),"",$B$4) | J22: =IF($K22=0,"",IF($K22<10,"0"&$K22,$K22)) | BB22: =SUM(AV22,AP22,AJ22,AD22,X22,R22,L22) -> 0 | BC22: =SUM(AW22,AQ22,AK22,AE22,Y22,S22,M22) -> 0 | BD22: =SUM(AX22,AR22,AL22,AF22,Z22,T22,N22) -> 0 | BE22: =SUM(AY22,AS22,AM22,AG22,AA22,U22,O22) -> 0 | BF22: =SUM(AZ22,AT22,AN22,AH22,AB22,V22,P22) -> 0 | BG22: =SUM(BA22,AU22,AO22,AI22,AC22,W22,Q22) -> 0 | BH22: =SUM(TimeSheet34[[#This Row],[1]:[4A]]) -> 0 | BI22: =IF(AND(NOT(ISBLANK($C22)),NOT(ISBLANK($E22)),$A22="x"),IF(L22=0,0,[2]!TSImport("PRTime","","Time_NINE","","Date",$BI$11,"Employee",$B$2,"JCJob",$C22,"JCExtra",$D22,"JCCostCode",$E22,"WCCode",$B22,"WCState",$G22,"State",$H22,"PayID",$BB$12,"Units",L22,"UnionID",$B$3,"UnionLocal",$F22,"UnionClass",$I22,"CertifiedClass",$J22)),0) -> 0 | BJ22: =IF(AND(NOT(ISBLANK($C22)),NOT(ISBLANK($E22)),$A22="x"),IF(M22=0,0,[2]!TSImport("PRTime","","Time_NINE","","Date",$BI$11,"Employee",$B$2,"JCJob",$C22,"JCExtra",$D22,"JCCostCode",$E22,"WCCode",$B22,"WCState",$G22,"State",$H22,"PayID",$BC$12,"Units",M22,"UnionID",$B$3,"UnionLocal",$F22,"UnionClass",$I22,"CertifiedClass",$J22)),0) -> 0 | BK22: =IF(AND(NOT(ISBLANK($C22)),NOT(ISBLANK($E22)),$A22="x"),IF(N22=0,0,[2]!TSImport("PRTime","","Time_NINE","","Date",$BI$11,"Employee",$B$2,"JCJob",$C22,"JCExtra",$D22,"JCCostCode",$E22,"WCCode",$B22,"WCState",$G22,"State",$H22,"PayID",$BD$12,"Units",N22,"UnionID",$B$3,"UnionLocal",$F22,"UnionClass",$I22,"CertifiedClass",$J22)),0) -> 0 | BL22: =IF(AND(NOT(ISBLANK($C22)),NOT(ISBLANK($E22)),$A22="x"),IF(O22=0,0,[2]!TSImport("PRTime","","Time_NINE","","Date",$BI$11,"Employee",$B$2,"JCJob",$C22,"JCExtra",$D22,"JCCostCode",$E22,"WCCode",$B22,"WCState",$G22,"State",$H22,"PayID",$BE$12,"Units",O22,"UnionID",$B$3,"UnionLocal",$F22,"UnionClass",$I22,"CertifiedClass",$J22)),0) -> 0 | BM22: =IF(AND(NOT(ISBLANK($C22)),NOT(ISBLANK($E22)),$A22="x"),IF(P22=0,0,[2]!TSImport("PRTime","","Time_NINE","","Date",$BI$11,"Employee",$B$2,"JCJob",$C22,"JCExtra",$D22,"JCCostCode",$E22,"WCCode",$B22,"WCState",$G22,"State",$H22,"PayID",$BF$12,"Units",P22,"UnionID",$B$3,"UnionLocal",$F22,"UnionClass",$I22,"CertifiedClass",$J22)),0) -> 0 | BN22: =IF(AND(NOT(ISBLANK($C22)),NOT(ISBLANK($E22)),$A22="x"),IF(Q22=0,0,[2]!TSImport("PRTime","","Time_NINE","","Date",$BI$11,"Employee",$B$2,"JCJob",$C22,"JCExtra",$D22,"JCCostCode",$E22,"WCCode",$B22,"WCState",$G22,"State",$H22,"PayID",$BG$12,"Units",Q22,"UnionID",$B$3,"UnionLocal",$F22,"UnionClass",$I22,"CertifiedClass",$J22)),0) -> 0 | BO22: =IF(AND(NOT(ISBLANK($C22)),NOT(ISBLANK($E22)),$A22="x"),IF(R22=0,0,[2]!TSImport("PRTime","","Time_NINE","","Date",$BO$11,"Employee",$B$2,"JCJob",$C22,"JCExtra",$D22,"JCCostCode",$E22,"WCCode",$B22,"WCState",$G22,"State",$H22,"PayID",$BB$12,"Units",R22,"UnionID",$B$3,"UnionLocal",$F22,"UnionClass",$I22,"CertifiedClass",$J22)),0) -> 0 | BP22: =IF(AND(NOT(ISBLANK($C22)),NOT(ISBLANK($E22)),$A22="x"),IF(S22=0,0,[2]!TSImport("PRTime","","Time_NINE","","Date",$BO$11,"Employee",$B$2,"JCJob",$C22,"JCExtra",$D22,"JCCostCode",$E22,"WCCode",$B22,"WCState",$G22,"State",$H22,"PayID",$BC$12,"Units",S22,"UnionID",$B$3,"UnionLocal",$F22,"UnionClass",$I22,"CertifiedClass",$J22)),0) -> 0 | BQ22: =IF(AND(NOT(ISBLANK($C22)),NOT(ISBLANK($E22)),$A22="x"),IF(T22=0,0,[2]!TSImport("PRTime","","Time_NINE","","Date",$BO$11,"Employee",$B$2,"JCJob",$C22,"JCExtra",$D22,"JCCostCode",$E22,"WCCode",$B22,"WCState",$G22,"State",$H22,"PayID",$BD$12,"Units",T22,"UnionID",$B$3,"UnionLocal",$F22,"UnionClass",$I22,"CertifiedClass",$J22)),0) -> 0 | BR22: =IF(AND(NOT(ISBLANK($C22)),NOT(ISBLANK($E22)),$A22="x"),IF(U22=0,0,[2]!TSImport("PRTime","","Time_NINE","","Date",$BO$11,"Employee",$B$2,"JCJob",$C22,"JCExtra",$D22,"JCCostCode",$E22,"WCCode",$B22,"WCState",$G22,"State",$H22,"PayID",$BE$12,"Units",U22,"UnionID",$B$3,"UnionLocal",$F22,"UnionClass",$I22,"CertifiedClass",$J22)),0) -> 0 | BS22: =IF(AND(NOT(ISBLANK($C22)),NOT(ISBLANK($E22)),$A22="x"),IF(V22=0,0,[2]!TSImport("PRTime","","Time_NINE","","Date",$BO$11,"Employee",$B$2,"JCJob",$C22,"JCExtra",$D22,"JCCostCode",$E22,"WCCode",$B22,"WCState",$G22,"State",$H22,"PayID",$BF$12,"Units",V22,"UnionID",$B$3,"UnionLocal",$F22,"UnionClass",$I22,"CertifiedClass",$J22)),0) -> 0 | BT22: =IF(AND(NOT(ISBLANK($C22)),NOT(ISBLANK($E22)),$A22="x"),IF(W22=0,0,[2]!TSImport("PRTime","","Time_NINE","","Date",$BO$11,"Employee",$B$2,"JCJob",$C22,"JCExtra",$D22,"JCCostCode",$E22,"WCCode",$B22,"WCState",$G22,"State",$H22,"PayID",$BG$12,"Units",W22,"UnionID",$B$3,"UnionLocal",$F22,"UnionClass",$I22,"CertifiedClass",$J22)),0) -> 0 | BU22: =IF(AND(NOT(ISBLANK($C22)),NOT(ISBLANK($E22)),$A22="x"),IF(X22=0,0,[2]!TSImport("PRTime","","Time_NINE","","Date",$BU$11,"Employee",$B$2,"JCJob",$C22,"JCExtra",$D22,"JCCostCode",$E22,"WCCode",$B22,"WCState",$G22,"State",$H22,"PayID",$BB$12,"Units",X22,"UnionID",$B$3,"UnionLocal",$F22,"UnionClass",$I22,"CertifiedClass",$J22)),0) -> 0 | BV22: =IF(AND(NOT(ISBLANK($C22)),NOT(ISBLANK($E22)),$A22="x"),IF(Y22=0,0,[2]!TSImport("PRTime","","Time_NINE","","Date",$BU$11,"Employee",$B$2,"JCJob",$C22,"JCExtra",$D22,"JCCostCode",$E22,"WCCode",$B22,"WCState",$G22,"State",$H22,"PayID",$BC$12,"Units",Y22,"UnionID",$B$3,"UnionLocal",$F22,"UnionClass",$I22,"CertifiedClass",$J22)),0) -> 0 | BW22: =IF(AND(NOT(ISBLANK($C22)),NOT(ISBLANK($E22)),$A22="x"),IF(Z22=0,0,[2]!TSImport("PRTime","","Time_NINE","","Date",$BU$11,"Employee",$B$2,"JCJob",$C22,"JCExtra",$D22,"JCCostCode",$E22,"WCCode",$B22,"WCState",$G22,"State",$H22,"PayID",$BD$12,"Units",Z22,"UnionID",$B$3,"UnionLocal",$F22,"UnionClass",$I22,"CertifiedClass",$J22)),0) -> 0 | BX22: =IF(AND(NOT(ISBLANK($C22)),NOT(ISBLANK($E22)),$A22="x"),IF(AA22=0,0,[2]!TSImport("PRTime","","Time_NINE","","Date",$BU$11,"Employee",$B$2,"JCJob",$C22,"JCExtra",$D22,"JCCostCode",$E22,"WCCode",$B22,"WCState",$G22,"State",$H22,"PayID",$BE$12,"Units",AA22,"UnionID",$B$3,"UnionLocal",$F22,"UnionClass",$I22,"CertifiedClass",$J22)),0) -> 0 | BY22: =IF(AND(NOT(ISBLANK($C22)),NOT(ISBLANK($E22)),$A22="x"),IF(AB22=0,0,[2]!TSImport("PRTime","","Time_NINE","","Date",$BU$11,"Employee",$B$2,"JCJob",$C22,"JCExtra",$D22,"JCCostCode",$E22,"WCCode",$B22,"WCState",$G22,"State",$H22,"PayID",$BF$12,"Units",AB22,"UnionID",$B$3,"UnionLocal",$F22,"UnionClass",$I22,"CertifiedClass",$J22)),0) -> 0 | BZ22: =IF(AND(NOT(ISBLANK($C22)),NOT(ISBLANK($E22)),$A22="x"),IF(AC22=0,0,[2]!TSImport("PRTime","","Time_NINE","","Date",$BU$11,"Employee",$B$2,"JCJob",$C22,"JCExtra",$D22,"JCCostCode",$E22,"WCCode",$B22,"WCState",$G22,"State",$H22,"PayID",$BG$12,"Units",AC22,"UnionID",$B$3,"UnionLocal",$F22,"UnionClass",$I22,"CertifiedClass",$J22)),0) -> 0 | CA22: =IF(AND(NOT(ISBLANK($C22)),NOT(ISBLANK($E22)),$A22="x"),IF(AD22=0,0,[2]!TSImport("PRTime","","Time_NINE","","Date",$CA$11,"Employee",$B$2,"JCJob",$C22,"JCExtra",$D22,"JCCostCode",$E22,"WCCode",$B22,"WCState",$G22,"State",$H22,"PayID",$BB$12,"Units",AD22,"UnionID",$B$3,"UnionLocal",$F22,"UnionClass",$I22,"CertifiedClass",$J22)),0) -> 0 | CB22: =IF(AND(NOT(ISBLANK($C22)),NOT(ISBLANK($E22)),$A22="x"),IF(AE22=0,0,[2]!TSImport("PRTime","","Time_NINE","","Date",$CA$11,"Employee",$B$2,"JCJob",$C22,"JCExtra",$D22,"JCCostCode",$E22,"WCCode",$B22,"WCState",$G22,"State",$H22,"PayID",$BC$12,"Units",AE22,"UnionID",$B$3,"UnionLocal",$F22,"UnionClass",$I22,"CertifiedClass",$J22)),0) -> 0 | CC22: =IF(AND(NOT(ISBLANK($C22)),NOT(ISBLANK($E22)),$A22="x"),IF(AF22=0,0,[2]!TSImport("PRTime","","Time_NINE","","Date",$CA$11,"Employee",$B$2,"JCJob",$C22,"JCExtra",$D22,"JCCostCode",$E22,"WCCode",$B22,"WCState",$G22,"State",$H22,"PayID",$BD$12,"Units",AF22,"UnionID",$B$3,"UnionLocal",$F22,"UnionClass",$I22,"CertifiedClass",$J22)),0) -> 0 | CD22: =IF(AND(NOT(ISBLANK($C22)),NOT(ISBLANK($E22)),$A22="x"),IF(AG22=0,0,[2]!TSImport("PRTime","","Time_NINE","","Date",$CA$11,"Employee",$B$2,"JCJob",$C22,"JCExtra",$D22,"JCCostCode",$E22,"WCCode",$B22,"WCState",$G22,"State",$H22,"PayID",$BE$12,"Units",AG22,"UnionID",$B$3,"UnionLocal",$F22,"UnionClass",$I22,"CertifiedClass",$J22)),0) -> 0 | CE22: =IF(AND(NOT(ISBLANK($C22)),NOT(ISBLANK($E22)),$A22="x"),IF(AH22=0,0,[2]!TSImport("PRTime","","Time_NINE","","Date",$CA$11,"Employee",$B$2,"JCJob",$C22,"JCExtra",$D22,"JCCostCode",$E22,"WCCode",$B22,"WCState",$G22,"State",$H22,"PayID",$BF$12,"Units",AH22,"UnionID",$B$3,"UnionLocal",$F22,"UnionClass",$I22,"CertifiedClass",$J22)),0) -> 0 | CF22: =IF(AND(NOT(ISBLANK($C22)),NOT(ISBLANK($E22)),$A22="x"),IF(AI22=0,0,[2]!TSImport("PRTime","","Time_NINE","","Date",$CA$11,"Employee",$B$2,"JCJob",$C22,"JCExtra",$D22,"JCCostCode",$E22,"WCCode",$B22,"WCState",$G22,"State",$H22,"PayID",$BG$12,"Units",AI22,"UnionID",$B$3,"UnionLocal",$F22,"UnionClass",$I22,"CertifiedClass",$J22)),0) -> 0 | CG22: =IF(AND(NOT(ISBLANK($C22)),NOT(ISBLANK($E22)),$A22="x"),IF(AJ22=0,0,[2]!TSImport("PRTime","","Time_NINE","","Date",$CG$11,"Employee",$B$2,"JCJob",$C22,"JCExtra",$D22,"JCCostCode",$E22,"WCCode",$B22,"WCState",$G22,"State",$H22,"PayID",$BB$12,"Units",AJ22,"UnionID",$B$3,"UnionLocal",$F22,"UnionClass",$I22,"CertifiedClass",$J22)),0) -> 0 | CH22: =IF(AND(NOT(ISBLANK($C22)),NOT(ISBLANK($E22)),$A22="x"),IF(AK22=0,0,[2]!TSImport("PRTime","","Time_NINE","","Date",$CG$11,"Employee",$B$2,"JCJob",$C22,"JCExtra",$D22,"JCCostCode",$E22,"WCCode",$B22,"WCState",$G22,"State",$H22,"PayID",$BC$12,"Units",AK22,"UnionID",$B$3,"UnionLocal",$F22,"UnionClass",$I22,"CertifiedClass",$J22)),0) -> 0 | CI22: =IF(AND(NOT(ISBLANK($C22)),NOT(ISBLANK($E22)),$A22="x"),IF(AL22=0,0,[2]!TSImport("PRTime","","Time_NINE","","Date",$CG$11,"Employee",$B$2,"JCJob",$C22,"JCExtra",$D22,"JCCostCode",$E22,"WCCode",$B22,"WCState",$G22,"State",$H22,"PayID",$BD$12,"Units",AL22,"UnionID",$B$3,"UnionLocal",$F22,"UnionClass",$I22,"CertifiedClass",$J22)),0) -> 0 | CJ22: =IF(AND(NOT(ISBLANK($C22)),NOT(ISBLANK($E22)),$A22="x"),IF(AM22=0,0,[2]!TSImport("PRTime","","Time_NINE","","Date",$CG$11,"Employee",$B$2,"JCJob",$C22,"JCExtra",$D22,"JCCostCode",$E22,"WCCode",$B22,"WCState",$G22,"State",$H22,"PayID",$BE$12,"Units",AM22,"UnionID",$B$3,"UnionLocal",$F22,"UnionClass",$I22,"CertifiedClass",$J22)),0) -> 0 | CK22: =IF(AND(NOT(ISBLANK($C22)),NOT(ISBLANK($E22)),$A22="x"),IF(AN22=0,0,[2]!TSImport("PRTime","","Time_NINE","","Date",$CG$11,"Employee",$B$2,"JCJob",$C22,"JCExtra",$D22,"JCCostCode",$E22,"WCCode",$B22,"WCState",$G22,"State",$H22,"PayID",$BF$12,"Units",AN22,"UnionID",$B$3,"UnionLocal",$F22,"UnionClass",$I22,"CertifiedClass",$J22)),0) -> 0 | CL22: =IF(AND(NOT(ISBLANK($C22)),NOT(ISBLANK($E22)),$A22="x"),IF(AO22=0,0,[2]!TSImport("PRTime","","Time_NINE","","Date",$CG$11,"Employee",$B$2,"JCJob",$C22,"JCExtra",$D22,"JCCostCode",$E22,"WCCode",$B22,"WCState",$G22,"State",$H22,"PayID",$BG$12,"Units",AO22,"UnionID",$B$3,"UnionLocal",$F22,"UnionClass",$I22,"CertifiedClass",$J22)),0) -> 0 | CM22: =IF(AND(NOT(ISBLANK($C22)),NOT(ISBLANK($E22)),$A22="x"),IF(AP22=0,0,[2]!TSImport("PRTime","","Time_NINE","","Date",$CM$11,"Employee",$B$2,"JCJob",$C22,"JCExtra",$D22,"JCCostCode",$E22,"WCCode",$B22,"WCState",$G22,"State",$H22,"PayID",$BB$12,"Units",AP22,"UnionID",$B$3,"UnionLocal",$F22,"UnionClass",$I22,"CertifiedClass",$J22)),0) -> 0 | CN22: =IF(AND(NOT(ISBLANK($C22)),NOT(ISBLANK($E22)),$A22="x"),IF(AQ22=0,0,[2]!TSImport("PRTime","","Time_NINE","","Date",$CM$11,"Employee",$B$2,"JCJob",$C22,"JCExtra",$D22,"JCCostCode",$E22,"WCCode",$B22,"WCState",$G22,"State",$H22,"PayID",$BC$12,"Units",AQ22,"UnionID",$B$3,"UnionLocal",$F22,"UnionClass",$I22,"CertifiedClass",$J22)),0) -> 0 | CO22: =IF(AND(NOT(ISBLANK($C22)),NOT(ISBLANK($E22)),$A22="x"),IF(AR22=0,0,[2]!TSImport("PRTime","","Time_NINE","","Date",$CM$11,"Employee",$B$2,"JCJob",$C22,"JCExtra",$D22,"JCCostCode",$E22,"WCCode",$B22,"WCState",$G22,"State",$H22,"PayID",$BD$12,"Units",AR22,"UnionID",$B$3,"UnionLocal",$F22,"UnionClass",$I22,"CertifiedClass",$J22)),0) -> 0 | CP22: =IF(AND(NOT(ISBLANK($C22)),NOT(ISBLANK($E22)),$A22="x"),IF(AS22=0,0,[2]!TSImport("PRTime","","Time_NINE","","Date",$CM$11,"Employee",$B$2,"JCJob",$C22,"JCExtra",$D22,"JCCostCode",$E22,"WCCode",$B22,"WCState",$G22,"State",$H22,"PayID",$BE$12,"Units",AS22,"UnionID",$B$3,"UnionLocal",$F22,"UnionClass",$I22,"CertifiedClass",$J22)),0) -> 0 | CQ22: =IF(AND(NOT(ISBLANK($C22)),NOT(ISBLANK($E22)),$A22="x"),IF(AT22=0,0,[2]!TSImport("PRTime","","Time_NINE","","Date",$CM$11,"Employee",$B$2,"JCJob",$C22,"JCExtra",$D22,"JCCostCode",$E22,"WCCode",$B22,"WCState",$G22,"State",$H22,"PayID",$BF$12,"Units",AT22,"UnionID",$B$3,"UnionLocal",$F22,"UnionClass",$I22,"CertifiedClass",$J22)),0) -> 0 | CR22: =IF(AND(NOT(ISBLANK($C22)),NOT(ISBLANK($E22)),$A22="x"),IF(AU22=0,0,[2]!TSImport("PRTime","","Time_NINE","","Date",$CM$11,"Employee",$B$2,"JCJob",$C22,"JCExtra",$D22,"JCCostCode",$E22,"WCCode",$B22,"WCState",$G22,"State",$H22,"PayID",$BG$12,"Units",AU22,"UnionID",$B$3,"UnionLocal",$F22,"UnionClass",$I22,"CertifiedClass",$J22)),0) -> 0 | CS22: =IF(AND(NOT(ISBLANK($C22)),NOT(ISBLANK($E22)),$A22="x"),IF(AV22=0,0,[2]!TSImport("PRTime","","Time_NINE","","Date",$CS$11,"Employee",$B$2,"JCJob",$C22,"JCExtra",$D22,"JCCostCode",$E22,"WCCode",$B22,"WCState",$G22,"State",$H22,"PayID",$BB$12,"Units",AV22,"UnionID",$B$3,"UnionLocal",$F22,"UnionClass",$I22,"CertifiedClass",$J22)),0) -> 0 | CT22: =IF(AND(NOT(ISBLANK($C22)),NOT(ISBLANK($E22)),$A22="x"),IF(AW22=0,0,[2]!TSImport("PRTime","","Time_NINE","","Date",$CS$11,"Employee",$B$2,"JCJob",$C22,"JCExtra",$D22,"JCCostCode",$E22,"WCCode",$B22,"WCState",$G22,"State",$H22,"PayID",$BC$12,"Units",AW22,"UnionID",$B$3,"UnionLocal",$F22,"UnionClass",$I22,"CertifiedClass",$J22)),0) -> 0 | CU22: =IF(AND(NOT(ISBLANK($C22)),NOT(ISBLANK($E22)),$A22="x"),IF(AX22=0,0,[2]!TSImport("PRTime","","Time_NINE","","Date",$CS$11,"Employee",$B$2,"JCJob",$C22,"JCExtra",$D22,"JCCostCode",$E22,"WCCode",$B22,"WCState",$G22,"State",$H22,"PayID",$BD$12,"Units",AX22,"UnionID",$B$3,"UnionLocal",$F22,"UnionClass",$I22,"CertifiedClass",$J22)),0) -> 0 | CV22: =IF(AND(NOT(ISBLANK($C22)),NOT(ISBLANK($E22)),$A22="x"),IF(AY22=0,0,[2]!TSImport("PRTime","","Time_NINE","","Date",$CS$11,"Employee",$B$2,"JCJob",$C22,"JCExtra",$D22,"JCCostCode",$E22,"WCCode",$B22,"WCState",$G22,"State",$H22,"PayID",$BE$12,"Units",AY22,"UnionID",$B$3,"UnionLocal",$F22,"UnionClass",$I22,"CertifiedClass",$J22)),0) -> 0 | CW22: =IF(AND(NOT(ISBLANK($C22)),NOT(ISBLANK($E22)),$A22="x"),IF(AZ22=0,0,[2]!TSImport("PRTime","","Time_NINE","","Date",$CS$11,"Employee",$B$2,"JCJob",$C22,"JCExtra",$D22,"JCCostCode",$E22,"WCCode",$B22,"WCState",$G22,"State",$H22,"PayID",$BF$12,"Units",AZ22,"UnionID",$B$3,"UnionLocal",$F22,"UnionClass",$I22,"CertifiedClass",$J22)),0) -> 0 | CX22: =IF(AND(NOT(ISBLANK($C22)),NOT(ISBLANK($E22)),$A22="x"),IF(BA22=0,0,[2]!TSImport("PRTime","","Time_NINE","","Date",$CS$11,"Employee",$B$2,"JCJob",$C22,"JCExtra",$D22,"JCCostCode",$E22,"WCCode",$B22,"WCState",$G22,"State",$H22,"PayID",$BG$12,"Units",BA22,"UnionID",$B$3,"UnionLocal",$F22,"UnionClass",$I22,"CertifiedClass",$J22)),0) -> 0
A23: =IF(ISBLANK(C23),"",IF(ISBLANK($D$3),"",$D$3)) | F23: =IF(ISBLANK($B$4),"",$B$4) | J23: =IF($K23=0,"",IF($K23<10,"0"&$K23,$K23)) | BB23: =SUM(AV23,AP23,AJ23,AD23,X23,R23,L23) -> 0 | BC23: =SUM(AW23,AQ23,AK23,AE23,Y23,S23,M23) -> 0 | BD23: =SUM(AX23,AR23,AL23,AF23,Z23,T23,N23) -> 0 | BE23: =SUM(AY23,AS23,AM23,AG23,AA23,U23,O23) -> 0 | BF23: =SUM(AZ23,AT23,AN23,AH23,AB23,V23,P23) -> 0 | BG23: =SUM(BA23,AU23,AO23,AI23,AC23,W23,Q23) -> 0 | BH23: =SUM(TimeSheet34[[#This Row],[1]:[4A]]) -> 0 | BI23: =IF(AND(NOT(ISBLANK($C23)),NOT(ISBLANK($E23)),$A23="x"),IF(L23=0,0,[2]!TSImport("PRTime","","Time_NINE","","Date",$BI$11,"Employee",$B$2,"JCJob",$C23,"JCExtra",$D23,"JCCostCode",$E23,"WCCode",$B23,"WCState",$G23,"State",$H23,"PayID",$BB$12,"Units",L23,"UnionID",$B$3,"UnionLocal",$F23,"UnionClass",$I23,"CertifiedClass",$J23)),0) -> 0 | BJ23: =IF(AND(NOT(ISBLANK($C23)),NOT(ISBLANK($E23)),$A23="x"),IF(M23=0,0,[2]!TSImport("PRTime","","Time_NINE","","Date",$BI$11,"Employee",$B$2,"JCJob",$C23,"JCExtra",$D23,"JCCostCode",$E23,"WCCode",$B23,"WCState",$G23,"State",$H23,"PayID",$BC$12,"Units",M23,"UnionID",$B$3,"UnionLocal",$F23,"UnionClass",$I23,"CertifiedClass",$J23)),0) -> 0 | BK23: =IF(AND(NOT(ISBLANK($C23)),NOT(ISBLANK($E23)),$A23="x"),IF(N23=0,0,[2]!TSImport("PRTime","","Time_NINE","","Date",$BI$11,"Employee",$B$2,"JCJob",$C23,"JCExtra",$D23,"JCCostCode",$E23,"WCCode",$B23,"WCState",$G23,"State",$H23,"PayID",$BD$12,"Units",N23,"UnionID",$B$3,"UnionLocal",$F23,"UnionClass",$I23,"CertifiedClass",$J23)),0) -> 0 | BL23: =IF(AND(NOT(ISBLANK($C23)),NOT(ISBLANK($E23)),$A23="x"),IF(O23=0,0,[2]!TSImport("PRTime","","Time_NINE","","Date",$BI$11,"Employee",$B$2,"JCJob",$C23,"JCExtra",$D23,"JCCostCode",$E23,"WCCode",$B23,"WCState",$G23,"State",$H23,"PayID",$BE$12,"Units",O23,"UnionID",$B$3,"UnionLocal",$F23,"UnionClass",$I23,"CertifiedClass",$J23)),0) -> 0 | BM23: =IF(AND(NOT(ISBLANK($C23)),NOT(ISBLANK($E23)),$A23="x"),IF(P23=0,0,[2]!TSImport("PRTime","","Time_NINE","","Date",$BI$11,"Employee",$B$2,"JCJob",$C23,"JCExtra",$D23,"JCCostCode",$E23,"WCCode",$B23,"WCState",$G23,"State",$H23,"PayID",$BF$12,"Units",P23,"UnionID",$B$3,"UnionLocal",$F23,"UnionClass",$I23,"CertifiedClass",$J23)),0) -> 0 | BN23: =IF(AND(NOT(ISBLANK($C23)),NOT(ISBLANK($E23)),$A23="x"),IF(Q23=0,0,[2]!TSImport("PRTime","","Time_NINE","","Date",$BI$11,"Employee",$B$2,"JCJob",$C23,"JCExtra",$D23,"JCCostCode",$E23,"WCCode",$B23,"WCState",$G23,"State",$H23,"PayID",$BG$12,"Units",Q23,"UnionID",$B$3,"UnionLocal",$F23,"UnionClass",$I23,"CertifiedClass",$J23)),0) -> 0 | BO23: =IF(AND(NOT(ISBLANK($C23)),NOT(ISBLANK($E23)),$A23="x"),IF(R23=0,0,[2]!TSImport("PRTime","","Time_NINE","","Date",$BO$11,"Employee",$B$2,"JCJob",$C23,"JCExtra",$D23,"JCCostCode",$E23,"WCCode",$B23,"WCState",$G23,"State",$H23,"PayID",$BB$12,"Units",R23,"UnionID",$B$3,"UnionLocal",$F23,"UnionClass",$I23,"CertifiedClass",$J23)),0) -> 0 | BP23: =IF(AND(NOT(ISBLANK($C23)),NOT(ISBLANK($E23)),$A23="x"),IF(S23=0,0,[2]!TSImport("PRTime","","Time_NINE","","Date",$BO$11,"Employee",$B$2,"JCJob",$C23,"JCExtra",$D23,"JCCostCode",$E23,"WCCode",$B23,"WCState",$G23,"State",$H23,"PayID",$BC$12,"Units",S23,"UnionID",$B$3,"UnionLocal",$F23,"UnionClass",$I23,"CertifiedClass",$J23)),0) -> 0 | BQ23: =IF(AND(NOT(ISBLANK($C23)),NOT(ISBLANK($E23)),$A23="x"),IF(T23=0,0,[2]!TSImport("PRTime","","Time_NINE","","Date",$BO$11,"Employee",$B$2,"JCJob",$C23,"JCExtra",$D23,"JCCostCode",$E23,"WCCode",$B23,"WCState",$G23,"State",$H23,"PayID",$BD$12,"Units",T23,"UnionID",$B$3,"UnionLocal",$F23,"UnionClass",$I23,"CertifiedClass",$J23)),0) -> 0 | BR23: =IF(AND(NOT(ISBLANK($C23)),NOT(ISBLANK($E23)),$A23="x"),IF(U23=0,0,[2]!TSImport("PRTime","","Time_NINE","","Date",$BO$11,"Employee",$B$2,"JCJob",$C23,"JCExtra",$D23,"JCCostCode",$E23,"WCCode",$B23,"WCState",$G23,"State",$H23,"PayID",$BE$12,"Units",U23,"UnionID",$B$3,"UnionLocal",$F23,"UnionClass",$I23,"CertifiedClass",$J23)),0) -> 0 | BS23: =IF(AND(NOT(ISBLANK($C23)),NOT(ISBLANK($E23)),$A23="x"),IF(V23=0,0,[2]!TSImport("PRTime","","Time_NINE","","Date",$BO$11,"Employee",$B$2,"JCJob",$C23,"JCExtra",$D23,"JCCostCode",$E23,"WCCode",$B23,"WCState",$G23,"State",$H23,"PayID",$BF$12,"Units",V23,"UnionID",$B$3,"UnionLocal",$F23,"UnionClass",$I23,"CertifiedClass",$J23)),0) -> 0 | BT23: =IF(AND(NOT(ISBLANK($C23)),NOT(ISBLANK($E23)),$A23="x"),IF(W23=0,0,[2]!TSImport("PRTime","","Time_NINE","","Date",$BO$11,"Employee",$B$2,"JCJob",$C23,"JCExtra",$D23,"JCCostCode",$E23,"WCCode",$B23,"WCState",$G23,"State",$H23,"PayID",$BG$12,"Units",W23,"UnionID",$B$3,"UnionLocal",$F23,"UnionClass",$I23,"CertifiedClass",$J23)),0) -> 0 | BU23: =IF(AND(NOT(ISBLANK($C23)),NOT(ISBLANK($E23)),$A23="x"),IF(X23=0,0,[2]!TSImport("PRTime","","Time_NINE","","Date",$BU$11,"Employee",$B$2,"JCJob",$C23,"JCExtra",$D23,"JCCostCode",$E23,"WCCode",$B23,"WCState",$G23,"State",$H23,"PayID",$BB$12,"Units",X23,"UnionID",$B$3,"UnionLocal",$F23,"UnionClass",$I23,"CertifiedClass",$J23)),0) -> 0 | BV23: =IF(AND(NOT(ISBLANK($C23)),NOT(ISBLANK($E23)),$A23="x"),IF(Y23=0,0,[2]!TSImport("PRTime","","Time_NINE","","Date",$BU$11,"Employee",$B$2,"JCJob",$C23,"JCExtra",$D23,"JCCostCode",$E23,"WCCode",$B23,"WCState",$G23,"State",$H23,"PayID",$BC$12,"Units",Y23,"UnionID",$B$3,"UnionLocal",$F23,"UnionClass",$I23,"CertifiedClass",$J23)),0) -> 0 | BW23: =IF(AND(NOT(ISBLANK($C23)),NOT(ISBLANK($E23)),$A23="x"),IF(Z23=0,0,[2]!TSImport("PRTime","","Time_NINE","","Date",$BU$11,"Employee",$B$2,"JCJob",$C23,"JCExtra",$D23,"JCCostCode",$E23,"WCCode",$B23,"WCState",$G23,"State",$H23,"PayID",$BD$12,"Units",Z23,"UnionID",$B$3,"UnionLocal",$F23,"UnionClass",$I23,"CertifiedClass",$J23)),0) -> 0 | BX23: =IF(AND(NOT(ISBLANK($C23)),NOT(ISBLANK($E23)),$A23="x"),IF(AA23=0,0,[2]!TSImport("PRTime","","Time_NINE","","Date",$BU$11,"Employee",$B$2,"JCJob",$C23,"JCExtra",$D23,"JCCostCode",$E23,"WCCode",$B23,"WCState",$G23,"State",$H23,"PayID",$BE$12,"Units",AA23,"UnionID",$B$3,"UnionLocal",$F23,"UnionClass",$I23,"CertifiedClass",$J23)),0) -> 0 | BY23: =IF(AND(NOT(ISBLANK($C23)),NOT(ISBLANK($E23)),$A23="x"),IF(AB23=0,0,[2]!TSImport("PRTime","","Time_NINE","","Date",$BU$11,"Employee",$B$2,"JCJob",$C23,"JCExtra",$D23,"JCCostCode",$E23,"WCCode",$B23,"WCState",$G23,"State",$H23,"PayID",$BF$12,"Units",AB23,"UnionID",$B$3,"UnionLocal",$F23,"UnionClass",$I23,"CertifiedClass",$J23)),0) -> 0 | BZ23: =IF(AND(NOT(ISBLANK($C23)),NOT(ISBLANK($E23)),$A23="x"),IF(AC23=0,0,[2]!TSImport("PRTime","","Time_NINE","","Date",$BU$11,"Employee",$B$2,"JCJob",$C23,"JCExtra",$D23,"JCCostCode",$E23,"WCCode",$B23,"WCState",$G23,"State",$H23,"PayID",$BG$12,"Units",AC23,"UnionID",$B$3,"UnionLocal",$F23,"UnionClass",$I23,"CertifiedClass",$J23)),0) -> 0 | CA23: =IF(AND(NOT(ISBLANK($C23)),NOT(ISBLANK($E23)),$A23="x"),IF(AD23=0,0,[2]!TSImport("PRTime","","Time_NINE","","Date",$CA$11,"Employee",$B$2,"JCJob",$C23,"JCExtra",$D23,"JCCostCode",$E23,"WCCode",$B23,"WCState",$G23,"State",$H23,"PayID",$BB$12,"Units",AD23,"UnionID",$B$3,"UnionLocal",$F23,"UnionClass",$I23,"CertifiedClass",$J23)),0) -> 0 | CB23: =IF(AND(NOT(ISBLANK($C23)),NOT(ISBLANK($E23)),$A23="x"),IF(AE23=0,0,[2]!TSImport("PRTime","","Time_NINE","","Date",$CA$11,"Employee",$B$2,"JCJob",$C23,"JCExtra",$D23,"JCCostCode",$E23,"WCCode",$B23,"WCState",$G23,"State",$H23,"PayID",$BC$12,"Units",AE23,"UnionID",$B$3,"UnionLocal",$F23,"UnionClass",$I23,"CertifiedClass",$J23)),0) -> 0 | CC23: =IF(AND(NOT(ISBLANK($C23)),NOT(ISBLANK($E23)),$A23="x"),IF(AF23=0,0,[2]!TSImport("PRTime","","Time_NINE","","Date",$CA$11,"Employee",$B$2,"JCJob",$C23,"JCExtra",$D23,"JCCostCode",$E23,"WCCode",$B23,"WCState",$G23,"State",$H23,"PayID",$BD$12,"Units",AF23,"UnionID",$B$3,"UnionLocal",$F23,"UnionClass",$I23,"CertifiedClass",$J23)),0) -> 0 | CD23: =IF(AND(NOT(ISBLANK($C23)),NOT(ISBLANK($E23)),$A23="x"),IF(AG23=0,0,[2]!TSImport("PRTime","","Time_NINE","","Date",$CA$11,"Employee",$B$2,"JCJob",$C23,"JCExtra",$D23,"JCCostCode",$E23,"WCCode",$B23,"WCState",$G23,"State",$H23,"PayID",$BE$12,"Units",AG23,"UnionID",$B$3,"UnionLocal",$F23,"UnionClass",$I23,"CertifiedClass",$J23)),0) -> 0 | CE23: =IF(AND(NOT(ISBLANK($C23)),NOT(ISBLANK($E23)),$A23="x"),IF(AH23=0,0,[2]!TSImport("PRTime","","Time_NINE","","Date",$CA$11,"Employee",$B$2,"JCJob",$C23,"JCExtra",$D23,"JCCostCode",$E23,"WCCode",$B23,"WCState",$G23,"State",$H23,"PayID",$BF$12,"Units",AH23,"UnionID",$B$3,"UnionLocal",$F23,"UnionClass",$I23,"CertifiedClass",$J23)),0) -> 0 | CF23: =IF(AND(NOT(ISBLANK($C23)),NOT(ISBLANK($E23)),$A23="x"),IF(AI23=0,0,[2]!TSImport("PRTime","","Time_NINE","","Date",$CA$11,"Employee",$B$2,"JCJob",$C23,"JCExtra",$D23,"JCCostCode",$E23,"WCCode",$B23,"WCState",$G23,"State",$H23,"PayID",$BG$12,"Units",AI23,"UnionID",$B$3,"UnionLocal",$F23,"UnionClass",$I23,"CertifiedClass",$J23)),0) -> 0 | CG23: =IF(AND(NOT(ISBLANK($C23)),NOT(ISBLANK($E23)),$A23="x"),IF(AJ23=0,0,[2]!TSImport("PRTime","","Time_NINE","","Date",$CG$11,"Employee",$B$2,"JCJob",$C23,"JCExtra",$D23,"JCCostCode",$E23,"WCCode",$B23,"WCState",$G23,"State",$H23,"PayID",$BB$12,"Units",AJ23,"UnionID",$B$3,"UnionLocal",$F23,"UnionClass",$I23,"CertifiedClass",$J23)),0) -> 0 | CH23: =IF(AND(NOT(ISBLANK($C23)),NOT(ISBLANK($E23)),$A23="x"),IF(AK23=0,0,[2]!TSImport("PRTime","","Time_NINE","","Date",$CG$11,"Employee",$B$2,"JCJob",$C23,"JCExtra",$D23,"JCCostCode",$E23,"WCCode",$B23,"WCState",$G23,"State",$H23,"PayID",$BC$12,"Units",AK23,"UnionID",$B$3,"UnionLocal",$F23,"UnionClass",$I23,"CertifiedClass",$J23)),0) -> 0 | CI23: =IF(AND(NOT(ISBLANK($C23)),NOT(ISBLANK($E23)),$A23="x"),IF(AL23=0,0,[2]!TSImport("PRTime","","Time_NINE","","Date",$CG$11,"Employee",$B$2,"JCJob",$C23,"JCExtra",$D23,"JCCostCode",$E23,"WCCode",$B23,"WCState",$G23,"State",$H23,"PayID",$BD$12,"Units",AL23,"UnionID",$B$3,"UnionLocal",$F23,"UnionClass",$I23,"CertifiedClass",$J23)),0) -> 0 | CJ23: =IF(AND(NOT(ISBLANK($C23)),NOT(ISBLANK($E23)),$A23="x"),IF(AM23=0,0,[2]!TSImport("PRTime","","Time_NINE","","Date",$CG$11,"Employee",$B$2,"JCJob",$C23,"JCExtra",$D23,"JCCostCode",$E23,"WCCode",$B23,"WCState",$G23,"State",$H23,"PayID",$BE$12,"Units",AM23,"UnionID",$B$3,"UnionLocal",$F23,"UnionClass",$I23,"CertifiedClass",$J23)),0) -> 0 | CK23: =IF(AND(NOT(ISBLANK($C23)),NOT(ISBLANK($E23)),$A23="x"),IF(AN23=0,0,[2]!TSImport("PRTime","","Time_NINE","","Date",$CG$11,"Employee",$B$2,"JCJob",$C23,"JCExtra",$D23,"JCCostCode",$E23,"WCCode",$B23,"WCState",$G23,"State",$H23,"PayID",$BF$12,"Units",AN23,"UnionID",$B$3,"UnionLocal",$F23,"UnionClass",$I23,"CertifiedClass",$J23)),0) -> 0 | CL23: =IF(AND(NOT(ISBLANK($C23)),NOT(ISBLANK($E23)),$A23="x"),IF(AO23=0,0,[2]!TSImport("PRTime","","Time_NINE","","Date",$CG$11,"Employee",$B$2,"JCJob",$C23,"JCExtra",$D23,"JCCostCode",$E23,"WCCode",$B23,"WCState",$G23,"State",$H23,"PayID",$BG$12,"Units",AO23,"UnionID",$B$3,"UnionLocal",$F23,"UnionClass",$I23,"CertifiedClass",$J23)),0) -> 0 | CM23: =IF(AND(NOT(ISBLANK($C23)),NOT(ISBLANK($E23)),$A23="x"),IF(AP23=0,0,[2]!TSImport("PRTime","","Time_NINE","","Date",$CM$11,"Employee",$B$2,"JCJob",$C23,"JCExtra",$D23,"JCCostCode",$E23,"WCCode",$B23,"WCState",$G23,"State",$H23,"PayID",$BB$12,"Units",AP23,"UnionID",$B$3,"UnionLocal",$F23,"UnionClass",$I23,"CertifiedClass",$J23)),0) -> 0 | CN23: =IF(AND(NOT(ISBLANK($C23)),NOT(ISBLANK($E23)),$A23="x"),IF(AQ23=0,0,[2]!TSImport("PRTime","","Time_NINE","","Date",$CM$11,"Employee",$B$2,"JCJob",$C23,"JCExtra",$D23,"JCCostCode",$E23,"WCCode",$B23,"WCState",$G23,"State",$H23,"PayID",$BC$12,"Units",AQ23,"UnionID",$B$3,"UnionLocal",$F23,"UnionClass",$I23,"CertifiedClass",$J23)),0) -> 0 | CO23: =IF(AND(NOT(ISBLANK($C23)),NOT(ISBLANK($E23)),$A23="x"),IF(AR23=0,0,[2]!TSImport("PRTime","","Time_NINE","","Date",$CM$11,"Employee",$B$2,"JCJob",$C23,"JCExtra",$D23,"JCCostCode",$E23,"WCCode",$B23,"WCState",$G23,"State",$H23,"PayID",$BD$12,"Units",AR23,"UnionID",$B$3,"UnionLocal",$F23,"UnionClass",$I23,"CertifiedClass",$J23)),0) -> 0 | CP23: =IF(AND(NOT(ISBLANK($C23)),NOT(ISBLANK($E23)),$A23="x"),IF(AS23=0,0,[2]!TSImport("PRTime","","Time_NINE","","Date",$CM$11,"Employee",$B$2,"JCJob",$C23,"JCExtra",$D23,"JCCostCode",$E23,"WCCode",$B23,"WCState",$G23,"State",$H23,"PayID",$BE$12,"Units",AS23,"UnionID",$B$3,"UnionLocal",$F23,"UnionClass",$I23,"CertifiedClass",$J23)),0) -> 0 | CQ23: =IF(AND(NOT(ISBLANK($C23)),NOT(ISBLANK($E23)),$A23="x"),IF(AT23=0,0,[2]!TSImport("PRTime","","Time_NINE","","Date",$CM$11,"Employee",$B$2,"JCJob",$C23,"JCExtra",$D23,"JCCostCode",$E23,"WCCode",$B23,"WCState",$G23,"State",$H23,"PayID",$BF$12,"Units",AT23,"UnionID",$B$3,"UnionLocal",$F23,"UnionClass",$I23,"CertifiedClass",$J23)),0) -> 0 | CR23: =IF(AND(NOT(ISBLANK($C23)),NOT(ISBLANK($E23)),$A23="x"),IF(AU23=0,0,[2]!TSImport("PRTime","","Time_NINE","","Date",$CM$11,"Employee",$B$2,"JCJob",$C23,"JCExtra",$D23,"JCCostCode",$E23,"WCCode",$B23,"WCState",$G23,"State",$H23,"PayID",$BG$12,"Units",AU23,"UnionID",$B$3,"UnionLocal",$F23,"UnionClass",$I23,"CertifiedClass",$J23)),0) -> 0 | CS23: =IF(AND(NOT(ISBLANK($C23)),NOT(ISBLANK($E23)),$A23="x"),IF(AV23=0,0,[2]!TSImport("PRTime","","Time_NINE","","Date",$CS$11,"Employee",$B$2,"JCJob",$C23,"JCExtra",$D23,"JCCostCode",$E23,"WCCode",$B23,"WCState",$G23,"State",$H23,"PayID",$BB$12,"Units",AV23,"UnionID",$B$3,"UnionLocal",$F23,"UnionClass",$I23,"CertifiedClass",$J23)),0) -> 0 | CT23: =IF(AND(NOT(ISBLANK($C23)),NOT(ISBLANK($E23)),$A23="x"),IF(AW23=0,0,[2]!TSImport("PRTime","","Time_NINE","","Date",$CS$11,"Employee",$B$2,"JCJob",$C23,"JCExtra",$D23,"JCCostCode",$E23,"WCCode",$B23,"WCState",$G23,"State",$H23,"PayID",$BC$12,"Units",AW23,"UnionID",$B$3,"UnionLocal",$F23,"UnionClass",$I23,"CertifiedClass",$J23)),0) -> 0 | CU23: =IF(AND(NOT(ISBLANK($C23)),NOT(ISBLANK($E23)),$A23="x"),IF(AX23=0,0,[2]!TSImport("PRTime","","Time_NINE","","Date",$CS$11,"Employee",$B$2,"JCJob",$C23,"JCExtra",$D23,"JCCostCode",$E23,"WCCode",$B23,"WCState",$G23,"State",$H23,"PayID",$BD$12,"Units",AX23,"UnionID",$B$3,"UnionLocal",$F23,"UnionClass",$I23,"CertifiedClass",$J23)),0) -> 0 | CV23: =IF(AND(NOT(ISBLANK($C23)),NOT(ISBLANK($E23)),$A23="x"),IF(AY23=0,0,[2]!TSImport("PRTime","","Time_NINE","","Date",$CS$11,"Employee",$B$2,"JCJob",$C23,"JCExtra",$D23,"JCCostCode",$E23,"WCCode",$B23,"WCState",$G23,"State",$H23,"PayID",$BE$12,"Units",AY23,"UnionID",$B$3,"UnionLocal",$F23,"UnionClass",$I23,"CertifiedClass",$J23)),0) -> 0 | CW23: =IF(AND(NOT(ISBLANK($C23)),NOT(ISBLANK($E23)),$A23="x"),IF(AZ23=0,0,[2]!TSImport("PRTime","","Time_NINE","","Date",$CS$11,"Employee",$B$2,"JCJob",$C23,"JCExtra",$D23,"JCCostCode",$E23,"WCCode",$B23,"WCState",$G23,"State",$H23,"PayID",$BF$12,"Units",AZ23,"UnionID",$B$3,"UnionLocal",$F23,"UnionClass",$I23,"CertifiedClass",$J23)),0) -> 0 | CX23: =IF(AND(NOT(ISBLANK($C23)),NOT(ISBLANK($E23)),$A23="x"),IF(BA23=0,0,[2]!TSImport("PRTime","","Time_NINE","","Date",$CS$11,"Employee",$B$2,"JCJob",$C23,"JCExtra",$D23,"JCCostCode",$E23,"WCCode",$B23,"WCState",$G23,"State",$H23,"PayID",$BG$12,"Units",BA23,"UnionID",$B$3,"UnionLocal",$F23,"UnionClass",$I23,"CertifiedClass",$J23)),0) -> 0
L24: =SUBTOTAL(109,TimeSheet34[RT1]) -> 0 | M24: =SUBTOTAL(109,TimeSheet34[OT1]) -> 0 | N24: =SUBTOTAL(109,TimeSheet34[DT1]) -> 0 | O24: =SUBTOTAL(109,TimeSheet34[PD1]) -> 0 | P24: =SUBTOTAL(109,TimeSheet34[4D1]) -> 0 | Q24: =SUBTOTAL(109,TimeSheet34[4A1]) -> 0 | R24: =SUBTOTAL(109,TimeSheet34[RT2]) -> 0 | S24: =SUBTOTAL(109,TimeSheet34[OT2]) -> 0 | T24: =SUBTOTAL(109,TimeSheet34[DT2]) -> 0 | U24: =SUBTOTAL(109,TimeSheet34[PD2]) -> 0 | V24: =SUBTOTAL(109,TimeSheet34[4D2]) -> 0 | W24: =SUBTOTAL(109,TimeSheet34[4A2]) -> 0 | X24: =SUBTOTAL(109,TimeSheet34[RT3]) -> 0 | Y24: =SUBTOTAL(109,TimeSheet34[OT3]) -> 0 | Z24: =SUBTOTAL(109,TimeSheet34[DT3]) -> 0 | AA24: =SUBTOTAL(109,TimeSheet34[PD3]) -> 0 | AB24: =SUBTOTAL(109,TimeSheet34[4D3]) -> 0 | AC24: =SUBTOTAL(109,TimeSheet34[4A3]) -> 0 | AD24: =SUBTOTAL(109,TimeSheet34[RT4]) -> 0 | AE24: =SUBTOTAL(109,TimeSheet34[OT4]) -> 0 | AF24: =SUBTOTAL(109,TimeSheet34[DT4]) -> 0 | AG24: =SUBTOTAL(109,TimeSheet34[PD4]) -> 0 | AH24: =SUBTOTAL(109,TimeSheet34[4D4]) -> 0 | AI24: =SUBTOTAL(109,TimeSheet34[4A4]) -> 0 | AJ24: =SUBTOTAL(109,TimeSheet34[RT5]) -> 0 | AK24: =SUBTOTAL(109,TimeSheet34[OT5]) -> 0 | AL24: =SUBTOTAL(109,TimeSheet34[DT5]) -> 0 | AM24: =SUBTOTAL(109,TimeSheet34[PD5]) -> 0 | AN24: =SUBTOTAL(109,TimeSheet34[4D5]) -> 0 | AO24: =SUBTOTAL(109,TimeSheet34[4A5]) -> 0 | AP24: =SUBTOTAL(109,TimeSheet34[RT6]) -> 0 | AQ24: =SUBTOTAL(109,TimeSheet34[OT6]) -> 0 | AR24: =SUBTOTAL(109,TimeSheet34[DT6]) -> 0 | AS24: =SUBTOTAL(109,TimeSheet34[PD6]) -> 0 | AT24: =SUBTOTAL(109,TimeSheet34[4D6]) -> 0 | AU24: =SUBTOTAL(109,TimeSheet34[4A6]) -> 0 | AV24: =SUBTOTAL(109,TimeSheet34[RT7]) -> 0 | AW24: =SUBTOTAL(109,TimeSheet34[OT7]) -> 0 | AX24: =SUBTOTAL(109,TimeSheet34[DT7]) -> 0 | AY24: =SUBTOTAL(109,TimeSheet34[PD7]) -> 0 | AZ24: =SUBTOTAL(109,TimeSheet34[4D7]) -> 0 | BA24: =SUBTOTAL(109,TimeSheet34[4A7]) -> 0 | BB24: =SUBTOTAL(109,TimeSheet34[1]) -> 0 | BC24: =SUBTOTAL(109,TimeSheet34[3]) -> 0 | BD24: =SUBTOTAL(109,TimeSheet34[2]) -> 0 | BE24: =SUBTOTAL(109,TimeSheet34[4]) -> 0 | BF24: =SUBTOTAL(109,TimeSheet34[4D]) -> 0 | BG24: =SUBTOTAL(109,TimeSheet34[4A]) -> 0 | BH24: =SUBTOTAL(109,TimeSheet34[Total])-SUM(TimeSheet34[[#Totals],[RT1]:[4A7]]) -> 0
B25: Update the Box below on the Job Details Worksheet
A26: =IF(ISBLANK('Job Details'!A5),"",'Job Details'!A5) -> Hours | C26: =IF(ISBLANK('Job Details'!B5),"",'Job Details'!B5) -> 8ST, then everything else DT | D26: =IF(ISBLANK('Job Details'!C5),"",'Job Details'!C5) | E26: =IF(ISBLANK('Job Details'!D5),"",'Job Details'!D5) | F26: =IF(ISBLANK('Job Details'!E5),"",'Job Details'!E5)
A27: =IF(ISBLANK('Job Details'!A6),"",'Job Details'!A6) -> PD | C27: =IF(ISBLANK('Job Details'!B6),"",'Job Details'!B6) -> $50/day (must work 4 hours or until noon, whichever is later) | D27: =IF(ISBLANK('Job Details'!C6),"",'Job Details'!C6) | E27: =IF(ISBLANK('Job Details'!D6),"",'Job Details'!D6) | F27: =IF(ISBLANK('Job Details'!E6),"",'Job Details'!E6)
A28: =IF(ISBLANK('Job Details'!A7),"",'Job Details'!A7) -> Meal | C28: =IF(ISBLANK('Job Details'!B7),"",'Job Details'!B7) -> $15 after 10.5 hours (then after every 4.5 hours) | D28: =IF(ISBLANK('Job Details'!C7),"",'Job Details'!C7) | E28: =IF(ISBLANK('Job Details'!D7),"",'Job Details'!D7) | F28: =IF(ISBLANK('Job Details'!E7),"",'Job Details'!E7)
A29: =IF(ISBLANK('Job Details'!A8),"",'Job Details'!A8) -> In Lieu | C29: =IF(ISBLANK('Job Details'!B8),"",'Job Details'!B8) -> 0.5DT after 10.5 hours (then after every 4.5 hours) | D29: =IF(ISBLANK('Job Details'!C8),"",'Job Details'!C8) | E29: =IF(ISBLANK('Job Details'!D8),"",'Job Details'!D8) | F29: =IF(ISBLANK('Job Details'!E8),"",'Job Details'!E8)
A30: =IF(ISBLANK('Job Details'!A9),"",'Job Details'!A9) -> Job Details | C30: =IF(ISBLANK('Job Details'!B9),"",'Job Details'!B9) | D30: =IF(ISBLANK('Job Details'!C9),"",'Job Details'!C9) | E30: =IF(ISBLANK('Job Details'!D9),"",'Job Details'!D9) | F30: =IF(ISBLANK('Job Details'!E9),"",'Job Details'!E9)
A31: =IF(ISBLANK('Job Details'!A10),"",'Job Details'!A10) -> Extra | C31: =IF(ISBLANK('Job Details'!B10),"",'Job Details'!B10) -> Phase | D31: =IF(ISBLANK('Job Details'!C10),"",'Job Details'!C10) -> Phase Description | E31: =IF(ISBLANK('Job Details'!D10),"",'Job Details'!D10) -> Category | F31: =IF(ISBLANK('Job Details'!E10),"",'Job Details'!E10) -> Description
A32: =IF(ISBLANK('Job Details'!A11),"",'Job Details'!A11) | C32: =IF(ISBLANK('Job Details'!B11),"",'Job Details'!B11) -> 1-001 | D32: =IF(ISBLANK('Job Details'!C11),"",'Job Details'!C11) -> Project Superintendent (Hrs) | E32: =IF(ISBLANK('Job Details'!D11),"",'Job Details'!D11) -> DT | F32: =IF(ISBLANK('Job Details'!E11),"",'Job Details'!E11) -> Double Time - Jobs

Sheet Certified Codes
A1: Certified Codes and Description
A2: Certified class | B2: Description | C2: Operator Stamp | D2: Date Stamp
A3: 4 | B3: Technician | C3: MICHELLE | D3: 40805
A4: 5 | B4: Lineman Welder | C4: DEBBIE | D4: 37167
A5: 01 | B5: General Foreman | C5: THERESE | D5: 40786
A6: 04 | B6: Cable Splicer | C6: MICHELLE | D6: 40805
A7: 05 | B7: General Foreman | C7: MICHELLE | D7: 38874
A8: 06 | B8: Cable Splicer Foreman | C8: DEBBIE | D8: 35607
A9: 07 | B9: Foreman Lineman | C9: DEBBIE | D9: 35607
A10: 08 | B10: Journeyman Lineman | C10: DEBBIE | D10: 35607
A11: 09 | B11: 7th Period Appn Lineman | C11: DEBBIE | D11: 35607
A12: 10 | B12: 6th Period Appn Lineman | C12: DEBBIE | D12: 35607
A13: 11 | B13: 5th Period Appn Lineman | C13: DEBBIE | D13: 35607
A14: 12 | B14: 4th Period Appn Lineman | C14: DEBBIE | D14: 35607
... A36: 35 | B36: Line Truck Driver | C36: ireyes | D36: 41506
A37: 40 | B37: General Foreman-Wireman | D37: 35709
A38: 41 | B38: Foreman Electrician | C38: DEBBIE | D38: 36038
A39: 42 | B39: Journeyman Electrician | C39: DEBBIE | D39: 36038
A40: 43 | B40: Journeyman Tech Wireman | C40: kcam | D40: 42055
A41: 44 | B41: Jourmenyam Wireman Weld | D41: 35709
A42: 45 | B42: Journeyman Wireman Cable | D42: 35709
A43: 46 | B43: 1st Period Electrician | C43: DEBBIE | D43: 36038
A44: 47 | B44: 2nd Period Electrician | C44: DEBBIE | D44: 36038
A45: 48 | B45: 3rd Period Electrician | C45: DEBBIE | D45: 36038
A46: 49 | B46: 4th Period Electrician | C46: DEBBIE | D46: 36038
A47: 50 | B47: 5th Period Electrician | C47: DEBBIE | D47: 36038
A48: 51 | B48: 6th Period Electrician | C48: DEBBIE | D48: 36038
A49: 52 | B49: 7th Period Appn Wireman | C49: DEBBIE | D49: 38231
A50: 53 | B50: 8th Per Appn Wireman | C50: DEBBIE | D50: 38261
A51: 54 | B51: Tele Heavy Equip Operator | C51: DEBBIE | D51: 36000
A52: 55 | B52: 10th Period Appn Wireman | C52: DEBBIE | D52: 38446
A53: 59 | B53: Substation Foreman | C53: THERESE | D53: 41306
A54: 60 | B54: Substation Technician | C54: tlang | D54: 43201
... A83: BHOE | B83: Backhoe Operator Group 5 | C83: tlang | D83: 43384

Sheet Employees
B1: Employees
A2: Employee | B2: EE ID | C2: Employee Name | D2: Pay Group | E2: Union ID | F2: Union Local | G2: Union Class | H2: Exclude From Cert. Report | I2: Title
A3: 1025 | B3: =_xlfn.NUMBERVALUE(A3,"#####") -> 1025 | C3: Abella; Christian Marcelo | D3: 1 | E3: IBEWOUT | F3: 1245 | G3: 1 | H3: 0 | I3: Foreman General
A4: 1027 | B4: =_xlfn.NUMBERVALUE(A4,"#####") -> 1027 | C4: Acosta; Christopher M | D4: 1 | H4: 0 | I4: Project Manager
A5: 1038 | B5: =_xlfn.NUMBERVALUE(A5,"#####") -> 1038 | C5: Aguilar; Juan A. | D5: 1 | H5: 0 | I5: Hangar Manager
A6: 1043 | B6: =_xlfn.NUMBERVALUE(A6,"#####") -> 1043 | C6: Adema; Matthew | D6: 1C | E6: IBEWOUT | F6: 1245 | G6: 8 | H6: 0 | I6: Lineman Journeyman
A7: 1046 | B7: =_xlfn.NUMBERVALUE(A7,"#####") -> 1046 | C7: Alcala Jr.; Juan Antonio | D7: 1C | E7: IBEWOUT | F7: 47 | G7: 7 | H7: 0 | I7: Foreman Journeyman
A8: 1055 | B8: =_xlfn.NUMBERVALUE(A8,"#####") -> 1055 | C8: Adams; Timothy J | D8: 1 | E8: IBEWOUT | F8: 125 | G8: 33 | H8: 0 | I8: Operator Heavy
A9: 1056 | B9: =_xlfn.NUMBERVALUE(A9,"#####") -> 1056 | C9: Ewanchew; John F. | D9: 1C | E9: IBEWOUT | F9: 396 | G9: 8 | H9: 0 | I9: Lineman Journeyman
A10: 1059 | B10: =_xlfn.NUMBERVALUE(A10,"#####") -> 1059 | C10: Aleman; Carlos A | D10: 1C | E10: IBEWOUT | F10: 1245 | G10: 11 | H10: 0 | I10: Apprentice Lineman 5th Step
A11: 1061 | B11: =_xlfn.NUMBERVALUE(A11,"#####") -> 1061 | C11: Alday; Caleb T. | D11: 1C | E11: IBEWOUT | F11: 1245 | G11: 8 | H11: 0 | I11: Lineman Journeyman
A12: 1064 | B12: =_xlfn.NUMBERVALUE(A12,"#####") -> 1064 | C12: Aguilar; Matthias J | D12: 1C | E12: IBEWOUT | F12: 1245 | G12: 17 | H12: 0 | I12: Groundman
A13: 1085 | B13: =_xlfn.NUMBERVALUE(A13,"#####") -> 1085 | C13: Almendarez; Raymond K | D13: 1C | E13: IBEWOUT | F13: 1245 | G13: 8 | H13: 0 | I13: Lineman Journeyman
A14: 1091 | B14: =_xlfn.NUMBERVALUE(A14,"#####") -> 1091 | C14: Alvarez; Jesus M | D14: 1C | E14: IBEWOUT | F14: 125 | G14: 8 | H14: 0 | I14: Lineman Journeyman
A15: 1095 | B15: =_xlfn.NUMBERVALUE(A15,"#####") -> 1095 | C15: Alexander; James C | D15: 1C | E15: IBEWOUT | F15: 47 | G15: 8 | H15: 0 | I15: Lineman Journeyman Tech
A16: 1103 | B16: =_xlfn.NUMBERVALUE(A16,"#####") -> 1103 | C16: Allen; Corey L. | D16: 1C | E16: IBEWOUT | F16: 1245 | G16: 7 | H16: 0 | I16: Foreman Journeyman
A17: 1104 | B17: =_xlfn.NUMBERVALUE(A17,"#####") -> 1104 | C17: Amburgey; James R | D17: 1C | E17: IBEWOUT | F17: 769 | G17: 8 | H17: 0 | I17: Lineman Journeyman
A18: 1105 | B18: =_xlfn.NUMBERVALUE(A18,"#####") -> 1105 | C18: Amador; Luis D | D18: 1 | H18: 0 | I18: Mobile Lube Tech
A19: 1106 | B19: =_xlfn.NUMBERVALUE(A19,"#####") -> 1106 | C19: Archibeque; Larry Michael | D19: 1C | E19: IBEWOUT | F19: 611 | G19: 16 | H19: 0 | I19: Operator
A20: 1108 | B20: =_xlfn.NUMBERVALUE(A20,"#####") -> 1108 | C20: Arehart; Joshua D. | D20: 1C | E20: IBEWOUT | F20: 125 | G20: 7 | H20: 0 | I20: Foreman Journeyman
A21: 1109 | B21: =_xlfn.NUMBERVALUE(A21,"#####") -> 1109 | C21: Atayde; Manuel | D21: 1C | E21: IBEWOUT | F21: 769 | G21: 22 | H21: 0 | I21: Groundman 4000 + Hours
A22: 1110 | B22: =_xlfn.NUMBERVALUE(A22,"#####") -> 1110 | C22: Al-Raies; Sam | D22: 1C | E22: IBEWOUT | F22: 47 | G22: 60 | H22: 0 | I22: Substation Technician
A23: 1111 | B23: =_xlfn.NUMBERVALUE(A23,"#####") -> 1111 | C23: Atchison; Jason E. | D23: 1C | E23: IBEWOUT | F23: 769 | G23: 8 | H23: 0 | I23: Lineman Journeyman
A24: 1112 | B24: =_xlfn.NUMBERVALUE(A24,"#####") -> 1112 | C24: Amato; Pietro | D24: 1C | E24: IBEWOUT | F24: 1049 | G24: 15 | H24: 0 | I24: Apprentice Lineman 1st Step
A25: 1114 | B25: =_xlfn.NUMBERVALUE(A25,"#####") -> 1114 | C25: Archuleta Jr.; Felix | D25: 1C | E25: IBEWOUT | F25: 611 | G25: 10 | H25: 0 | I25: Apprentice Lineman 6th Step
A26: 1115 | B26: =_xlfn.NUMBERVALUE(A26,"#####") -> 1115 | C26: Archuleta; Louis A. | D26: 1C | E26: IBEWOUT | F26: 1245 | G26: 17 | H26: 0 | I26: Groundman
A27: 1119 | B27: =_xlfn.NUMBERVALUE(A27,"#####") -> 1119 | C27: Amato; Joshua D | D27: 1C | E27: IBEWOUT | F27: 611 | G27: 14 | H27: 0 | I27: Apprentice Lineman 2nd Step
A28: 1130 | B28: =_xlfn.NUMBERVALUE(A28,"#####") -> 1130 | C28: Allred; Shane M. | D28: 1C | E28: IBEWOUT | F28: 1245 | G28: 8 | H28: 0 | I28: Lineman Journeyman
A29: 1180 | B29: =_xlfn.NUMBERVALUE(A29,"#####") -> 1180 | C29: Atayde; Dimas | D29: 1C | E29: IBEWOUT | F29: 769 | G29: 22 | H29: 0 | I29: Groundman 4000 + Hours
A30: 1192 | B30: =_xlfn.NUMBERVALUE(A30,"#####") -> 1192 | C30: Andersen; David Mitch | D30: 1C | H30: 0 | I30: Assistant Project Manager
A31: 1193 | B31: =_xlfn.NUMBERVALUE(A31,"#####") -> 1193 | C31: Arredondo; Juan V | D31: 1C | E31: IBEWOUT | F31: 769 | G31: 8 | H31: 0 | I31: Lineman Journeyman
A32: 1194 | B32: =_xlfn.NUMBERVALUE(A32,"#####") -> 1194 | C32: Arreola; George | D32: 1C | E32: IBEWOUT | F32: 47 | G32: 17 | H32: 0 | I32: Groundman
A33: 1197 | B33: =_xlfn.NUMBERVALUE(A33,"#####") -> 1197 | C33: Andrea; Josh M | D33: 1C | E33: IBEWOUT | F33: 77 | G33: 15 | H33: 0 | I33: Apprentice Lineman 1st Step
A34: 1199 | B34: =_xlfn.NUMBERVALUE(A34,"#####") -> 1199 | C34: Andress; Jesse B | D34: 1C | E34: IBEWOUT | F34: 77 | G34: 8 | H34: 0 | I34: Lineman Journeyman
A35: 1202 | B35: =_xlfn.NUMBERVALUE(A35,"#####") -> 1202 | C35: Anderson; Chad M. | D35: 1C | H35: 1 | I35: Mechanic - Canby
A36: 1203 | B36: =_xlfn.NUMBERVALUE(A36,"#####") -> 1203 | C36: Anderson; Clyde M. | D36: 1C | H36: 1 | I36: Mechanic - Canby
A37: 1206 | B37: =_xlfn.NUMBERVALUE(A37,"#####") -> 1206 | C37: Arroyo; Jose M | D37: 1 | E37: IBEWOUT | F37: 1245 | G37: 9 | H37: 0 | I37: Apprentice Lineman 7th Step
A38: 1207 | B38: =_xlfn.NUMBERVALUE(A38,"#####") -> 1207 | C38: Arrington; Austin M | D38: 1 | E38: IBEWOUT | F38: 77 | G38: 13 | H38: 0 | I38: Apprentice Lineman 3rd Step
A39: 1209 | B39: =_xlfn.NUMBERVALUE(A39,"#####") -> 1209 | C39: Andrade; Carlos | D39: 1 | E39: IBEWOUT | F39: 47 | G39: 9 | H39: 0 | I39: Apprentice Lineman 7th Step
A40: 1210 | B40: =_xlfn.NUMBERVALUE(A40,"#####") -> 1210 | C40: Anderson; Calvin J | D40: 1 | E40: IBEWOUT | F40: 1245 | G40: 8 | H40: 0 | I40: Lineman Journeyman
A41: 1217 | B41: =_xlfn.NUMBERVALUE(A41,"#####") -> 1217 | C41: Andrews; Cory R | D41: 1C | E41: IBEWOUT | F41: 125 | G41: 8 | H41: 0 | I41: Lineman Journeyman
A42: 1219 | B42: =_xlfn.NUMBERVALUE(A42,"#####") -> 1219 | C42: Andrews; James H | D42: 1C | E42: IBEWOUT | F42: 1245 | G42: 8 | H42: 0 | I42: Lineman Journeyman
A43: 1221 | B43: =_xlfn.NUMBERVALUE(A43,"#####") -> 1221 | C43: Arlt; Dalton M | D43: 1C | E43: IBEWOUT | F43: 769 | G43: 9 | H43: 0 | I43: Apprentice Lineman 7th Step
A44: 1223 | B44: =_xlfn.NUMBERVALUE(A44,"#####") -> 1223 | C44: Angulo; Jose L | D44: 1C | E44: IBEWOUT | F44: 47 | G44: 17 | H44: 0 | I44: Groundman
A45: 1224 | B45: =_xlfn.NUMBERVALUE(A45,"#####") -> 1224 | C45: Anonuevo; Jomar N | D45: 1 | E45: IBEWOUT | F45: 125 | G45: 14 | H45: 0 | I45: Apprentice Lineman 2nd Step
A46: 1225 | B46: =_xlfn.NUMBERVALUE(A46,"#####") -> 1225 | C46: Angelucci; Dylan R | D46: 1 | E46: IBEWOUT | F46: 611 | G46: 17 | H46: 0 | I46: Groundman
A47: 1228 | B47: =_xlfn.NUMBERVALUE(A47,"#####") -> 1228 | C47: Apalategui; Randall | D47: 1 | E47: IBEWOUT | F47: 1245 | G47: 11 | H47: 0 | I47: Apprentice Lineman 5th Step
A48: 1229 | B48: =_xlfn.NUMBERVALUE(A48,"#####") -> 1229 | C48: Apana; Walter K | D48: 1C | E48: IBEWOUT | F48: 1186 | G48: 16 | H48: 0 | I48: Operator
... A59: 1255 | B59: =_xlfn.NUMBERVALUE(A59,"#####") -> 1255 | C59: Ash IV; Leonard C | D59: 1C | E59: IBEWOUT | F59: 611 | G59: 8 | H59: 0 | I59: Lineman Journeyman
A60: 1260 | B60: =_xlfn.NUMBERVALUE(A60,"#####") -> 1260 | C60: Austin; Berton R. | D60: 1C | H60: 1 | I60: Superintendent
A61: 1261 | B61: =_xlfn.NUMBERVALUE(A61,"#####") -> 1261 | C61: Auzston; Russell E | D61: 1C | E61: IBEWOUT | F61: 47 | G61: 8 | H61: 0 | I61: Lineman Journeyman
A62: 1264 | B62: =_xlfn.NUMBERVALUE(A62,"#####") -> 1264 | C62: Aumann III; Walter R | D62: 1 | E62: IBEWOUT | F62: 47 | G62: 8 | H62: 0 | I62: Lineman Journeyman
A63: 1270 | B63: =_xlfn.NUMBERVALUE(A63,"#####") -> 1270 | C63: Ayers; Christopher S | D63: 1C | E63: IBEWOUT | F63: 769 | G63: 15 | H63: 0 | I63: Apprentice Lineman 1st Step
A64: 1274 | B64: =_xlfn.NUMBERVALUE(A64,"#####") -> 1274 | C64: Averhart; Alexander M | D64: 1 | E64: IBEWOUT | F64: 769 | G64: 15 | H64: 0 | I64: Apprentice Lineman 1st Step
A65: 1275 | B65: =_xlfn.NUMBERVALUE(A65,"#####") -> 1275 | C65: Avery; Bella | D65: 1C | H65: 0 | I65: Project Coordinator
A66: 1276 | B66: =_xlfn.NUMBERVALUE(A66,"#####") -> 1276 | C66: Avila; David J | D66: 1C | E66: IBEWOUT | F66: 1245 | G66: 17 | H66: 0 | I66: Groundman
A67: 1283 | B67: =_xlfn.NUMBERVALUE(A67,"#####") -> 1283 | C67: Avelar Palacios; Moises | D67: 1C | E67: IBEWOUT | F67: 1245 | G67: 11 | H67: 0 | I67: Apprentice Lineman 5th Step
A68: 1331 | B68: =_xlfn.NUMBERVALUE(A68,"#####") -> 1331 | C68: Babb; Mitchell R. | D68: 1C | E68: IBEWOUT | F68: 1245 | G68: 8 | H68: 0 | I68: Lineman Journeyman
A69: 1332 | B69: =_xlfn.NUMBERVALUE(A69,"#####") -> 1332 | C69: Babbitt; Brian S | D69: 1 | E69: IBEWOUT | F69: 77 | G69: 7 | H69: 0 | I69: Foreman Journeyman
A70: 1335 | B70: =_xlfn.NUMBERVALUE(A70,"#####") -> 1335 | C70: Badalamente; Joseph A | D70: 1C | E70: IBEWOUT | F70: 1049 | G70: 15 | H70: 0 | I70: Apprentice Lineman 1st Step
A71: 1353 | B71: =_xlfn.NUMBERVALUE(A71,"#####") -> 1353 | C71: Bannister Jr; Kenneth W | D71: 1 | E71: IBEWOUT | F71: 1245 | G71: 7 | H71: 0 | I71: Foreman Journeyman
A72: 1358 | B72: =_xlfn.NUMBERVALUE(A72,"#####") -> 1358 | C72: Baldovino; Ernest Dion | D72: 1C | E72: IBEWOUT | F72: 1049 | G72: 8 | H72: 0 | I72: Lineman Journeyman
A73: 1359 | B73: =_xlfn.NUMBERVALUE(A73,"#####") -> 1359 | C73: Bailey; Gary D | D73: 1C | E73: IBEWOUT | F73: 602R | G73: 15T | H73: 0 | I73: Transmission Tech 1
A74: 1361 | B74: =_xlfn.NUMBERVALUE(A74,"#####") -> 1361 | C74: Bailey; Michael J | D74: 1C | E74: IBEWOUT | F74: 483 | G74: 8 | H74: 0 | I74: Lineman Journeyman
A75: 1365 | B75: =_xlfn.NUMBERVALUE(A75,"#####") -> 1365 | C75: Bagwell; Douglas W. | D75: 1 | E75: IBEWOUT | F75: 611 | G75: 16 | H75: 0 | I75: Operator
A76: 1371 | B76: =_xlfn.NUMBERVALUE(A76,"#####") -> 1371 | C76: Baggerly; Richard A | D76: 1C | E76: IBEWOUT | F76: 77 | G76: 17 | H76: 0 | I76: Groundman
A77: 1372 | B77: =_xlfn.NUMBERVALUE(A77,"#####") -> 1372 | C77: Bamer; Gregory F | D77: 1C | E77: IBEWOUT | F77: 77 | G77: 7 | H77: 0 | I77: Foreman Journeyman
... A98: 1565 | B98: =_xlfn.NUMBERVALUE(A98,"#####") -> 1565 | C98: Begaye; Donald | D98: 1C | E98: IBEWOUT | F98: 769 | G98: 8 | H98: 0 | I98: Lineman Journeyman
A99: 1568 | B99: =_xlfn.NUMBERVALUE(A99,"#####") -> 1568 | C99: Beissel; Lee C | D99: 1C | H99: 1 | I99: Helicopter Pilot
A100: 1572 | B100: =_xlfn.NUMBERVALUE(A100,"#####") -> 1572 | C100: Belcher; Jeffrey James | D100: 1C | E100: IBEWOUT | F100: 47 | G100: 8 | H100: 0 | I100: Lineman Journeyman
A101: 1574 | B101: =_xlfn.NUMBERVALUE(A101,"#####") -> 1574 | C101: Beach; Dale D. | D101: 1 | E101: IBEWOUT | F101: 77 | G101: 1 | H101: 0 | I101: Foreman General
A102: 1579 | B102: =_xlfn.NUMBERVALUE(A102,"#####") -> 1579 | C102: Bauer; Bradley L | D102: 1C | E102: IBEWOUT | F102: 160 | G102: 8 | H102: 0 | I102: Foreman Journeyman
A103: 1580 | B103: =_xlfn.NUMBERVALUE(A103,"#####") -> 1580 | C103: Bell; Edward Douglas | D103: 1C | E103: IBEWOUT | F103: 1245 | G103: 8 | H103: 0 | I103: Lineman Journeyman
A104: 1581 | B104: =_xlfn.NUMBERVALUE(A104,"#####") -> 1581 | C104: Bedoy; Cody J | D104: 1C | E104: IBEWOUT | F104: 1245 | G104: 8 | H104: 0 | I104: Lineman Journeyman
A105: 1585 | B105: =_xlfn.NUMBERVALUE(A105,"#####") -> 1585 | C105: Bellos; Jacob G. | D105: 1C | E105: IBEWOUT | F105: 77 | G105: 12 | H105: 0 | I105: Apprentice Lineman 4th Step
A106: 1586 | B106: =_xlfn.NUMBERVALUE(A106,"#####") -> 1586 | C106: Beeler; Michael A | D106: 1 | H106: 0 | I106: Mechanic - Field
A107: 1595 | B107: =_xlfn.NUMBERVALUE(A107,"#####") -> 1595 | C107: Beltran; Juan F | D107: 1C | E107: IBEWOUT | F107: 47 | G107: 8 | H107: 0 | I107: Lineman Journeyman
A108: 1598 | B108: =_xlfn.NUMBERVALUE(A108,"#####") -> 1598 | C108: Becker; Bryan | D108: 1C | H108: 0 | I108: Runner
A109: 1599 | B109: =_xlfn.NUMBERVALUE(A109,"#####") -> 1599 | C109: Luna Beltran; Ramon | D109: 1C | E109: IBEWOUT | F109: 1245 | G109: 17 | H109: 0 | I109: Groundman
A110: 1604 | B110: =_xlfn.NUMBERVALUE(A110,"#####") -> 1604 | C110: Bojt; James E | D110: 1C | E110: IBEWOUT | F110: 126 | G110: 7S | H110: 0 | I110: Foreman Small Job
A111: 1606 | B111: =_xlfn.NUMBERVALUE(A111,"#####") -> 1606 | C111: Bock; Nathan Philip | D111: 1C | E111: IBEWOUT | F111: 77 | G111: 8 | H111: 0 | I111: Lineman Journeyman
A112: 1608 | B112: =_xlfn.NUMBERVALUE(A112,"#####") -> 1608 | C112: Boisvert; Harry A | D112: 1 | E112: IBEWOUT | F112: 1245 | G112: 8 | H112: 0 | I112: Lineman Journeyman
A113: 1610 | B113: =_xlfn.NUMBERVALUE(A113,"#####") -> 1610 | C113: Belsterling; David J | D113: 1C | E113: IBEWOUT | F113: 126 | G113: 13 | H113: 0 | I113: Apprentice Lineman 3rd Step
A114: 1614 | B114: =_xlfn.NUMBERVALUE(A114,"#####") -> 1614 | C114: Bentley; Lonne | D114: 1C | E114: IBEWOUT | F114: 77 | G114: 8 | H114: 0 | I114: Lineman Journeyman
A115: 1619 | B115: =_xlfn.NUMBERVALUE(A115,"#####") -> 1619 | C115: Berg; Dane M | D115: 1 | E115: IBEWOUT | F115: 77 | G115: 7 | H115: 0 | I115: Foreman Journeyman
A116: 1623 | B116: =_xlfn.NUMBERVALUE(A116,"#####") -> 1623 | C116: Benedict; Vincent A | D116: 1 | E116: IBEWOUT | F116: 47 | G116: 17 | H116: 0 | I116: Groundman
A117: 1625 | B117: =_xlfn.NUMBERVALUE(A117,"#####") -> 1625 | C117: Bentley; Michael J | D117: 1C | E117: IBEWOUT | F117: 1245 | G117: 8 | H117: 0 | I117: Lineman Journeyman
A118: 1647 | B118: =_xlfn.NUMBERVALUE(A118,"#####") -> 1647 | C118: Baxter; Olliver | D118: 1 | H118: 0 | I118: Mechanic
A119: 1720 | B119: =_xlfn.NUMBERVALUE(A119,"#####") -> 1720 | C119: Berry; Andrew C. | D119: 1 | E119: IBEWOUT | F119: 47 | G119: 7 | H119: 0 | I119: Foreman Journeyman
A120: 1738 | B120: =_xlfn.NUMBERVALUE(A120,"#####") -> 1738 | C120: Bereta Jr; Larry L | D120: 1C | E120: IBEWOUT | F120: 47 | G120: 8 | H120: 0 | I120: Lineman Journeyman
A121: 1755 | B121: =_xlfn.NUMBERVALUE(A121,"#####") -> 1755 | C121: Bibiano; Brandon Lee | D121: 1C | E121: IBEWOUT | F121: 611 | G121: 8 | H121: 0 | I121: Lineman Journeyman
A122: 1763 | B122: =_xlfn.NUMBERVALUE(A122,"#####") -> 1763 | C122: Biggs; Bret S | D122: 1C | E122: IBEWOUT | F122: 1245 | G122: 8 | H122: 0 | I122: Lineman Journeyman
A123: 1769 | B123: =_xlfn.NUMBERVALUE(A123,"#####") -> 1769 | C123: Bindel; Bruce A. | D123: 1C | E123: IBEWOUT | F123: 1245 | G123: 17 | H123: 0 | I123: Groundman
A124: 1770 | B124: =_xlfn.NUMBERVALUE(A124,"#####") -> 1770 | C124: Biro; Brandon J | D124: 1C | E124: IBEWOUT | F124: 769 | G124: 17 | H124: 0 | I124: Groundman 0-2000 Hours
A125: 1773 | B125: =_xlfn.NUMBERVALUE(A125,"#####") -> 1773 | C125: Bills; Connor L | D125: 1 | E125: IBEWOUT | F125: 1245 | G125: 13 | H125: 0 | I125: Apprentice Lineman 3rd Step
A126: 1774 | B126: =_xlfn.NUMBERVALUE(A126,"#####") -> 1774 | C126: Bishop; Clark Bryant | D126: 1C | E126: IBEWOUT | F126: 1245 | G126: 8 | H126: 0 | I126: Lineman Journeyman
A127: 1775 | B127: =_xlfn.NUMBERVALUE(A127,"#####") -> 1775 | C127: Bishop; Andrew M | D127: 1C | E127: IBEWOUT | F127: 77 | G127: 23 | H127: 0 | I127: Groundman 2081+ Hours
A128: 1778 | B128: =_xlfn.NUMBERVALUE(A128,"#####") -> 1778 | C128: Bishop; Toby J. | D128: 1C | E128: IBEWOUT | F128: 396 | G128: 8 | H128: 0 | I128: Lineman Journeyman
A129: 1780 | B129: =_xlfn.NUMBERVALUE(A129,"#####") -> 1780 | C129: Bischoff; Robert S | D129: 1C | E129: IBEWOUT | F129: 1319 | G129: 8 | H129: 0 | I129: Lineman Journeyman
A130: 1829 | B130: =_xlfn.NUMBERVALUE(A130,"#####") -> 1829 | C130: Black; Cody S | D130: 1 | E130: IBEWOUT | F130: 1245 | G130: 15 | H130: 0 | I130: Apprentice Linemam 1st Step
...

Sheet Job Details
A1: Job Details
A2: 664920-70-0 | B2: Must Enter Job Number with Dashes and Refresh Office Connector
A3: IBEWOUT | B3: Enter Union ID
A4: Local 1245/47 | B4: Update the Box below on the Job Details Worksheet
A5: Hours | B5: 8ST, then everything else DT
A6: PD | B6: $50/day (must work 4 hours or until noon, whichever is later)
A7: Meal | B7: $15 after 10.5 hours (then after every 4.5 hours)
A8: In Lieu | B8: 0.5DT after 10.5 hours (then after every 4.5 hours)
A9: Job Details | G9: Extra Information | K9: Do Not Delete
A10: Extra | B10: Phase | C10: Phase Description | D10: Category | E10: Description | G10: Extra | H10: Description | I10: Address 2 | K10: Phase | L10: Description
B11: 1-001 | C11: =VLOOKUP(B11,'Job Details'!$K:$L,2,FALSE) -> Project Superintendent (Hrs) | D11: DT | E11: Double Time - Jobs | K11: 1-000 | L11: SUPERVISION & ADMINISTRATION
B12: 1-001 | C12: =VLOOKUP(B12,'Job Details'!$K:$L,2,FALSE) -> Project Superintendent (Hrs) | D12: HP | E12: HOLIDAY PAY | K12: 1-001 | L12: Project Superintendent (Hrs)
B13: 1-001 | C13: =VLOOKUP(B13,'Job Details'!$K:$L,2,FALSE) -> Project Superintendent (Hrs) | D13: OT | E13: Over Time - Jobs | K13: 1-002 | L13: General Foreman (Hrs)
B14: 1-001 | C14: =VLOOKUP(B14,'Job Details'!$K:$L,2,FALSE) -> Project Superintendent (Hrs) | D14: PD | E14: Per Diem - Jobs | K14: 1-005 | L14: Office (Hrs)
B15: 1-001 | C15: =VLOOKUP(B15,'Job Details'!$K:$L,2,FALSE) -> Project Superintendent (Hrs) | D15: PDS | E15: Per Diem - Supervisors | K15: 1-007 | L15: Environmental Costs (Hrs)
B16: 1-001 | C16: =VLOOKUP(B16,'Job Details'!$K:$L,2,FALSE) -> Project Superintendent (Hrs) | D16: PP | E16: Premium Pay | K16: 1-008 | L16: Safety Manager (Hrs)
B17: 1-001 | C17: =VLOOKUP(B17,'Job Details'!$K:$L,2,FALSE) -> Project Superintendent (Hrs) | D17: PRT | E17: Payroll Taxes-Jobs | K17: 1-009 | L17: Helicopter Costs
B18: 1-001 | C18: =VLOOKUP(B18,'Job Details'!$K:$L,2,FALSE) -> Project Superintendent (Hrs) | D18: PTO | E18: PERSONAL TIME OFF | K18: 1-019 | L18: Equipment Maint/Repair (Hrs)
B19: 1-001 | C19: =VLOOKUP(B19,'Job Details'!$K:$L,2,FALSE) -> Project Superintendent (Hrs) | D19: RT | E19: Regular Time - Jobs | K19: 1-110 | L19: Safety Training (Hrs)
B20: 1-001 | C20: =VLOOKUP(B20,'Job Details'!$K:$L,2,FALSE) -> Project Superintendent (Hrs) | D20: TRL | E20: Training Labor | K20: 1-200 | L20: Wilson Per Diem
B21: 1-001 | C21: =VLOOKUP(B21,'Job Details'!$K:$L,2,FALSE) -> Project Superintendent (Hrs) | D21: TRP | E21: Training Per Diem | K21: 2-000 | L21: NON-PRODUCTION
B22: 1-002 | C22: =VLOOKUP(B22,'Job Details'!$K:$L,2,FALSE) -> General Foreman (Hrs) | D22: DT | E22: Double Time - Jobs | K22: 2-110 | L22: Safety Training (Hrs)
... B40: 1-005 | C40: =VLOOKUP(B40,'Job Details'!$K:$L,2,FALSE) -> Office (Hrs) | D40: PP | E40: Premium Pay | K40: 990-900 | L40: Accrued Revenue
B41: 1-005 | C41: =VLOOKUP(B41,'Job Details'!$K:$L,2,FALSE) -> Office (Hrs) | D41: PRT | E41: Payroll Taxes-Jobs
B42: 1-005 | C42: =VLOOKUP(B42,'Job Details'!$K:$L,2,FALSE) -> Office (Hrs) | D42: PTO | E42: PERSONAL TIME OFF
B43: 1-005 | C43: =VLOOKUP(B43,'Job Details'!$K:$L,2,FALSE) -> Office (Hrs) | D43: RT | E43: Regular Time - Jobs
B44: 1-005 | C44: =VLOOKUP(B44,'Job Details'!$K:$L,2,FALSE) -> Office (Hrs) | D44: TRL | E44: Training Labor
B45: 1-005 | C45: =VLOOKUP(B45,'Job Details'!$K:$L,2,FALSE) -> Office (Hrs) | D45: TRP | E45: Training Per Diem
B46: 1-007 | C46: =VLOOKUP(B46,'Job Details'!$K:$L,2,FALSE) -> Environmental Costs (Hrs) | D46: 2.0 | E46: Material - Jobs
B47: 1-007 | C47: =VLOOKUP(B47,'Job Details'!$K:$L,2,FALSE) -> Environmental Costs (Hrs) | D47: 401 | E47: 401(k) Employer Contribution
B48: 1-007 | C48: =VLOOKUP(B48,'Job Details'!$K:$L,2,FALSE) -> Environmental Costs (Hrs) | D48: DT | E48: Double Time - Jobs
B49: 1-007 | C49: =VLOOKUP(B49,'Job Details'!$K:$L,2,FALSE) -> Environmental Costs (Hrs) | D49: HP | E49: HOLIDAY PAY
B50: 1-007 | C50: =VLOOKUP(B50,'Job Details'!$K:$L,2,FALSE) -> Environmental Costs (Hrs) | D50: OT | E50: Over Time - Jobs
B51: 1-007 | C51: =VLOOKUP(B51,'Job Details'!$K:$L,2,FALSE) -> Environmental Costs (Hrs) | D51: PD | E51: Per Diem - Jobs
B52: 1-007 | C52: =VLOOKUP(B52,'Job Details'!$K:$L,2,FALSE) -> Environmental Costs (Hrs) | D52: PDS | E52: Per Diem - Supervisors
... B229: 990-900 | C229: =VLOOKUP(B229,'Job Details'!$K:$L,2,FALSE) -> Accrued Revenue | D229: REV | E229: EARNED REVENUE WIP

Sheet Job List
A1: List of Jobs not Closed in Timberline | BB1: 43617
A2: Job | B2: Description | C2: Project Manager | D2: Foreman | E2: Status | F2: Revenue account | G2: Workers' Comp Group | H2: Work state
A3: 2020-00-0 | B3: OVERHEAD COSTS G&A 2020 | C3: DEBBIE GREENE | E3: In progress | H3: OR
A4: 2020-01-0 | B4: WILSON QA/QC OVERHEAD | C4: MARK BRITTON | E4: In progress
A5: 2020-02-0 | B5: INDIRECT COSTS 2020 | C5: JON OISTAD | E5: In progress | G5: 7538OR | H5: OR
A6: 2020-07-0 | B6: BUSINESS DEVELOPMENT | C6: JON OISTAD | E6: In progress
A7: 2020-08-0 | B7: PENNSYLVANIA OFFICE COSTS | C7: AJAY JOSHI | E7: In progress | G7: 8810PA | H7: PA
A8: 2020-20-0 | B8: EQUIPMENT REPAIRS-THIRD PARTY | C8: SCOTT CARR | E8: In progress | F8: 4400 | G8: 8227OR | H8: OR
A9: 2020-27-0 | B9: OVERHEAD PENNSYLVANIA | C9: AJAY JOSHI | E9: In progress | G9: 7538PA | H9: PA
A10: 2020-28-0 | B10: OVERHEAD NEW YORK | C10: JIM KEEGAN | E10: In progress
A11: 2020-58-0 | B11: OVERHEAD MINNESOTA | C11: JON OISTAD | E11: In progress
A12: 2020-70-0 | B12: OVERHEAD CALIFORNIA | C12: DAVE LOWERISON | E12: In progress | G12: 7538CA | H12: CA
A13: 2020-72-0 | B13: OVERHEAD RANCHO OFFICE | C13: TED LEINEKE | E13: In progress | H13: CA
A14: 2020-82-0 | B14: ENVIRONMENTAL OVERHEAD | C14: BRANDON HAWKINS | D14: MATT HOOGE | E14: In progress | G14: 8810 | H14: OR
A15: 2020-82-2 | B15: ENVIRONMENTAL OVERHEAD CA | C15: BRANDON HAWKINS | E15: In progress | G15: 8810CA | H15: CA
A16: 2020-85-0 | B16: OVERHEAD CANADA | E16: In progress
A17: 2020-87-0 | B17: WOODBURN FACILITIES MAINT | C17: TONY HELBLING | E17: In progress | G17: 8227OR | H17: OR
A18: 2020-89-0 | B18: AURORA HANGAR COSTS | C18: STACY WILSON | D18: JUAN AGUILAR | E18: In progress
A19: 2020-90-0 | B19: OVERHEAD COSTS WASHINGTON | C19: BRAD PROCTOR | D19: BRAD FRAZIER | E19: In progress | H19: WA
A20: 2020-91-0 | B20: OVERHEAD COSTS ARIZONA | C20: BRAD PROCTOR | D20: ROD ENDERS | E20: In progress | H20: AZ
A21: 2020-92-0 | B21: OVERHEAD COSTS S. CALIFORNIA | C21: JON OISTAD | D21: DAVE LOWERISON | E21: In progress | G21: 8810CA | H21: CA
A22: 2020-95-0 | B22: COVID-19 PAID LEAVE COSTS | E22: In progress
A23: 2020-99-0 | B23: OVERHEAD ARIZONA GENERAL | C23: PHIL CONNOR | E23: In progress | G23: 5606AZ | H23: AZ
A24: 2021-00-0 | B24: OVERHEAD COSTS G&A 2021 | C24: DEBBIE GREENE | E24: In progress | H24: OR
A25: 2021-01-0 | B25: WILSON QA/QC OVERHEAD 2021 | C25: MARK BRITTON | E25: In progress
A26: 2021-02-0 | B26: INDIRECT COSTS 2021 | C26: JON OISTAD | E26: Unstarted | G26: 7538OR | H26: OR
A27: 2021-06-0 | B27: COUGAR CONSTRUCTION INC | C27: JON OISTAD | E27: In progress | H27: OR
A28: 2021-07-0 | B28: BUSINESS DEVELOPMENT 2021 | C28: JON OISTAD | E28: In progress
A29: 2021-08-0 | B29: PENNSYLVANIA OFFICE COSTS 2021 | C29: AJAY JOSHI | D29: JIM KEEGAN | E29: In progress | G29: 7538PA | H29: PA
A30: 2021-20-0 | B30: EQUIPMENT REPAIRS-THIRD PARTY | C30: SCOTT CARR | D30: STACEY BOSSEN | E30: In progress | F30: 4400 | H30: OR
A31: 2021-27-0 | B31: OVERHEAD PENNSYLVANIA 2021 | C31: AJAY JOSHI | E31: In progress | G31: 7538PA | H31: PA
A32: 2021-28-0 | B32: OVERHEAD NEW YORK 2021 | C32: JIM KEEGAN | D32: AJAY JOSHI | E32: In progress | G32: 7538NY | H32: NY
A33: 2021-58-0 | B33: OVERHEAD MINNESOTA 2021 | C33: JON OISTAD | E33: Unstarted | G33: 7538MN | H33: MN
